{
  "tour_000": {
    "tour_id": "tour_000",
    "index": 0,
    "tour_name": "Mưa Đỏ và Trường Sơn – Hành Trình Khát Vọng (2 ngày 1 đêm)",
    "location": "Thị xã Quảng Trị, Vĩnh Linh, Gio Linh, Hướng hoá (cũ) - Quảng Trị",
    "region": "Miền Trung",
    "tags": [
      "thiền",
      "2_ngày",
      "du_lịch_xanh",
      "lửa_trại",
      "mạo_hiểm",
      "trải_nghiệm",
      "tâm_linh",
      "thanh_niên",
      "lịch_sử",
      "team_building",
      "văn_hóa"
    ],
    "duration": "2 ngày 1 đêm",
    "duration_days": 2,
    "price_text": "1.700.000 – 2.300.000 VNĐ/người",
    "min_price": 1700000,
    "max_price": 2300000,
    "avg_price": 2000000,
    "embedding_text": "Mưa Đỏ và Trường Sơn – Hành Trình Khát Vọng (2 ngày 1 đêm) Hành trình 2 ngày tri ân lịch sử, trải nghiệm văn hoá Vân Kiều – Pa Kô, rèn luyện tinh thần và kết nối nội tâm. Thị xã Quảng Trị, Vĩnh Linh, Gio Linh, Hướng hoá (cũ) - Quảng Trị Hành trình trải nghiệm văn hóa – kết nối cộng đồng – rèn luyện nội tâm; kết hợp giữa khám phá bản sắc Vân Kiều – Pa Kô, hoạt động lửa trại cồng chiêng – đàn Ta Lư, tri ân và hành trình xanh bền vững. Nhịp đi phù hợp đoàn viên thanh niên, học sinh – sinh viên với các hoạt động trẻ trung, gắn kết tập thể, xen kẽ thực hành thiền – khí công cơ bản (tuỳ chọn) giúp cân bằng năng lượng và nuôi dưỡng tinh thần. Đêm lửa trại với cồng chiêng & đàn Ta Lư Trải nghiệm văn hóa Vân Kiều – Pa Kô Hoạt động tri ân & hành trình xanh phát triển bền vững Thực hành thiền – khí công cơ bản - tuỳ chọn Thích hợp đoàn viên thanh niên, học sinh – sinh viên. Lưu ý về trang phục, sức khỏe, an toàn di chuyển; chuẩn bị giấy tờ tùy thân; tuân thủ hướng dẫn của HDV; bảo vệ môi trường tại điểm đến; hạn chế mang đồ công nghệ không cần thiết; có mặt đúng giờ theo lịch trình; một số hoạt động có thể thay đổi tùy điều kiện thời tiết hoặc quy định địa phương 2 ngày 1 đêm 1.700.000 – 2.300.000 VNĐ/người Khách sạn tiêu chuẩn từ 3* hoặc homestay chất lượng tương đương; phòng sạch sẽ, thoáng mát, đầy đủ tiện nghi cơ bản (máy lạnh, nước nóng, vệ sinh riêng). Tiêu chuẩn có thể thay đổi tùy theo gói dịch vụ, địa phương lưu trú và nhu cầu nâng cấp của đoàn ăn 3 bữa chính tiêu chuẩn 150.000 VNĐ/khách (01 bữa tăng cường trong đêm giao lưu tiêu chuẩn 200.000VNĐ/khách), ăn theo thực đơn thống nhất ưu tiên các món đặc sản địa phương  Xe 16-29-35-45 chỗ; Xe đời mới chất lượng cao Hỗ trợ đoàn trong suốt hành trình: theo sát lịch trình – điều phối giờ giấc – hỗ trợ chụp ảnh – ghi nhận nhu cầu cá nhân; kiểm soát an toàn điểm đến; nhắc nhở sức khỏe – trang phục – di chuyển; hỗ trợ xử lý tình huống phát sinh; đồng hành kết nối tập thể; tối ưu trải nghiệm khách hàng theo chuẩn Ruby Wings.",
    "popularity_score": 1.0,
    "value_score": 0.6,
    "family_friendly": false,
    "senior_friendly": false,
    "corporate_friendly": true,
    "summary": "Hành trình 2 ngày tri ân lịch sử, trải nghiệm văn hoá Vân Kiều – Pa Kô, rèn luyện tinh thần và kết nối nội tâm.",
    "style": "Hành trình trải nghiệm văn hóa – kết nối cộng đồng – rèn luyện nội tâm; kết hợp giữa khám phá bản sắc Vân Kiều – Pa Kô, hoạt động lửa trại cồng chiêng – đàn Ta Lư, tri ân và hành trình xanh bền vững. Nhịp đi phù hợp đoàn viên thanh niên, học sinh – sinh viên với các hoạt động trẻ trung, gắn kết tập thể, xen kẽ thực hành thiền – khí công cơ bản (tuỳ chọn) giúp cân bằng năng lượng và nuôi dưỡng tinh thần.",
    "includes": [
      "Đêm lửa trại với cồng chiêng & đàn Ta Lư",
      "Trải nghiệm văn hóa Vân Kiều – Pa Kô",
      "Hoạt động tri ân & hành trình xanh phát triển bền vững",
      "Thực hành thiền – khí công cơ bản - tuỳ chọn"
    ],
    "notes": "Thích hợp đoàn viên thanh niên, học sinh – sinh viên. Lưu ý về trang phục, sức khỏe, an toàn di chuyển; chuẩn bị giấy tờ tùy thân; tuân thủ hướng dẫn của HDV; bảo vệ môi trường tại điểm đến; hạn chế mang đồ công nghệ không cần thiết; có mặt đúng giờ theo lịch trình; một số hoạt động có thể thay đổi tùy điều kiện thời tiết hoặc quy định địa phương",
    "transport": " Xe 16-29-35-45 chỗ; Xe đời mới chất lượng cao",
    "accommodation": "Khách sạn tiêu chuẩn từ 3* hoặc homestay chất lượng tương đương; phòng sạch sẽ, thoáng mát, đầy đủ tiện nghi cơ bản (máy lạnh, nước nóng, vệ sinh riêng). Tiêu chuẩn có thể thay đổi tùy theo gói dịch vụ, địa phương lưu trú và nhu cầu nâng cấp của đoàn",
    "meals": "ăn 3 bữa chính tiêu chuẩn 150.000 VNĐ/khách (01 bữa tăng cường trong đêm giao lưu tiêu chuẩn 200.000VNĐ/khách), ăn theo thực đơn thống nhất ưu tiên các món đặc sản địa phương",
    "event_support": "Hỗ trợ đoàn trong suốt hành trình: theo sát lịch trình – điều phối giờ giấc – hỗ trợ chụp ảnh – ghi nhận nhu cầu cá nhân; kiểm soát an toàn điểm đến; nhắc nhở sức khỏe – trang phục – di chuyển; hỗ trợ xử lý tình huống phát sinh; đồng hành kết nối tập thể; tối ưu trải nghiệm khách hàng theo chuẩn Ruby Wings.",
    "created_at": "2026-01-16T09:07:10.067776Z",
    "last_updated": "2026-01-16T09:07:10.067776Z"
  },
  "tour_001": {
    "tour_id": "tour_001",
    "index": 1,
    "tour_name": "Non nước Bạch Mã – Một ngày giữa thiên nhiên",
    "location": "Vườn quốc gia Bạch Mã – xuất phát tại Thành phố Huế",
    "region": "Miền Trung",
    "tags": [
      "thiền",
      "2_ngày",
      "du_lịch_xanh",
      "cao_cấp",
      "retreat",
      "1_ngày",
      "thiên_nhiên",
      "mạo_hiểm",
      "trải_nghiệm",
      "tâm_linh",
      "picnic"
    ],
    "duration": "1 ngày",
    "duration_days": 1,
    "price_text": "Gói cơ bản: 890.000 VNĐ/khách (khi đủ 12 khách). Gói theo đoàn: giá tuỳ nhóm (đã có bảng giá chi tiết). Gói nâng cao & gói cao cấp: giá theo yêu cầu. Tất cả chi phí chi tiết sẽ được cập nhật theo từng thời điểm.",
    "min_price": 623000,
    "max_price": 1157000,
    "avg_price": 890000,
    "embedding_text": "Non nước Bạch Mã – Một ngày giữa thiên nhiên Retreat 1 ngày về với rừng nguyên sinh Bạch Mã dành cho người muốn tĩnh tại, chữa lành và tái tạo năng lượng. Hành trình nhịp chậm, chú trọng cảm nhận, thiền – chánh niệm, suối – núi – rừng và sự kết nối nội tâm. Không chạy theo số lượng điểm đến mà dừng lại để cảm, để lắng và để trở về với chính mình. Vườn quốc gia Bạch Mã – xuất phát tại Thành phố Huế Retreat nhẹ nhàng – lãng mạn – xanh – nhịp đi chậm – chú trọng cảm nhận thiên nhiên và kết nối nội tâm. Không ồn ào – không chạy số lượng – hướng đến chất lượng trải nghiệm. Xe du lịch đời mới (7–16 chỗ) khởi hành từ Huế, phục vụ theo chương trình. Snack nhẹ tại đỉnh Bạch Mã (bánh mì chay và sữa hạt dinh dưỡng). Picnic thuần chay giữa rừng – tiêu chuẩn dinh dưỡng 80.000đ/người. Hướng dẫn viên chuyên môn, giàu trải nghiệm thiền – chánh niệm. Trải nghiệm retreat: chia sẻ chữa lành bằng thiền – thiên nhiên – hơi thở. Thiền chánh niệm bên suối tại Ngũ Hồ; thời gian tĩnh lặng – nghỉ ngơi giữa rừng. Trekking nhẹ lên đỉnh Bạch Mã – ngắm mây núi giao hòa. Tham quan Ngũ Hồ, Thác Đỗ Quyên và các cung đường rừng. Quà tặng tinh thần theo huyền học cổ phương Đông (Kinh Dịch – Bát Trạch – Huyền Không…), cá nhân hóa thông điệp. 01 phục vụ hậu cần khi đủ số lượng 12 khách nhóm xe 16 chỗ. Vé tham quan đầu tiên theo chương trình. Bảo hiểm du lịch – nước uống – nón/mũ du lịch (quà tặng xác định sau). Gói nâng cao (tùy chọn): thêm bữa sáng nhẹ; xe riêng; bộ ảnh máy chuyên dụng; thiền sâu hơn; tư vấn cá nhân hóa. Gói cao cấp retreat riêng (tùy chọn): xe đời mới riêng tư, thực đơn dưỡng sinh, quà cao cấp, thực hành nội tâm chuyên sâu. Hành trình thiên về retreat – thiên nhiên – chánh niệm. Không phù hợp cho trẻ dưới 9 tuổi. Hạn chế thiết bị công nghệ để trải nghiệm sâu. Mang giày thể thao/leo núi, áo khoác nhẹ, quần áo dài. Không xả rác, không bẻ cây, giữ gìn nguyên sơ của Bạch Mã. Cung cấp đầy đủ thông tin khách trước 5 ngày để chuẩn bị hồ sơ. Trường hợp cần tặng quà tinh thần: cung cấp ngày sinh dương lịch (và giờ sinh nếu có). Quy định huỷ: 5–6 ngày: 30%; 3–4 ngày: 50%; 1–2 ngày: 90%; đúng ngày: 100%. 1 ngày Gói cơ bản: 890.000 VNĐ/khách (khi đủ 12 khách). Gói theo đoàn: giá tuỳ nhóm (đã có bảng giá chi tiết). Gói nâng cao & gói cao cấp: giá theo yêu cầu. Tất cả chi phí chi tiết sẽ được cập nhật theo từng thời điểm. Hành trịnh 01 ngày nên không có lưu trú, tuy nhiên nếu bạn muốn nghỉ lại cho chương trình cá nhân, chúng tôi sẽ hỗ trợ cho bạn nơi nghỉ ngơi phù hợp Picnic thuần chay giữa rừng + snack tại đỉnh Bạch Mã. Gói nâng cao/cao cấp có thêm bữa sáng nhẹ và thực đơn dưỡng sinh tuỳ nhu cầu. ['Xe 7 chỗ', 'Xe 16 chỗ', 'Xe 9–16 chỗ riêng cho gói cao cấp', 'Xe 2024–2025 đời mới (tuỳ gói nâng cao/cao cấp)'] Quà tinh thần cá nhân hóa theo huyền học – hỗ trợ HDV & phục vụ đoàn – trải nghiệm thiền mở rộng tuỳ gói nâng cao/cao cấp.",
    "popularity_score": 0.99,
    "value_score": 0.8,
    "family_friendly": false,
    "senior_friendly": false,
    "corporate_friendly": false,
    "summary": "Retreat 1 ngày về với rừng nguyên sinh Bạch Mã dành cho người muốn tĩnh tại, chữa lành và tái tạo năng lượng. Hành trình nhịp chậm, chú trọng cảm nhận, thiền – chánh niệm, suối – núi – rừng và sự kết nối nội tâm. Không chạy theo số lượng điểm đến mà dừng lại để cảm, để lắng và để trở về với chính mình.",
    "style": "Retreat nhẹ nhàng – lãng mạn – xanh – nhịp đi chậm – chú trọng cảm nhận thiên nhiên và kết nối nội tâm. Không ồn ào – không chạy số lượng – hướng đến chất lượng trải nghiệm.",
    "includes": [
      "Xe du lịch đời mới (7–16 chỗ) khởi hành từ Huế, phục vụ theo chương trình.",
      "Snack nhẹ tại đỉnh Bạch Mã (bánh mì chay và sữa hạt dinh dưỡng).",
      "Picnic thuần chay giữa rừng – tiêu chuẩn dinh dưỡng 80.000đ/người.",
      "Hướng dẫn viên chuyên môn, giàu trải nghiệm thiền – chánh niệm.",
      "Trải nghiệm retreat: chia sẻ chữa lành bằng thiền – thiên nhiên – hơi thở.",
      "Thiền chánh niệm bên suối tại Ngũ Hồ; thời gian tĩnh lặng – nghỉ ngơi giữa rừng.",
      "Trekking nhẹ lên đỉnh Bạch Mã – ngắm mây núi giao hòa.",
      "Tham quan Ngũ Hồ, Thác Đỗ Quyên và các cung đường rừng.",
      "Quà tặng tinh thần theo huyền học cổ phương Đông (Kinh Dịch – Bát Trạch – Huyền Không…), cá nhân hóa thông điệp.",
      "01 phục vụ hậu cần khi đủ số lượng 12 khách nhóm xe 16 chỗ.",
      "Vé tham quan đầu tiên theo chương trình.",
      "Bảo hiểm du lịch – nước uống – nón/mũ du lịch (quà tặng xác định sau).",
      "Gói nâng cao (tùy chọn): thêm bữa sáng nhẹ; xe riêng; bộ ảnh máy chuyên dụng; thiền sâu hơn; tư vấn cá nhân hóa.",
      "Gói cao cấp retreat riêng (tùy chọn): xe đời mới riêng tư, thực đơn dưỡng sinh, quà cao cấp, thực hành nội tâm chuyên sâu."
    ],
    "notes": "Hành trình thiên về retreat – thiên nhiên – chánh niệm. Không phù hợp cho trẻ dưới 9 tuổi. Hạn chế thiết bị công nghệ để trải nghiệm sâu. Mang giày thể thao/leo núi, áo khoác nhẹ, quần áo dài. Không xả rác, không bẻ cây, giữ gìn nguyên sơ của Bạch Mã. Cung cấp đầy đủ thông tin khách trước 5 ngày để chuẩn bị hồ sơ. Trường hợp cần tặng quà tinh thần: cung cấp ngày sinh dương lịch (và giờ sinh nếu có). Quy định huỷ: 5–6 ngày: 30%; 3–4 ngày: 50%; 1–2 ngày: 90%; đúng ngày: 100%.",
    "transport": [
      "Xe 7 chỗ",
      "Xe 16 chỗ",
      "Xe 9–16 chỗ riêng cho gói cao cấp",
      "Xe 2024–2025 đời mới (tuỳ gói nâng cao/cao cấp)"
    ],
    "accommodation": "Hành trịnh 01 ngày nên không có lưu trú, tuy nhiên nếu bạn muốn nghỉ lại cho chương trình cá nhân, chúng tôi sẽ hỗ trợ cho bạn nơi nghỉ ngơi phù hợp",
    "meals": "Picnic thuần chay giữa rừng + snack tại đỉnh Bạch Mã. Gói nâng cao/cao cấp có thêm bữa sáng nhẹ và thực đơn dưỡng sinh tuỳ nhu cầu.",
    "event_support": "Quà tinh thần cá nhân hóa theo huyền học – hỗ trợ HDV & phục vụ đoàn – trải nghiệm thiền mở rộng tuỳ gói nâng cao/cao cấp.",
    "created_at": "2026-01-16T09:07:10.067776Z",
    "last_updated": "2026-01-16T09:07:10.067776Z"
  },
  "tour_002": {
    "tour_id": "tour_002",
    "index": 2,
    "tour_name": "Mưa Đỏ và Trường Sơn – Hành Trình Khát Vọng-(2 ngày 1 đêm) ",
    "location": "Tây Trường Sơn – Quảng Trị",
    "region": "Miền Trung",
    "tags": [
      "thiền",
      "2_ngày",
      "du_lịch_xanh",
      "lửa_trại",
      "trải_nghiệm",
      "tâm_linh",
      "lịch_sử",
      "văn_hóa"
    ],
    "duration": "2 ngày 1 đêm",
    "duration_days": 2,
    "price_text": "1.500.000 – 2.200.000 VNĐ/người (Tùy lựa chọn dịch vụ)",
    "min_price": 1500000,
    "max_price": 2200000,
    "avg_price": 1850000,
    "embedding_text": "Mưa Đỏ và Trường Sơn – Hành Trình Khát Vọng-(2 ngày 1 đêm)  Hành trình 2 ngày tri ân, trải nghiệm văn hóa Vân Kiều – Pa Kô, nghe nhân chứng lịch sử, rèn sức – dưỡng tâm qua thiền và khí công, cùng hoạt động tri ân – phát triển bền vững. Tây Trường Sơn – Quảng Trị Tìm về nguồn cội – rèn luyện thể chất – tinh thần – lắng nghe nội tâm – nuôi dưỡng lòng biết ơn và khát vọng sống đẹp Giao lưu Cựu chiến binh – nhân chứng lịch sử - tuỳ chọn Đêm lửa trại 'Ngọn lửa Trường Sơn' với cồng chiêng và đàn Ta Lư Hoạt động tri ân tại Nghĩa trang Liệt sĩ Hoạt động 'Hành trình xanh' – giáo dục bảo vệ môi trường Thiền – khí công rèn sức – dưỡng tâm Khơi dậy nội lực và tinh thần sống đẹp Ngày 1: Đông Hà – Vĩ tuyến 17 – Hướng Hóa (Ăn: sáng, trưa, tối), khởi hành – tham quan – nhận phòng – sinh hoạt nhóm, buổi tối lửa trại và giao lưu văn hóa Ngày 2: Hướng Hóa – Nghĩa trang Liệt sĩ Trường Sơn – Đông Hà (Ăn: sáng, trưa, tối), viếng nghĩa trang – tri ân – kết thúc chương trình Lưu ý về trang phục, sức khỏe, an toàn di chuyển; chuẩn bị giấy tờ tùy thân; tuân thủ hướng dẫn của HDV; bảo vệ môi trường tại điểm đến; hạn chế mang đồ công nghệ không cần thiết; có mặt đúng giờ theo lịch trình; một số hoạt động có thể thay đổi tùy điều kiện thời tiết hoặc quy định địa phương 2 ngày 1 đêm 1.500.000 – 2.200.000 VNĐ/người (Tùy lựa chọn dịch vụ) ['1 đêm homestay/nhà khách cộng đồng tại Khe Sanh/Hướng Hóa'] ăn 3 bữa chính tiêu chuẩn 150.000 VNĐ/khách (01 bữa tăng cường trong đêm giao lưu tiêu chuẩn 200.000VNĐ/khách), ăn theo thực đơn thống nhất ưu tiên các món đặc sản địa phương Xe 16-29-35-45 chỗ; Xe đời mới chất lượng cao Hỗ trợ đoàn trong suốt hành trình: theo sát lịch trình – điều phối giờ giấc – hỗ trợ chụp ảnh – ghi nhận nhu cầu cá nhân; kiểm soát an toàn điểm đến; nhắc nhở sức khỏe – trang phục – di chuyển; hỗ trợ xử lý tình huống phát sinh; đồng hành kết nối tập thể; tối ưu trải nghiệm khách hàng theo chuẩn Ruby Wings.",
    "popularity_score": 0.98,
    "value_score": 0.8,
    "family_friendly": false,
    "senior_friendly": true,
    "corporate_friendly": false,
    "summary": "Hành trình 2 ngày tri ân, trải nghiệm văn hóa Vân Kiều – Pa Kô, nghe nhân chứng lịch sử, rèn sức – dưỡng tâm qua thiền và khí công, cùng hoạt động tri ân – phát triển bền vững.",
    "style": "Tìm về nguồn cội – rèn luyện thể chất – tinh thần – lắng nghe nội tâm – nuôi dưỡng lòng biết ơn và khát vọng sống đẹp",
    "includes": [
      "Giao lưu Cựu chiến binh – nhân chứng lịch sử - tuỳ chọn",
      "Đêm lửa trại 'Ngọn lửa Trường Sơn' với cồng chiêng và đàn Ta Lư",
      "Hoạt động tri ân tại Nghĩa trang Liệt sĩ",
      "Hoạt động 'Hành trình xanh' – giáo dục bảo vệ môi trường",
      "Thiền – khí công rèn sức – dưỡng tâm",
      "Khơi dậy nội lực và tinh thần sống đẹp",
      "Ngày 1: Đông Hà – Vĩ tuyến 17 – Hướng Hóa (Ăn: sáng, trưa, tối), khởi hành – tham quan – nhận phòng – sinh hoạt nhóm, buổi tối lửa trại và giao lưu văn hóa",
      "Ngày 2: Hướng Hóa – Nghĩa trang Liệt sĩ Trường Sơn – Đông Hà (Ăn: sáng, trưa, tối), viếng nghĩa trang – tri ân – kết thúc chương trình"
    ],
    "notes": "Lưu ý về trang phục, sức khỏe, an toàn di chuyển; chuẩn bị giấy tờ tùy thân; tuân thủ hướng dẫn của HDV; bảo vệ môi trường tại điểm đến; hạn chế mang đồ công nghệ không cần thiết; có mặt đúng giờ theo lịch trình; một số hoạt động có thể thay đổi tùy điều kiện thời tiết hoặc quy định địa phương",
    "transport": "Xe 16-29-35-45 chỗ; Xe đời mới chất lượng cao",
    "accommodation": [
      "1 đêm homestay/nhà khách cộng đồng tại Khe Sanh/Hướng Hóa"
    ],
    "meals": "ăn 3 bữa chính tiêu chuẩn 150.000 VNĐ/khách (01 bữa tăng cường trong đêm giao lưu tiêu chuẩn 200.000VNĐ/khách), ăn theo thực đơn thống nhất ưu tiên các món đặc sản địa phương",
    "event_support": "Hỗ trợ đoàn trong suốt hành trình: theo sát lịch trình – điều phối giờ giấc – hỗ trợ chụp ảnh – ghi nhận nhu cầu cá nhân; kiểm soát an toàn điểm đến; nhắc nhở sức khỏe – trang phục – di chuyển; hỗ trợ xử lý tình huống phát sinh; đồng hành kết nối tập thể; tối ưu trải nghiệm khách hàng theo chuẩn Ruby Wings.",
    "created_at": "2026-01-16T09:07:10.067776Z",
    "last_updated": "2026-01-16T09:07:10.067776Z"
  },
  "tour_003": {
    "tour_id": "tour_003",
    "index": 3,
    "tour_name": "Ký ức – Lịch Sử và Đại Ngàn – Tĩnh Lặng (2 ngày 1 đêm)",
    "location": "Quảng Trị – Huế – Bạch Mã",
    "region": "Miền Trung",
    "tags": [
      "thiền",
      "2_ngày",
      "du_lịch_xanh",
      "thiên_nhiên",
      "trải_nghiệm",
      "tâm_linh",
      "lịch_sử"
    ],
    "duration": "2 ngày 1 đêm",
    "duration_days": 2,
    "price_text": "Bảng giá theo số lượng (nghìn VNĐ/người): 10-12: 3500; 12-13: 2800; 14-18: 2950; 19-21: 2500; 22-24: 2365; 25-27: 2290; 28-30: 2200; 31-33: 2190; 34-36: 2100; 37-39: 2050",
    "min_price": 2050,
    "max_price": 3500,
    "avg_price": 2775,
    "embedding_text": "Ký ức – Lịch Sử và Đại Ngàn – Tĩnh Lặng (2 ngày 1 đêm) Hành trình 2 ngày trở về ký ức lịch sử, lắng nghe thuyết minh chuyên sâu, thực hành thiền – khí công giữa đại ngàn Bạch Mã và tham dự nghi lễ tri ân tại Thành cổ Quảng Trị. Quảng Trị – Huế – Bạch Mã Kết nối quá khứ – hiện tại – lịch sử – đời sống – con người – thiên nhiên; mang đến năng lượng mới và sự an yên nội tâm. Nghe những câu chuyện lịch sử chân thực từ hướng dẫn viên chuyên sâu Tham dự nghi lễ tưởng niệm tại Thành cổ Quảng Trị Trải nghiệm thiền – khí công giữa đại ngàn Bạch Mã Hành trình tri ân kết hợp phát triển bền vững Kết nối quá khứ – hiện tại, nuôi dưỡng năng lượng tích cực Ngày 1: Khe Sanh – Thành cổ Quảng Trị – Huế (Ăn: sáng, trưa, tối), tham quan – nghe thuyết minh – sinh hoạt nhóm Ngày 2: Thành phố Huế – Bạch Mã – Hướng Hóa (Ăn: sáng, trưa, …), thiền – khí công – viếng di tích – kết thúc hành trình Lưu ý về trang phục, sức khỏe, an toàn di chuyển; chuẩn bị giấy tờ tùy thân; tuân thủ hướng dẫn của HDV; bảo vệ môi trường tại điểm đến; hạn chế mang đồ công nghệ không cần thiết; có mặt đúng giờ theo lịch trình; một số hoạt động có thể thay đổi tùy điều kiện thời tiết hoặc quy định địa phương 2 ngày 1 đêm Bảng giá theo số lượng (nghìn VNĐ/người): 10-12: 3500; 12-13: 2800; 14-18: 2950; 19-21: 2500; 22-24: 2365; 25-27: 2290; 28-30: 2200; 31-33: 2190; 34-36: 2100; 37-39: 2050 1 đêm khách sạn từ 3* (hoặc  homestay chất lượng tương đương) tại Thành phố Huế  ăn 3 bữa chính tiêu chuẩn 150.000 VNĐ/khách (01 bữa tăng cường trong đêm giao lưu tiêu chuẩn 200.000VNĐ/khách), ăn theo thực đơn thống nhất ưu tiên các món đặc sản địa phương ['Xe 16 chỗ', 'Xe 29 chỗ', 'Xe 35 chỗ', 'Xe 45 chỗ'] Hỗ trợ đoàn trong suốt hành trình: theo sát lịch trình – điều phối giờ giấc – hỗ trợ chụp ảnh – ghi nhận nhu cầu cá nhân; kiểm soát an toàn điểm đến; nhắc nhở sức khỏe – trang phục – di chuyển; hỗ trợ xử lý tình huống phát sinh; đồng hành kết nối tập thể; tối ưu trải nghiệm khách hàng theo chuẩn Ruby Wings",
    "popularity_score": 0.97,
    "value_score": 0.8,
    "family_friendly": false,
    "senior_friendly": true,
    "corporate_friendly": false,
    "summary": "Hành trình 2 ngày trở về ký ức lịch sử, lắng nghe thuyết minh chuyên sâu, thực hành thiền – khí công giữa đại ngàn Bạch Mã và tham dự nghi lễ tri ân tại Thành cổ Quảng Trị.",
    "style": "Kết nối quá khứ – hiện tại – lịch sử – đời sống – con người – thiên nhiên; mang đến năng lượng mới và sự an yên nội tâm.",
    "includes": [
      "Nghe những câu chuyện lịch sử chân thực từ hướng dẫn viên chuyên sâu",
      "Tham dự nghi lễ tưởng niệm tại Thành cổ Quảng Trị",
      "Trải nghiệm thiền – khí công giữa đại ngàn Bạch Mã",
      "Hành trình tri ân kết hợp phát triển bền vững",
      "Kết nối quá khứ – hiện tại, nuôi dưỡng năng lượng tích cực",
      "Ngày 1: Khe Sanh – Thành cổ Quảng Trị – Huế (Ăn: sáng, trưa, tối), tham quan – nghe thuyết minh – sinh hoạt nhóm",
      "Ngày 2: Thành phố Huế – Bạch Mã – Hướng Hóa (Ăn: sáng, trưa, …), thiền – khí công – viếng di tích – kết thúc hành trình"
    ],
    "notes": "Lưu ý về trang phục, sức khỏe, an toàn di chuyển; chuẩn bị giấy tờ tùy thân; tuân thủ hướng dẫn của HDV; bảo vệ môi trường tại điểm đến; hạn chế mang đồ công nghệ không cần thiết; có mặt đúng giờ theo lịch trình; một số hoạt động có thể thay đổi tùy điều kiện thời tiết hoặc quy định địa phương",
    "transport": [
      "Xe 16 chỗ",
      "Xe 29 chỗ",
      "Xe 35 chỗ",
      "Xe 45 chỗ"
    ],
    "accommodation": "1 đêm khách sạn từ 3* (hoặc  homestay chất lượng tương đương) tại Thành phố Huế ",
    "meals": "ăn 3 bữa chính tiêu chuẩn 150.000 VNĐ/khách (01 bữa tăng cường trong đêm giao lưu tiêu chuẩn 200.000VNĐ/khách), ăn theo thực đơn thống nhất ưu tiên các món đặc sản địa phương",
    "event_support": "Hỗ trợ đoàn trong suốt hành trình: theo sát lịch trình – điều phối giờ giấc – hỗ trợ chụp ảnh – ghi nhận nhu cầu cá nhân; kiểm soát an toàn điểm đến; nhắc nhở sức khỏe – trang phục – di chuyển; hỗ trợ xử lý tình huống phát sinh; đồng hành kết nối tập thể; tối ưu trải nghiệm khách hàng theo chuẩn Ruby Wings",
    "created_at": "2026-01-16T09:07:10.067776Z",
    "last_updated": "2026-01-16T09:07:10.067776Z"
  },
  "tour_004": {
    "tour_id": "tour_004",
    "index": 4,
    "tour_name": "Mưa Đỏ và Đôi bờ Hiền Lương",
    "location": "Quảng Trị – Thành Cổ – Hiền Lương",
    "region": "Miền Trung",
    "tags": [
      "trải_nghiệm",
      "1_ngày",
      "lịch_sử",
      "du_lịch_xanh"
    ],
    "duration": "1 ngày",
    "duration_days": 1,
    "price_text": "Bảng giá theo số lượng (nghìn VNĐ/người): 10-12: 1250–1395; 12-13: 1130–1270; 14-16: 1170–1300; 17-19: 1060–1185; 20-22: 985–1095; 23-25: 930–1035; 26-28: 950–1060; 29-31: 905–1015; 32-34: 925–1033; 35-37: 895–997; 38-40: 870–967",
    "min_price": 1015,
    "max_price": 1395,
    "avg_price": 1205,
    "embedding_text": "Mưa Đỏ và Đôi bờ Hiền Lương Hành trình 1 ngày kết nối quá khứ – hiện tại, nghe câu chuyện lịch sử từ nhân chứng sống, thực hiện nghi lễ tri ân và trải nghiệm giá trị sâu sắc trên mảnh đất Quảng Trị thiêng liêng. Quảng Trị – Thành Cổ – Hiền Lương Hòa quyện lịch sử – trải nghiệm – cảm xúc; kết nối ký ức và thức tỉnh giá trị sống. Nghe câu chuyện lịch sử từ HDV chuyên sâu và cựu chiến binh Nghi lễ tưởng niệm tại Thành Cổ Quảng Trị Viếng Nghĩa trang Liệt sĩ Quốc gia Trường Sơn Trải nghiệm giá trị – cảm xúc, không chạy theo check-in Khơi dậy lòng biết ơn và sự tự hào của thế hệ trẻ Ngày 1: Huế – Thành Cổ – Quảng Trị (Ăn sáng, trưa, tối) Lưu ý về trang phục, sức khỏe, an toàn di chuyển; chuẩn bị giấy tờ tùy thân; tuân thủ hướng dẫn của HDV; bảo vệ môi trường tại điểm đến; hạn chế mang đồ công nghệ không cần thiết; có mặt đúng giờ theo lịch trình; một số hoạt động có thể thay đổi tùy điều kiện thời tiết hoặc quy định địa phương 1 ngày Bảng giá theo số lượng (nghìn VNĐ/người): 10-12: 1250–1395; 12-13: 1130–1270; 14-16: 1170–1300; 17-19: 1060–1185; 20-22: 985–1095; 23-25: 930–1035; 26-28: 950–1060; 29-31: 905–1015; 32-34: 925–1033; 35-37: 895–997; 38-40: 870–967  Xe 16-29-35-45 chỗ; Xe đời mới chất lượng cao ăn 02 bữa chính tiêu chuẩn 150.000 VNĐ/khách, ăn theo thực đơn thống nhất ưu tiên các món đặc sản địa phương ['Xe 16 chỗ', 'Xe 29 chỗ', 'Xe 35 chỗ', 'Xe 45 chỗ'] Hỗ trợ đoàn trong suốt hành trình: theo sát lịch trình – điều phối giờ giấc – hỗ trợ chụp ảnh – ghi nhận nhu cầu cá nhân; kiểm soát an toàn điểm đến; nhắc nhở sức khỏe – trang phục – di chuyển; hỗ trợ xử lý tình huống phát sinh; đồng hành kết nối tập thể; tối ưu trải nghiệm khách hàng theo chuẩn Ruby Wings.",
    "popularity_score": 0.96,
    "value_score": 0.8,
    "family_friendly": false,
    "senior_friendly": true,
    "corporate_friendly": false,
    "summary": "Hành trình 1 ngày kết nối quá khứ – hiện tại, nghe câu chuyện lịch sử từ nhân chứng sống, thực hiện nghi lễ tri ân và trải nghiệm giá trị sâu sắc trên mảnh đất Quảng Trị thiêng liêng.",
    "style": "Hòa quyện lịch sử – trải nghiệm – cảm xúc; kết nối ký ức và thức tỉnh giá trị sống.",
    "includes": [
      "Nghe câu chuyện lịch sử từ HDV chuyên sâu và cựu chiến binh",
      "Nghi lễ tưởng niệm tại Thành Cổ Quảng Trị",
      "Viếng Nghĩa trang Liệt sĩ Quốc gia Trường Sơn",
      "Trải nghiệm giá trị – cảm xúc, không chạy theo check-in",
      "Khơi dậy lòng biết ơn và sự tự hào của thế hệ trẻ",
      "Ngày 1: Huế – Thành Cổ – Quảng Trị (Ăn sáng, trưa, tối)"
    ],
    "notes": "Lưu ý về trang phục, sức khỏe, an toàn di chuyển; chuẩn bị giấy tờ tùy thân; tuân thủ hướng dẫn của HDV; bảo vệ môi trường tại điểm đến; hạn chế mang đồ công nghệ không cần thiết; có mặt đúng giờ theo lịch trình; một số hoạt động có thể thay đổi tùy điều kiện thời tiết hoặc quy định địa phương",
    "transport": [
      "Xe 16 chỗ",
      "Xe 29 chỗ",
      "Xe 35 chỗ",
      "Xe 45 chỗ"
    ],
    "accommodation": " Xe 16-29-35-45 chỗ; Xe đời mới chất lượng cao",
    "meals": "ăn 02 bữa chính tiêu chuẩn 150.000 VNĐ/khách, ăn theo thực đơn thống nhất ưu tiên các món đặc sản địa phương",
    "event_support": "Hỗ trợ đoàn trong suốt hành trình: theo sát lịch trình – điều phối giờ giấc – hỗ trợ chụp ảnh – ghi nhận nhu cầu cá nhân; kiểm soát an toàn điểm đến; nhắc nhở sức khỏe – trang phục – di chuyển; hỗ trợ xử lý tình huống phát sinh; đồng hành kết nối tập thể; tối ưu trải nghiệm khách hàng theo chuẩn Ruby Wings.",
    "created_at": "2026-01-16T09:07:10.067776Z",
    "last_updated": "2026-01-16T09:07:10.067776Z"
  },
  "tour_005": {
    "tour_id": "tour_005",
    "index": 5,
    "tour_name": "Ngọn Lửa Trường Sơn – Ký ức và Khát vọng (2 ngày 1 đêm)",
    "location": "Quảng Trị – Hướng Hóa – Trường Sơn – Huế",
    "region": "Miền Trung",
    "tags": [
      "thiền",
      "2_ngày",
      "du_lịch_xanh",
      "lửa_trại",
      "retreat",
      "thiên_nhiên",
      "trải_nghiệm",
      "tâm_linh",
      "lịch_sử",
      "văn_hóa"
    ],
    "duration": "2 ngày 1 đêm",
    "duration_days": 2,
    "price_text": "Bảng giá theo số lượng (nghìn VNĐ/người): 10-12: 3850; 12-13: 3450; 14-18: 3250; 19-21: 2830; 22-24: 2630; 25-27: 2460; 28-30: 2390; 31-33: 2290; 34-36: 2180; 37-39: 2090",
    "min_price": 2090,
    "max_price": 3850,
    "avg_price": 2970,
    "embedding_text": "Ngọn Lửa Trường Sơn – Ký ức và Khát vọng (2 ngày 1 đêm) Hành trình 2 ngày 1 đêm tại Quảng Trị, kết nối ký ức – hiện tại qua giao lưu Cựu chiến binh, đêm lửa trại Trường Sơn, thiền – khí công, hoạt động tri ân và phát triển bền vững. Quảng Trị – Hướng Hóa – Trường Sơn – Huế Kết hợp tĩnh tại – năng động; rèn luyện thể chất – tinh thần; hoạt động đội nhóm và kết nối lịch sử – văn hóa. Giao lưu với Cựu chiến binh – nhân chứng lịch sử - Tuỳ chọn Đêm lửa trại 'Ngọn lửa Trường Sơn' với cồng chiêng và đàn Ta Lư Hoạt động tri ân tại Nghĩa trang Liệt sĩ Trường Sơn Hành trình xanh – giáo dục bảo vệ môi trường Thiền – khí công cơ bản, học phương pháp sống khỏe từ thiên nhiên Hoạt động đội nhóm tạo giá trị – kết nối cộng đồng Bác sĩ – chuyên viên y tế đồng hành Ngày 1: Huế – Nghĩa trang Liệt sĩ Trường Sơn – Hướng Hóa (Ăn sáng, trưa, tối) Ngày 2: Hướng Hóa – Quảng Trị – Huế (Ăn sáng, trưa, ...) Lưu ý về trang phục, sức khỏe, an toàn di chuyển; chuẩn bị giấy tờ tùy thân; tuân thủ hướng dẫn của HDV; bảo vệ môi trường tại điểm đến; hạn chế mang đồ công nghệ không cần thiết; có mặt đúng giờ theo lịch trình; một số hoạt động có thể thay đổi tùy điều kiện thời tiết hoặc quy định địa phương 2 ngày 1 đêm Bảng giá theo số lượng (nghìn VNĐ/người): 10-12: 3850; 12-13: 3450; 14-18: 3250; 19-21: 2830; 22-24: 2630; 25-27: 2460; 28-30: 2390; 31-33: 2290; 34-36: 2180; 37-39: 2090 1 đêm khách sạn 3* tại Thị xã Quảng Trị (hoặc thành phố Đông Hà) 1 đêm homestay/nhà khách cộng đồng tại Khe Sanh/Hướng Hóa ăn 3 bữa chính tiêu chuẩn 150.000 VNĐ/khách (01 bữa tăng cường trong đêm giao lưu tiêu chuẩn 200.000VNĐ/khách), ăn theo thực đơn thống nhất ưu tiên các món đặc sản địa phương ['Xe từ 16 chỗ đến 45 chỗ tuỳ số lượng khách, bảo đảm xe đời mới, chất lượng cao', 'Xe 16 chỗ', 'Xe 29 chỗ', 'Xe 35 chỗ', 'Xe 45 chỗ'] Hỗ trợ đoàn trong suốt hành trình: theo sát lịch trình – điều phối giờ giấc – hỗ trợ chụp ảnh – ghi nhận nhu cầu cá nhân; kiểm soát an toàn điểm đến; nhắc nhở sức khỏe – trang phục – di chuyển; hỗ trợ xử lý tình huống phát sinh; đồng hành kết nối tập thể; tối ưu trải nghiệm khách hàng theo chuẩn Ruby Wings.",
    "popularity_score": 0.95,
    "value_score": 0.8,
    "family_friendly": false,
    "senior_friendly": true,
    "corporate_friendly": false,
    "summary": "Hành trình 2 ngày 1 đêm tại Quảng Trị, kết nối ký ức – hiện tại qua giao lưu Cựu chiến binh, đêm lửa trại Trường Sơn, thiền – khí công, hoạt động tri ân và phát triển bền vững.",
    "style": "Kết hợp tĩnh tại – năng động; rèn luyện thể chất – tinh thần; hoạt động đội nhóm và kết nối lịch sử – văn hóa.",
    "includes": [
      "Giao lưu với Cựu chiến binh – nhân chứng lịch sử - Tuỳ chọn",
      "Đêm lửa trại 'Ngọn lửa Trường Sơn' với cồng chiêng và đàn Ta Lư",
      "Hoạt động tri ân tại Nghĩa trang Liệt sĩ Trường Sơn",
      "Hành trình xanh – giáo dục bảo vệ môi trường",
      "Thiền – khí công cơ bản, học phương pháp sống khỏe từ thiên nhiên",
      "Hoạt động đội nhóm tạo giá trị – kết nối cộng đồng",
      "Bác sĩ – chuyên viên y tế đồng hành",
      "Ngày 1: Huế – Nghĩa trang Liệt sĩ Trường Sơn – Hướng Hóa (Ăn sáng, trưa, tối)",
      "Ngày 2: Hướng Hóa – Quảng Trị – Huế (Ăn sáng, trưa, ...)"
    ],
    "notes": "Lưu ý về trang phục, sức khỏe, an toàn di chuyển; chuẩn bị giấy tờ tùy thân; tuân thủ hướng dẫn của HDV; bảo vệ môi trường tại điểm đến; hạn chế mang đồ công nghệ không cần thiết; có mặt đúng giờ theo lịch trình; một số hoạt động có thể thay đổi tùy điều kiện thời tiết hoặc quy định địa phương",
    "transport": [
      "Xe từ 16 chỗ đến 45 chỗ tuỳ số lượng khách, bảo đảm xe đời mới, chất lượng cao",
      "Xe 16 chỗ",
      "Xe 29 chỗ",
      "Xe 35 chỗ",
      "Xe 45 chỗ"
    ],
    "accommodation": "1 đêm khách sạn 3* tại Thị xã Quảng Trị (hoặc thành phố Đông Hà) 1 đêm homestay/nhà khách cộng đồng tại Khe Sanh/Hướng Hóa",
    "meals": "ăn 3 bữa chính tiêu chuẩn 150.000 VNĐ/khách (01 bữa tăng cường trong đêm giao lưu tiêu chuẩn 200.000VNĐ/khách), ăn theo thực đơn thống nhất ưu tiên các món đặc sản địa phương",
    "event_support": "Hỗ trợ đoàn trong suốt hành trình: theo sát lịch trình – điều phối giờ giấc – hỗ trợ chụp ảnh – ghi nhận nhu cầu cá nhân; kiểm soát an toàn điểm đến; nhắc nhở sức khỏe – trang phục – di chuyển; hỗ trợ xử lý tình huống phát sinh; đồng hành kết nối tập thể; tối ưu trải nghiệm khách hàng theo chuẩn Ruby Wings.",
    "created_at": "2026-01-16T09:07:10.067776Z",
    "last_updated": "2026-01-16T09:07:10.067776Z"
  },
  "tour_006": {
    "tour_id": "tour_006",
    "index": 6,
    "tour_name": "Mưa Đỏ và Tây Trường Sơn (2 ngày 1 đêm)",
    "location": "Tây Trường Sơn – Quảng Trị – Hướng Hóa",
    "region": "Miền Trung",
    "tags": [
      "thiền",
      "2_ngày",
      "du_lịch_xanh",
      "lửa_trại",
      "retreat",
      "thiên_nhiên",
      "trải_nghiệm",
      "tâm_linh",
      "lịch_sử",
      "văn_hóa"
    ],
    "duration": "2 ngày 1 đêm",
    "duration_days": 2,
    "price_text": "1.500.000 – 2.500.000 VNĐ/người (Tùy lựa chọn dịch vụ – phương tiện – số lượng đoàn)",
    "min_price": 1500000,
    "max_price": 2500000,
    "avg_price": 2000000,
    "embedding_text": "Mưa Đỏ và Tây Trường Sơn (2 ngày 1 đêm) Hành trình 2 ngày 1 đêm kết nối lịch sử Mưa Đỏ, văn hoá bản địa Tây Trường Sơn và không gian retreat tĩnh lặng giữa đại ngàn – mang lại cảm hứng sống đẹp và năng lượng tích cực. Tây Trường Sơn – Quảng Trị – Hướng Hóa Lịch sử – văn hoá bản địa – retreat thiên nhiên; kết nối cảm xúc – nuôi dưỡng năng lượng – lan toả giá trị sống. Gặp gỡ và nghe chuyện từ Cựu chiến binh – nhân chứng lịch sử Đêm lửa trại 'Ngọn lửa Trường Sơn' với cồng chiêng – đàn Ta Lư Nghi lễ tưởng niệm tại Nghĩa trang Liệt sĩ Quốc gia Trường Sơn Thiền – khí công giữa thiên nhiên Tây Trường Sơn Trải nghiệm văn hoá bản địa Vân Kiều – Pa Kô Được đồng hành bởi chuyên viên y tế suốt tuyến Ngày 1: Huế – Thành Cổ – Nghĩa trang Liệt sĩ Trường Sơn – Hướng Hóa (Ăn sáng, trưa, tối) Ngày 2: Hướng Hóa – Quảng Trị – Huế (Ăn sáng, trưa, ...) Lưu ý về trang phục, sức khỏe, an toàn di chuyển; chuẩn bị giấy tờ tùy thân; tuân thủ hướng dẫn của HDV; bảo vệ môi trường tại điểm đến; hạn chế mang đồ công nghệ không cần thiết; có mặt đúng giờ theo lịch trình; một số hoạt động có thể thay đổi tùy điều kiện thời tiết hoặc quy định địa phương 2 ngày 1 đêm 1.500.000 – 2.500.000 VNĐ/người (Tùy lựa chọn dịch vụ – phương tiện – số lượng đoàn) Khách sạn tiêu chuẩn từ 3* hoặc homestay chất lượng tương đương; phòng sạch sẽ, thoáng mát, đầy đủ tiện nghi cơ bản (máy lạnh, nước nóng, vệ sinh riêng). Tiêu chuẩn có thể thay đổi tùy theo gói dịch vụ, địa phương lưu trú và nhu cầu nâng cấp của đoàn ăn 3 bữa chính tiêu chuẩn 150.000 VNĐ/khách (01 bữa tăng cường trong đêm giao lưu tiêu chuẩn 200.000VNĐ/khách), ăn theo thực đơn thống nhất ưu tiên các món đặc sản địa phương, nước uống suốt hành trình Xe từ 16 chỗ đến 45 chỗ tuỳ số lượng khách, bảo đảm xe đời mới, chất lượng cao Hỗ trợ đoàn trong suốt hành trình: theo sát lịch trình – điều phối giờ giấc – hỗ trợ chụp ảnh – ghi nhận nhu cầu cá nhân; kiểm soát an toàn điểm đến; nhắc nhở sức khỏe – trang phục – di chuyển; hỗ trợ xử lý tình huống phát sinh; đồng hành kết nối tập thể; tối ưu trải nghiệm khách hàng theo chuẩn Ruby Wings.",
    "popularity_score": 0.94,
    "value_score": 0.6,
    "family_friendly": false,
    "senior_friendly": true,
    "corporate_friendly": false,
    "summary": "Hành trình 2 ngày 1 đêm kết nối lịch sử Mưa Đỏ, văn hoá bản địa Tây Trường Sơn và không gian retreat tĩnh lặng giữa đại ngàn – mang lại cảm hứng sống đẹp và năng lượng tích cực.",
    "style": "Lịch sử – văn hoá bản địa – retreat thiên nhiên; kết nối cảm xúc – nuôi dưỡng năng lượng – lan toả giá trị sống.",
    "includes": [
      "Gặp gỡ và nghe chuyện từ Cựu chiến binh – nhân chứng lịch sử",
      "Đêm lửa trại 'Ngọn lửa Trường Sơn' với cồng chiêng – đàn Ta Lư",
      "Nghi lễ tưởng niệm tại Nghĩa trang Liệt sĩ Quốc gia Trường Sơn",
      "Thiền – khí công giữa thiên nhiên Tây Trường Sơn",
      "Trải nghiệm văn hoá bản địa Vân Kiều – Pa Kô",
      "Được đồng hành bởi chuyên viên y tế suốt tuyến",
      "Ngày 1: Huế – Thành Cổ – Nghĩa trang Liệt sĩ Trường Sơn – Hướng Hóa (Ăn sáng, trưa, tối)",
      "Ngày 2: Hướng Hóa – Quảng Trị – Huế (Ăn sáng, trưa, ...)"
    ],
    "notes": "Lưu ý về trang phục, sức khỏe, an toàn di chuyển; chuẩn bị giấy tờ tùy thân; tuân thủ hướng dẫn của HDV; bảo vệ môi trường tại điểm đến; hạn chế mang đồ công nghệ không cần thiết; có mặt đúng giờ theo lịch trình; một số hoạt động có thể thay đổi tùy điều kiện thời tiết hoặc quy định địa phương",
    "transport": "Xe từ 16 chỗ đến 45 chỗ tuỳ số lượng khách, bảo đảm xe đời mới, chất lượng cao",
    "accommodation": "Khách sạn tiêu chuẩn từ 3* hoặc homestay chất lượng tương đương; phòng sạch sẽ, thoáng mát, đầy đủ tiện nghi cơ bản (máy lạnh, nước nóng, vệ sinh riêng). Tiêu chuẩn có thể thay đổi tùy theo gói dịch vụ, địa phương lưu trú và nhu cầu nâng cấp của đoàn",
    "meals": "ăn 3 bữa chính tiêu chuẩn 150.000 VNĐ/khách (01 bữa tăng cường trong đêm giao lưu tiêu chuẩn 200.000VNĐ/khách), ăn theo thực đơn thống nhất ưu tiên các món đặc sản địa phương, nước uống suốt hành trình",
    "event_support": "Hỗ trợ đoàn trong suốt hành trình: theo sát lịch trình – điều phối giờ giấc – hỗ trợ chụp ảnh – ghi nhận nhu cầu cá nhân; kiểm soát an toàn điểm đến; nhắc nhở sức khỏe – trang phục – di chuyển; hỗ trợ xử lý tình huống phát sinh; đồng hành kết nối tập thể; tối ưu trải nghiệm khách hàng theo chuẩn Ruby Wings.",
    "created_at": "2026-01-16T09:07:10.067776Z",
    "last_updated": "2026-01-16T09:07:10.067776Z"
  },
  "tour_007": {
    "tour_id": "tour_007",
    "index": 7,
    "tour_name": "Ngọn Lửa Trường Sơn – Hành Trình Ký Ức (2 ngày 1 đêm)",
    "location": "Thị xã Quảng Trị, Vĩnh Linh, Gio Linh, Hướng Hoá (cũ) - Quảng Trị",
    "region": "Miền Trung",
    "tags": [
      "thiền",
      "2_ngày",
      "du_lịch_xanh",
      "lửa_trại",
      "retreat",
      "thiên_nhiên",
      "trải_nghiệm",
      "tâm_linh",
      "lịch_sử",
      "văn_hóa"
    ],
    "duration": "2 ngày 1 đêm",
    "duration_days": 2,
    "price_text": "Tùy theo gói dịch vụ (khoảng 1.800.000 – 2.800.000 VNĐ/người), giá thay đổi theo đoàn – phương tiện – dịch vụ kèm theo",
    "min_price": 1800000,
    "max_price": 2800000,
    "avg_price": 2300000,
    "embedding_text": "Ngọn Lửa Trường Sơn – Hành Trình Ký Ức (2 ngày 1 đêm) Hành trình 2 ngày 1 đêm tại Quảng Trị kết nối ký ức lịch sử, trải nghiệm văn hoá bản địa, thiền – khí công chăm sóc sức khỏe và đêm lửa trại Trường Sơn đầy cảm xúc. Thị xã Quảng Trị, Vĩnh Linh, Gio Linh, Hướng Hoá (cũ) - Quảng Trị Tĩnh tại – năng động; nuôi dưỡng thể chất – tinh thần; kết nối lịch sử – văn hóa – thiên nhiên. Đêm lửa trại 'Ngọn lửa Trường Sơn' với cồng chiêng – đàn Ta Lư Hoạt động tri ân – tưởng niệm tại Nghĩa trang Liệt sĩ Quốc gia Giao lưu với Cựu chiến binh – nhân chứng lịch sử Thiền – khí công chăm sóc sức khỏe từ gốc Khơi dậy giá trị sống – tinh thần sẻ chia – trách nhiệm cộng đồng Trải nghiệm văn hoá bản địa Vân Kiều – Pa Kô Ngày 1: Huế – Nghĩa trang Liệt sĩ Trường Sơn – Hướng Hóa (Ăn ---, trưa, tối) Ngày 2: Hướng Hóa – Quảng Trị – Huế (Ăn sáng, trưa, tối) Lưu ý về trang phục, sức khỏe, an toàn di chuyển; chuẩn bị giấy tờ tùy thân; tuân thủ hướng dẫn của HDV; bảo vệ môi trường tại điểm đến; hạn chế mang đồ công nghệ không cần thiết; có mặt đúng giờ theo lịch trình; một số hoạt động có thể thay đổi tùy điều kiện thời tiết hoặc quy định địa phương 2 ngày 1 đêm Tùy theo gói dịch vụ (khoảng 1.800.000 – 2.800.000 VNĐ/người), giá thay đổi theo đoàn – phương tiện – dịch vụ kèm theo Khách sạn tiêu chuẩn từ 3* hoặc homestay chất lượng tương đương; phòng sạch sẽ, thoáng mát, đầy đủ tiện nghi cơ bản (máy lạnh, nước nóng, vệ sinh riêng). Tiêu chuẩn có thể thay đổi tùy theo gói dịch vụ, địa phương lưu trú và nhu cầu nâng cấp của đoàn ăn 3 bữa chính tiêu chuẩn 150.000 VNĐ/khách (01 bữa tăng cường trong đêm giao lưu tiêu chuẩn 200.000VNĐ/khách), ăn theo thực đơn thống nhất ưu tiên các món đặc sản địa phương, nước uống suốt hành trình Xe từ 16 chỗ đến 45 chỗ tuỳ số lượng khách, bảo đảm xe đời mới, chất lượng cao Hỗ trợ đoàn trong suốt hành trình: theo sát lịch trình – điều phối giờ giấc – hỗ trợ chụp ảnh – ghi nhận nhu cầu cá nhân; kiểm soát an toàn điểm đến; nhắc nhở sức khỏe – trang phục – di chuyển; hỗ trợ xử lý tình huống phát sinh; đồng hành kết nối tập thể; tối ưu trải nghiệm khách hàng theo chuẩn Ruby Wings.",
    "popularity_score": 0.93,
    "value_score": 0.6,
    "family_friendly": false,
    "senior_friendly": true,
    "corporate_friendly": false,
    "summary": "Hành trình 2 ngày 1 đêm tại Quảng Trị kết nối ký ức lịch sử, trải nghiệm văn hoá bản địa, thiền – khí công chăm sóc sức khỏe và đêm lửa trại Trường Sơn đầy cảm xúc.",
    "style": "Tĩnh tại – năng động; nuôi dưỡng thể chất – tinh thần; kết nối lịch sử – văn hóa – thiên nhiên.",
    "includes": [
      "Đêm lửa trại 'Ngọn lửa Trường Sơn' với cồng chiêng – đàn Ta Lư",
      "Hoạt động tri ân – tưởng niệm tại Nghĩa trang Liệt sĩ Quốc gia",
      "Giao lưu với Cựu chiến binh – nhân chứng lịch sử",
      "Thiền – khí công chăm sóc sức khỏe từ gốc",
      "Khơi dậy giá trị sống – tinh thần sẻ chia – trách nhiệm cộng đồng",
      "Trải nghiệm văn hoá bản địa Vân Kiều – Pa Kô",
      "Ngày 1: Huế – Nghĩa trang Liệt sĩ Trường Sơn – Hướng Hóa (Ăn ---, trưa, tối)",
      "Ngày 2: Hướng Hóa – Quảng Trị – Huế (Ăn sáng, trưa, tối)"
    ],
    "notes": "Lưu ý về trang phục, sức khỏe, an toàn di chuyển; chuẩn bị giấy tờ tùy thân; tuân thủ hướng dẫn của HDV; bảo vệ môi trường tại điểm đến; hạn chế mang đồ công nghệ không cần thiết; có mặt đúng giờ theo lịch trình; một số hoạt động có thể thay đổi tùy điều kiện thời tiết hoặc quy định địa phương",
    "transport": "Xe từ 16 chỗ đến 45 chỗ tuỳ số lượng khách, bảo đảm xe đời mới, chất lượng cao",
    "accommodation": "Khách sạn tiêu chuẩn từ 3* hoặc homestay chất lượng tương đương; phòng sạch sẽ, thoáng mát, đầy đủ tiện nghi cơ bản (máy lạnh, nước nóng, vệ sinh riêng). Tiêu chuẩn có thể thay đổi tùy theo gói dịch vụ, địa phương lưu trú và nhu cầu nâng cấp của đoàn",
    "meals": "ăn 3 bữa chính tiêu chuẩn 150.000 VNĐ/khách (01 bữa tăng cường trong đêm giao lưu tiêu chuẩn 200.000VNĐ/khách), ăn theo thực đơn thống nhất ưu tiên các món đặc sản địa phương, nước uống suốt hành trình",
    "event_support": "Hỗ trợ đoàn trong suốt hành trình: theo sát lịch trình – điều phối giờ giấc – hỗ trợ chụp ảnh – ghi nhận nhu cầu cá nhân; kiểm soát an toàn điểm đến; nhắc nhở sức khỏe – trang phục – di chuyển; hỗ trợ xử lý tình huống phát sinh; đồng hành kết nối tập thể; tối ưu trải nghiệm khách hàng theo chuẩn Ruby Wings.",
    "created_at": "2026-01-16T09:07:10.068797Z",
    "last_updated": "2026-01-16T09:07:10.068797Z"
  },
  "tour_008": {
    "tour_id": "tour_008",
    "index": 8,
    "tour_name": "Tiếng gọi Vĩ tuyến 17 – Hồi ức cùng đồng đội",
    "location": "Quảng Trị – Vĩ tuyến 17 – Trường Sơn",
    "region": "Miền Trung",
    "tags": [
      "trải_nghiệm",
      "retreat",
      "lịch_sử",
      "du_lịch_xanh"
    ],
    "duration": "3 ngày 2 đêm",
    "duration_days": 3,
    "price_text": "3.000.000 – 4.500.000 VNĐ/người (tùy dịch vụ – xe – số lượng CCB trong đoàn)",
    "min_price": 3000000,
    "max_price": 4500000,
    "avg_price": 3750000,
    "embedding_text": "Tiếng gọi Vĩ tuyến 17 – Hồi ức cùng đồng đội Hành trình 3 ngày 2 đêm dành cho Cựu chiến binh, với nhịp đi nhẹ nhàng – cảm xúc sâu sắc, lắng nghe – tri ân – kết nối ký ức và lan tỏa giá trị nhân văn. Quảng Trị – Vĩ tuyến 17 – Trường Sơn Retreat nhẹ nhàng – cảm xúc – kết nối ký ức – lắng nghe – tri ân. Lắng nghe – chia sẻ câu chuyện của Cựu chiến binh Tri ân tại các điểm lịch sử linh thiêng Hành trình kết nối ký ức – đồng đội – thế hệ trẻ Không gian retreat cảm xúc sâu sắc Nhịp đi nhẹ nhàng phù hợp cho CCB Ngày 1: Dấu ấn Vĩ tuyến – Hào hùng khát vọng (Ăn ---, trưa, tối) Ngày 2: Huyền thoại Trường Sơn (Ăn sáng, trưa, tối) Ngày 3: Tổng kết hành trình – Tri ân – chia tay (Ăn sáng, trưa) Lưu ý về trang phục, sức khỏe, an toàn di chuyển; chuẩn bị giấy tờ tùy thân; tuân thủ hướng dẫn của HDV; bảo vệ môi trường tại điểm đến; hạn chế mang đồ công nghệ không cần thiết; có mặt đúng giờ theo lịch trình; một số hoạt động có thể thay đổi tùy điều kiện thời tiết hoặc quy định địa phương 3 ngày 2 đêm 3.000.000 – 4.500.000 VNĐ/người (tùy dịch vụ – xe – số lượng CCB trong đoàn) Khách sạn tiêu chuẩn từ 3* hoặc homestay chất lượng tương đương; phòng sạch sẽ, thoáng mát, đầy đủ tiện nghi cơ bản (máy lạnh, nước nóng, vệ sinh riêng). Tiêu chuẩn có thể thay đổi tùy theo gói dịch vụ, địa phương lưu trú và nhu cầu nâng cấp của đoàn ăn 5 bữa chính tiêu chuẩn 150.000 VNĐ/khách (01 bữa tăng cường trong đêm giao lưu tiêu chuẩn 200.000VNĐ/khách), ăn theo thực đơn thống nhất ưu tiên các món đặc sản địa phương, nước uống suốt hành trình Xe từ 16 chỗ đến 45 chỗ tuỳ số lượng khách, bảo đảm xe đời mới, chất lượng cao Hỗ trợ đoàn trong suốt hành trình: theo sát lịch trình – điều phối giờ giấc – hỗ trợ chụp ảnh – ghi nhận nhu cầu cá nhân; kiểm soát an toàn điểm đến; nhắc nhở sức khỏe – trang phục – di chuyển; hỗ trợ xử lý tình huống phát sinh; đồng hành kết nối tập thể; tối ưu trải nghiệm khách hàng theo chuẩn Ruby Wings.",
    "popularity_score": 0.92,
    "value_score": 0.6,
    "family_friendly": false,
    "senior_friendly": false,
    "corporate_friendly": false,
    "summary": "Hành trình 3 ngày 2 đêm dành cho Cựu chiến binh, với nhịp đi nhẹ nhàng – cảm xúc sâu sắc, lắng nghe – tri ân – kết nối ký ức và lan tỏa giá trị nhân văn.",
    "style": "Retreat nhẹ nhàng – cảm xúc – kết nối ký ức – lắng nghe – tri ân.",
    "includes": [
      "Lắng nghe – chia sẻ câu chuyện của Cựu chiến binh",
      "Tri ân tại các điểm lịch sử linh thiêng",
      "Hành trình kết nối ký ức – đồng đội – thế hệ trẻ",
      "Không gian retreat cảm xúc sâu sắc",
      "Nhịp đi nhẹ nhàng phù hợp cho CCB",
      "Ngày 1: Dấu ấn Vĩ tuyến – Hào hùng khát vọng (Ăn ---, trưa, tối)",
      "Ngày 2: Huyền thoại Trường Sơn (Ăn sáng, trưa, tối)",
      "Ngày 3: Tổng kết hành trình – Tri ân – chia tay (Ăn sáng, trưa)"
    ],
    "notes": "Lưu ý về trang phục, sức khỏe, an toàn di chuyển; chuẩn bị giấy tờ tùy thân; tuân thủ hướng dẫn của HDV; bảo vệ môi trường tại điểm đến; hạn chế mang đồ công nghệ không cần thiết; có mặt đúng giờ theo lịch trình; một số hoạt động có thể thay đổi tùy điều kiện thời tiết hoặc quy định địa phương",
    "transport": "Xe từ 16 chỗ đến 45 chỗ tuỳ số lượng khách, bảo đảm xe đời mới, chất lượng cao",
    "accommodation": "Khách sạn tiêu chuẩn từ 3* hoặc homestay chất lượng tương đương; phòng sạch sẽ, thoáng mát, đầy đủ tiện nghi cơ bản (máy lạnh, nước nóng, vệ sinh riêng). Tiêu chuẩn có thể thay đổi tùy theo gói dịch vụ, địa phương lưu trú và nhu cầu nâng cấp của đoàn",
    "meals": "ăn 5 bữa chính tiêu chuẩn 150.000 VNĐ/khách (01 bữa tăng cường trong đêm giao lưu tiêu chuẩn 200.000VNĐ/khách), ăn theo thực đơn thống nhất ưu tiên các món đặc sản địa phương, nước uống suốt hành trình",
    "event_support": "Hỗ trợ đoàn trong suốt hành trình: theo sát lịch trình – điều phối giờ giấc – hỗ trợ chụp ảnh – ghi nhận nhu cầu cá nhân; kiểm soát an toàn điểm đến; nhắc nhở sức khỏe – trang phục – di chuyển; hỗ trợ xử lý tình huống phát sinh; đồng hành kết nối tập thể; tối ưu trải nghiệm khách hàng theo chuẩn Ruby Wings.",
    "created_at": "2026-01-16T09:07:10.068797Z",
    "last_updated": "2026-01-16T09:07:10.068797Z"
  },
  "tour_009": {
    "tour_id": "tour_009",
    "index": 9,
    "tour_name": "Tiếng gọi Vĩ tuyến 17 – Hồi ức cùng đồng đội",
    "location": "Vĩ tuyến 17 – Quảng Trị",
    "region": "Miền Trung",
    "tags": [
      "trải_nghiệm",
      "1_ngày",
      "lịch_sử",
      "du_lịch_xanh"
    ],
    "duration": "1 ngày",
    "duration_days": 1,
    "price_text": "Bảng giá theo số lượng (nghìn VNĐ/người): 10-12: 2095; 13-14: 1750; 15-18: 1669; 19-21: 1500; 22-24: 1385; 25-27: 1295; 28-30: 1250; 31-33: 1180; 34-36: 1140; 37-39: 1095; 40-42: 1065",
    "min_price": 1065,
    "max_price": 2095,
    "avg_price": 1580,
    "embedding_text": "Tiếng gọi Vĩ tuyến 17 – Hồi ức cùng đồng đội Hành trình 1 ngày dành cho Cựu chiến binh trở lại chiến trường xưa, lắng nghe – chia sẻ ký ức, tri ân và kết nối đồng đội trong không khí trang trọng và xúc động. Vĩ tuyến 17 – Quảng Trị Nhịp đi nhẹ nhàng – cảm xúc – tri ân – kết nối ký ức. Thăm lại chiến trường xưa – Vĩ tuyến 17 Lắng nghe và chia sẻ câu chuyện của Cựu chiến binh Giao lưu ý nghĩa – kết nối đồng đội Tri ân tại các điểm lịch sử thiêng liêng Hành trình nhẹ nhàng, phù hợp cho CCB Lan tỏa giá trị nhân văn và tinh thần đoàn kết Ngày 1: Tiếng gọi Vĩ tuyến 17 – Hồi ức cùng đồng đội (Ăn ---, trưa, tối) Lưu ý về trang phục, sức khỏe, an toàn di chuyển; chuẩn bị giấy tờ tùy thân; tuân thủ hướng dẫn của HDV; bảo vệ môi trường tại điểm đến; hạn chế mang đồ công nghệ không cần thiết; có mặt đúng giờ theo lịch trình; một số hoạt động có thể thay đổi tùy điều kiện thời tiết hoặc quy định địa phương 1 ngày Bảng giá theo số lượng (nghìn VNĐ/người): 10-12: 2095; 13-14: 1750; 15-18: 1669; 19-21: 1500; 22-24: 1385; 25-27: 1295; 28-30: 1250; 31-33: 1180; 34-36: 1140; 37-39: 1095; 40-42: 1065 Không áp dụng (tour 1 ngày) ăn 2 bữa chính tiêu chuẩn 150.000 VNĐ/khách (trong đó có 01 bữa tăng cường tiêu chuẩn 200.000VNĐ/khách), ăn theo thực đơn thống nhất ưu tiên các món đặc sản địa phương, nước uống suốt hành trình Xe từ 16 chỗ đến 45 chỗ tuỳ số lượng khách, bảo đảm xe đời mới, chất lượng cao Hỗ trợ đoàn trong suốt hành trình: theo sát lịch trình – điều phối giờ giấc – hỗ trợ chụp ảnh – ghi nhận nhu cầu cá nhân; kiểm soát an toàn điểm đến; nhắc nhở sức khỏe – trang phục – di chuyển; hỗ trợ xử lý tình huống phát sinh; đồng hành kết nối tập thể; tối ưu trải nghiệm khách hàng theo chuẩn Ruby Wings.",
    "popularity_score": 0.92,
    "value_score": 0.8,
    "family_friendly": false,
    "senior_friendly": true,
    "corporate_friendly": false,
    "summary": "Hành trình 1 ngày dành cho Cựu chiến binh trở lại chiến trường xưa, lắng nghe – chia sẻ ký ức, tri ân và kết nối đồng đội trong không khí trang trọng và xúc động.",
    "style": "Nhịp đi nhẹ nhàng – cảm xúc – tri ân – kết nối ký ức.",
    "includes": [
      "Thăm lại chiến trường xưa – Vĩ tuyến 17",
      "Lắng nghe và chia sẻ câu chuyện của Cựu chiến binh",
      "Giao lưu ý nghĩa – kết nối đồng đội",
      "Tri ân tại các điểm lịch sử thiêng liêng",
      "Hành trình nhẹ nhàng, phù hợp cho CCB",
      "Lan tỏa giá trị nhân văn và tinh thần đoàn kết",
      "Ngày 1: Tiếng gọi Vĩ tuyến 17 – Hồi ức cùng đồng đội (Ăn ---, trưa, tối)"
    ],
    "notes": "Lưu ý về trang phục, sức khỏe, an toàn di chuyển; chuẩn bị giấy tờ tùy thân; tuân thủ hướng dẫn của HDV; bảo vệ môi trường tại điểm đến; hạn chế mang đồ công nghệ không cần thiết; có mặt đúng giờ theo lịch trình; một số hoạt động có thể thay đổi tùy điều kiện thời tiết hoặc quy định địa phương",
    "transport": "Xe từ 16 chỗ đến 45 chỗ tuỳ số lượng khách, bảo đảm xe đời mới, chất lượng cao",
    "accommodation": "Không áp dụng (tour 1 ngày)",
    "meals": "ăn 2 bữa chính tiêu chuẩn 150.000 VNĐ/khách (trong đó có 01 bữa tăng cường tiêu chuẩn 200.000VNĐ/khách), ăn theo thực đơn thống nhất ưu tiên các món đặc sản địa phương, nước uống suốt hành trình",
    "event_support": "Hỗ trợ đoàn trong suốt hành trình: theo sát lịch trình – điều phối giờ giấc – hỗ trợ chụp ảnh – ghi nhận nhu cầu cá nhân; kiểm soát an toàn điểm đến; nhắc nhở sức khỏe – trang phục – di chuyển; hỗ trợ xử lý tình huống phát sinh; đồng hành kết nối tập thể; tối ưu trải nghiệm khách hàng theo chuẩn Ruby Wings.",
    "created_at": "2026-01-16T09:07:10.068797Z",
    "last_updated": "2026-01-16T09:07:10.068797Z"
  },
  "tour_010": {
    "tour_id": "tour_010",
    "index": 10,
    "tour_name": "Hành trình Phong Hương – Bình yên giữa núi rừng Trường Sơn (2 ngày 1 đêm)",
    "location": "Quảng Trị – Hướng Hóa – Rào Quán – Trường Sơn",
    "region": "Miền Trung",
    "tags": [
      "thiền",
      "2_ngày",
      "du_lịch_xanh",
      "lửa_trại",
      "retreat",
      "thiên_nhiên",
      "trải_nghiệm",
      "tâm_linh",
      "lịch_sử",
      "văn_hóa"
    ],
    "duration": "2 ngày 1 đêm",
    "duration_days": 2,
    "price_text": "Giá theo bảng (đơn vị: nghìn VNĐ/người): 11-13: 2570; 14-16: 2500; 17-19: 2250; 20-22: 2070; 23-25: 1950; 26-28: 1900; 29-31: 1860; 32-34: 1820; 35-37: 1770; 38-40: 1720",
    "min_price": 1720,
    "max_price": 2570,
    "avg_price": 2145,
    "embedding_text": "Hành trình Phong Hương – Bình yên giữa núi rừng Trường Sơn (2 ngày 1 đêm) Hành trình 2 ngày 1 đêm kết hợp tri ân lịch sử, trải nghiệm rừng phong hương, văn hóa Vân Kiều – Pa Kô và các hoạt động thiền – khí công giữa thiên nhiên nguyên sơ. Quảng Trị – Hướng Hóa – Rào Quán – Trường Sơn Tri ân – thiên nhiên – văn hoá bản địa – retreat chữa lành. Đêm lửa trại 'Ngọn lửa Trường Sơn' – cồng chiêng – đàn Ta Lư – dân ca Vân Kiều Du thuyền ngắm rừng phong hương – sắc màu như trời Tây Hoạt động tri ân và phát triển bền vững Thiền – khí công trong rừng núi Trải nghiệm văn hoá bản địa Vân Kiều – Pa Kô Khoảnh khắc chữa lành tại hồ Rào Quán Ngày 1: Huế – Thành cổ Quảng Trị – Hướng Hóa (Ăn ---, trưa, tối) Ngày 2: Hướng Hóa – Quảng Trị – Huế (Ăn sáng, trưa, tối) Hành trình được thiết kế nhịp độ chậm, nhưng vẫn có các hoạt động đi bộ, vui lòng thông báo trước về tình trạng sức khỏe, bệnh lý đặc biệt (nếu có) để BTC có sự chuẩn bị và hỗ trợ y tế tốt nhất. Khi tham quan các điểm tâm linh (Thành Cổ) và di tích lịch sử, quý khách mang lịch sự, kín đáo (quần dài, áo có tay). Nên mang giày thể thao để dễ dàng di chuyển, lên thuyền cần cỡi bỏ dày dép. Chuẩn bị thêm áo khoác nhẹ, và các vật dụng chống nắng/mưa.: Hãy đến với một tâm thế cởi mở và sẵn sàng chia sẻ (nếu muốn) để hành trình thêm phần ý nghĩa và nhân văn.Luôn tuân thủ các quy tắc ứng xử tại các điểm di tích lịch sử và khi giao lưu với cộng đồng dân tộc thiểu số, giữ gìn sự trang nghiêm, tôn kính tại những nơi linh thiêng.Luôn tuân thủ hướng dẫn của trưởng đoàn và hướng dẫn viên để đảm bảo an toàn tuyệt đối trong suốt hành trình 2 ngày 1 đêm Giá theo bảng (đơn vị: nghìn VNĐ/người): 11-13: 2570; 14-16: 2500; 17-19: 2250; 20-22: 2070; 23-25: 1950; 26-28: 1900; 29-31: 1860; 32-34: 1820; 35-37: 1770; 38-40: 1720 Homestay hoặc khách sạn 3* (cách 1 km), bao gồm ăn sáng ăn 3 bữa chính tiêu chuẩn 150.000 VNĐ/khách (01 bữa tăng cường trong đêm giao lưu tiêu chuẩn 200.000VNĐ/khách), ăn theo thực đơn thống nhất ưu tiên các món đặc sản địa phương, nước uống suốt hành trình Xe từ 16 chỗ đến 45 chỗ tuỳ số lượng khách, bảo đảm xe đời mới, chất lượng cao Hỗ trợ âm thanh – không gian tổng kết; ảnh – clip – slideshow cơ bản",
    "popularity_score": 0.91,
    "value_score": 0.8,
    "family_friendly": false,
    "senior_friendly": true,
    "corporate_friendly": false,
    "summary": "Hành trình 2 ngày 1 đêm kết hợp tri ân lịch sử, trải nghiệm rừng phong hương, văn hóa Vân Kiều – Pa Kô và các hoạt động thiền – khí công giữa thiên nhiên nguyên sơ.",
    "style": "Tri ân – thiên nhiên – văn hoá bản địa – retreat chữa lành.",
    "includes": [
      "Đêm lửa trại 'Ngọn lửa Trường Sơn' – cồng chiêng – đàn Ta Lư – dân ca Vân Kiều",
      "Du thuyền ngắm rừng phong hương – sắc màu như trời Tây",
      "Hoạt động tri ân và phát triển bền vững",
      "Thiền – khí công trong rừng núi",
      "Trải nghiệm văn hoá bản địa Vân Kiều – Pa Kô",
      "Khoảnh khắc chữa lành tại hồ Rào Quán",
      "Ngày 1: Huế – Thành cổ Quảng Trị – Hướng Hóa (Ăn ---, trưa, tối)",
      "Ngày 2: Hướng Hóa – Quảng Trị – Huế (Ăn sáng, trưa, tối)"
    ],
    "notes": "Hành trình được thiết kế nhịp độ chậm, nhưng vẫn có các hoạt động đi bộ, vui lòng thông báo trước về tình trạng sức khỏe, bệnh lý đặc biệt (nếu có) để BTC có sự chuẩn bị và hỗ trợ y tế tốt nhất. Khi tham quan các điểm tâm linh (Thành Cổ) và di tích lịch sử, quý khách mang lịch sự, kín đáo (quần dài, áo có tay). Nên mang giày thể thao để dễ dàng di chuyển, lên thuyền cần cỡi bỏ dày dép. Chuẩn bị thêm áo khoác nhẹ, và các vật dụng chống nắng/mưa.: Hãy đến với một tâm thế cởi mở và sẵn sàng chia sẻ (nếu muốn) để hành trình thêm phần ý nghĩa và nhân văn.Luôn tuân thủ các quy tắc ứng xử tại các điểm di tích lịch sử và khi giao lưu với cộng đồng dân tộc thiểu số, giữ gìn sự trang nghiêm, tôn kính tại những nơi linh thiêng.Luôn tuân thủ hướng dẫn của trưởng đoàn và hướng dẫn viên để đảm bảo an toàn tuyệt đối trong suốt hành trình",
    "transport": "Xe từ 16 chỗ đến 45 chỗ tuỳ số lượng khách, bảo đảm xe đời mới, chất lượng cao",
    "accommodation": "Homestay hoặc khách sạn 3* (cách 1 km), bao gồm ăn sáng",
    "meals": "ăn 3 bữa chính tiêu chuẩn 150.000 VNĐ/khách (01 bữa tăng cường trong đêm giao lưu tiêu chuẩn 200.000VNĐ/khách), ăn theo thực đơn thống nhất ưu tiên các món đặc sản địa phương, nước uống suốt hành trình",
    "event_support": "Hỗ trợ âm thanh – không gian tổng kết; ảnh – clip – slideshow cơ bản",
    "created_at": "2026-01-16T09:07:10.068797Z",
    "last_updated": "2026-01-16T09:07:10.068797Z"
  },
  "tour_011": {
    "tour_id": "tour_011",
    "index": 11,
    "tour_name": "Hành hương tâm linh – Đảo Cồn Cỏ anh hùng (3N2Đ)",
    "location": "Huế – Đông Hà – DMZ – Cửa Việt – Đảo Cồn Cỏ – Vĩnh Mốc – Hiền Lương",
    "region": "Miền Trung",
    "tags": [
      "du_lịch_xanh",
      "gia_đình",
      "lửa_trại",
      "giá_rẻ",
      "cao_cấp",
      "thiên_nhiên",
      "mạo_hiểm",
      "trải_nghiệm",
      "biển_đảo",
      "tâm_linh",
      "lịch_sử",
      "team_building",
      "văn_hóa"
    ],
    "duration": "3 ngày 2 đêm",
    "duration_days": 3,
    "price_text": "3.500.000 – 4.400.000 VNĐ/khách tuỳ số lượng đoàn (15–44 khách). Xe open bus Hà Nội–Đông Hà: 500.000đ; tàu SE ngồi mềm điều hòa: 1.000.000đ.",
    "min_price": 500000,
    "max_price": 4400000,
    "avg_price": 2450000,
    "embedding_text": "Hành hương tâm linh – Đảo Cồn Cỏ anh hùng (3N2Đ) Hành trình 3 ngày 2 đêm khám phá Cồn Cỏ – hòn đảo anh hùng giữa biển Đông, kết hợp trải nghiệm tâm linh – lịch sử tại Trường Sơn, Thành Cổ Quảng Trị, La Vang, Tà Cơn – Khe Sanh, và hệ thống hầm địa đạo Vịnh Mốc. Hành trình thiêng liêng của tri ân, kết nối biển đảo, thưởng thức ẩm thực Duyên hải miền Trung. Huế – Đông Hà – DMZ – Cửa Việt – Đảo Cồn Cỏ – Vĩnh Mốc – Hiền Lương Hành hương tâm linh – trải nghiệm lịch sử – khám phá biển đảo – thiên nhiên nguyên sơ. Nhịp đi ý nghĩa, lắng đọng, kết nối tri ân – trải nghiệm – tìm hiểu văn hóa chiến khu – đảo tiền tiêu. Xe chất lượng cao đưa đón theo chương trình (30–45 chỗ tùy đoàn). Vé tàu khứ hồi Cửa Việt – Cồn Cỏ (tàu du lịch 80 chỗ, hải trình 45 phút). 06 bữa chính tiêu chuẩn 120.000–150.000đ/suất (thay đổi theo khu vực). Khách sạn Đông Hà tiêu chuẩn 4 sao (2 người/phòng, phòng 3 khách khi lẻ nam/nữ). Lưu trú tại Đảo Cồn Cỏ: phòng 3–4 khách/phòng, đầy đủ tiện nghi cơ bản. Hướng dẫn viên chuyên tuyến, nhiệt tình, am hiểu lịch sử – biển đảo. Tham quan & dâng hương Nghĩa trang Trường Sơn, Thành Cổ Quảng Trị, Chùa Sắc Tứ, Thánh địa La Vang. Tham quan Cồn Cỏ: Cổng chào, cột cờ, nhà truyền thống – bảo tàng đảo, Hải đăng, chòi canh Anh hùng Thái Văn A, Bến Nghè, Mõm Hổ, bãi Xuân Hương. Khám phá hệ thống hầm hào – lô cốt – hầm Quân y, rừng nguyên sinh, san hô và đời sống ngư dân đảo. Tham quan Địa đạo Vịnh Mốc – cụm di tích Hiền Lương – Bến Hải. Xe điện trên đảo. Khăn lạnh – nước uống xuyên suốt hành trình. Vòng hoa viếng nghĩa trang. Quà tặng: nón du lịch, ảnh tập thể. Bảo hiểm du lịch theo quy định TCDL Việt Nam. Không bao gồm: nước ngọt, bia, nước giải khát trong bữa ăn; chi tiêu cá nhân; tip HDV – lái xe; âm thanh đêm lửa trại trên đảo (200.000đ/giờ); VAT; các trải nghiệm tự do trên đảo như chèo thuyền, đạp xe, lặn ngắm san hô chuyên nghiệp… Trẻ em: dưới 4 tuổi miễn phí; 4–8 tuổi: 50%; 8–11 tuổi: 75%; từ 11 tuổi tính vé người lớn. Lưu ý: mang CMND/CCCD; chuẩn bị thuốc say sóng, kem chống nắng, giày mềm; tiết kiệm nước ngọt trên đảo; không bắt cua đá, không chụp nơi có biển cấm; giữ gìn môi trường biển đảo. 3 ngày 2 đêm 3.500.000 – 4.400.000 VNĐ/khách tuỳ số lượng đoàn (15–44 khách). Xe open bus Hà Nội–Đông Hà: 500.000đ; tàu SE ngồi mềm điều hòa: 1.000.000đ. Khách sạn 4* tại Đông Hà; phòng 3–4 khách/phòng trên Đảo Cồn Cỏ (tiện nghi cơ bản). 06 bữa chính tiêu chuẩn 120.000–150.000đ/suất; ăn sáng tại khách sạn hoặc tô + ly; hải sản Cồn Cỏ nổi tiếng, đặc biệt hàu Cồn Cỏ. ['Xe 30 chỗ', 'Xe 34 chỗ', 'Xe 40 chỗ', 'Xe 45 chỗ', 'Tàu du lịch biển 80 chỗ'] Hỗ trợ đoàn tri ân – dâng hương; hỗ trợ tổ chức giao lưu cùng chiến sĩ đảo; hỗ trợ thiết kế chương trình theo đoàn.",
    "popularity_score": 0.9,
    "value_score": 0.8,
    "family_friendly": true,
    "senior_friendly": false,
    "corporate_friendly": true,
    "summary": "Hành trình 3 ngày 2 đêm khám phá Cồn Cỏ – hòn đảo anh hùng giữa biển Đông, kết hợp trải nghiệm tâm linh – lịch sử tại Trường Sơn, Thành Cổ Quảng Trị, La Vang, Tà Cơn – Khe Sanh, và hệ thống hầm địa đạo Vịnh Mốc. Hành trình thiêng liêng của tri ân, kết nối biển đảo, thưởng thức ẩm thực Duyên hải miền Trung.",
    "style": "Hành hương tâm linh – trải nghiệm lịch sử – khám phá biển đảo – thiên nhiên nguyên sơ. Nhịp đi ý nghĩa, lắng đọng, kết nối tri ân – trải nghiệm – tìm hiểu văn hóa chiến khu – đảo tiền tiêu.",
    "includes": [
      "Xe chất lượng cao đưa đón theo chương trình (30–45 chỗ tùy đoàn).",
      "Vé tàu khứ hồi Cửa Việt – Cồn Cỏ (tàu du lịch 80 chỗ, hải trình 45 phút).",
      "06 bữa chính tiêu chuẩn 120.000–150.000đ/suất (thay đổi theo khu vực).",
      "Khách sạn Đông Hà tiêu chuẩn 4 sao (2 người/phòng, phòng 3 khách khi lẻ nam/nữ).",
      "Lưu trú tại Đảo Cồn Cỏ: phòng 3–4 khách/phòng, đầy đủ tiện nghi cơ bản.",
      "Hướng dẫn viên chuyên tuyến, nhiệt tình, am hiểu lịch sử – biển đảo.",
      "Tham quan & dâng hương Nghĩa trang Trường Sơn, Thành Cổ Quảng Trị, Chùa Sắc Tứ, Thánh địa La Vang.",
      "Tham quan Cồn Cỏ: Cổng chào, cột cờ, nhà truyền thống – bảo tàng đảo, Hải đăng, chòi canh Anh hùng Thái Văn A, Bến Nghè, Mõm Hổ, bãi Xuân Hương.",
      "Khám phá hệ thống hầm hào – lô cốt – hầm Quân y, rừng nguyên sinh, san hô và đời sống ngư dân đảo.",
      "Tham quan Địa đạo Vịnh Mốc – cụm di tích Hiền Lương – Bến Hải.",
      "Xe điện trên đảo.",
      "Khăn lạnh – nước uống xuyên suốt hành trình.",
      "Vòng hoa viếng nghĩa trang.",
      "Quà tặng: nón du lịch, ảnh tập thể.",
      "Bảo hiểm du lịch theo quy định TCDL Việt Nam."
    ],
    "notes": "Không bao gồm: nước ngọt, bia, nước giải khát trong bữa ăn; chi tiêu cá nhân; tip HDV – lái xe; âm thanh đêm lửa trại trên đảo (200.000đ/giờ); VAT; các trải nghiệm tự do trên đảo như chèo thuyền, đạp xe, lặn ngắm san hô chuyên nghiệp… Trẻ em: dưới 4 tuổi miễn phí; 4–8 tuổi: 50%; 8–11 tuổi: 75%; từ 11 tuổi tính vé người lớn. Lưu ý: mang CMND/CCCD; chuẩn bị thuốc say sóng, kem chống nắng, giày mềm; tiết kiệm nước ngọt trên đảo; không bắt cua đá, không chụp nơi có biển cấm; giữ gìn môi trường biển đảo.",
    "transport": [
      "Xe 30 chỗ",
      "Xe 34 chỗ",
      "Xe 40 chỗ",
      "Xe 45 chỗ",
      "Tàu du lịch biển 80 chỗ"
    ],
    "accommodation": "Khách sạn 4* tại Đông Hà; phòng 3–4 khách/phòng trên Đảo Cồn Cỏ (tiện nghi cơ bản).",
    "meals": "06 bữa chính tiêu chuẩn 120.000–150.000đ/suất; ăn sáng tại khách sạn hoặc tô + ly; hải sản Cồn Cỏ nổi tiếng, đặc biệt hàu Cồn Cỏ.",
    "event_support": "Hỗ trợ đoàn tri ân – dâng hương; hỗ trợ tổ chức giao lưu cùng chiến sĩ đảo; hỗ trợ thiết kế chương trình theo đoàn.",
    "created_at": "2026-01-16T09:07:10.068797Z",
    "last_updated": "2026-01-16T09:07:10.068797Z"
  },
  "tour_012": {
    "tour_id": "tour_012",
    "index": 12,
    "tour_name": "Cảng Cửa Việt – Đảo Cồn Cỏ Anh Hùng (2 ngày 1 đêm)",
    "location": "Cửa Việt – Cồn Cỏ – Quảng Trị",
    "region": "Miền Trung",
    "tags": [
      "2_ngày",
      "giá_rẻ",
      "thiên_nhiên",
      "mạo_hiểm",
      "trải_nghiệm",
      "biển_đảo",
      "lịch_sử",
      "văn_hóa"
    ],
    "duration": "2 ngày 1 đêm",
    "duration_days": 2,
    "price_text": "1.600.000 – 2.500.000 VNĐ/người (phụ thuộc tàu và dịch vụ trên đảo)",
    "min_price": 1600000,
    "max_price": 2500000,
    "avg_price": 2050000,
    "embedding_text": "Cảng Cửa Việt – Đảo Cồn Cỏ Anh Hùng (2 ngày 1 đêm) Hành trình 2 ngày 1 đêm khám phá biển đảo Cồn Cỏ – pháo đài tiền tiêu biển Đông, kết hợp trải nghiệm thiên nhiên hoang sơ, văn hóa cư dân và lịch sử oai hùng. Cửa Việt – Cồn Cỏ – Quảng Trị Khám phá biển đảo – lịch sử – thiên nhiên – trải nghiệm linh hoạt. Khám phá đảo Cồn Cỏ – pháo đài tiền tiêu biển Đông Trải nghiệm tàu du lịch và xe điện trên đảo Tìm hiểu kinh tế biển đảo – dịch vụ hậu cần – đời sống cư dân Ngắm cảnh biển và thiên nhiên hoang sơ Trải nghiệm đời sống cộng đồng cư dân đảo Ngày 1: Cửa Việt – Cồn Cỏ (-- / trưa, chiều) Ngày 2: Cồn Cỏ – Cảng Cửa Việt (sáng / -- / --) Mang giấy CMND, CCCDđể sử dụng khi cần; Chuẩn bị áo bơi, mủ, máy ảnh, giày mềm (cao su),... để tắm biển ngắm san hô; Nên chuẩn bị: Thuốc chống say tàu xe; Kem chống nắng, kem chống côn trùng cắn; thuốc đặc trị cho những thành viên có bệnh lý riêng; quý khách sử dụng nước tiết kiệm;Không chụp hình quay phim những nơi có biển cấm (Fly cam phải có giấy phép mới được sử dụng);Không được bắt, di chuyển cua đá, động vật rừng, chuối rừng, sâm cau;Quà có thể mua từ đảo: nước mắm, cá khô, hải sản tươi, giảo cổ lam. 2 ngày 1 đêm 1.600.000 – 2.500.000 VNĐ/người (phụ thuộc tàu và dịch vụ trên đảo) Nhà khách hoặc homestay trên đảo ăn 3 bữa chính tiêu chuẩn 150.000 VNĐ/khách (01 bữa tăng cường nếu có giao lưu 200.000 VNĐ/khách), ăn theo thực đơn ưu tiên đặc sản địa phương, nước uống suốt hành trình Xe từ 16 chỗ đến 45 chỗ tuỳ số lượng khách, bảo đảm xe đời mới, chất lượng cao Hỗ trợ đoàn trong suốt hành trình: theo sát lịch trình – điều phối giờ giấc – hỗ trợ chụp ảnh – ghi nhận nhu cầu cá nhân; kiểm soát an toàn điểm đến; nhắc nhở sức khỏe – trang phục – di chuyển; hỗ trợ xử lý tình huống phát sinh; đồng hành kết nối tập thể; tối ưu trải nghiệm khách hàng theo chuẩn Ruby Wings.",
    "popularity_score": 0.89,
    "value_score": 0.6,
    "family_friendly": false,
    "senior_friendly": false,
    "corporate_friendly": false,
    "summary": "Hành trình 2 ngày 1 đêm khám phá biển đảo Cồn Cỏ – pháo đài tiền tiêu biển Đông, kết hợp trải nghiệm thiên nhiên hoang sơ, văn hóa cư dân và lịch sử oai hùng.",
    "style": "Khám phá biển đảo – lịch sử – thiên nhiên – trải nghiệm linh hoạt.",
    "includes": [
      "Khám phá đảo Cồn Cỏ – pháo đài tiền tiêu biển Đông",
      "Trải nghiệm tàu du lịch và xe điện trên đảo",
      "Tìm hiểu kinh tế biển đảo – dịch vụ hậu cần – đời sống cư dân",
      "Ngắm cảnh biển và thiên nhiên hoang sơ",
      "Trải nghiệm đời sống cộng đồng cư dân đảo",
      "Ngày 1: Cửa Việt – Cồn Cỏ (-- / trưa, chiều)",
      "Ngày 2: Cồn Cỏ – Cảng Cửa Việt (sáng / -- / --)"
    ],
    "notes": "Mang giấy CMND, CCCDđể sử dụng khi cần; Chuẩn bị áo bơi, mủ, máy ảnh, giày mềm (cao su),... để tắm biển ngắm san hô; Nên chuẩn bị: Thuốc chống say tàu xe; Kem chống nắng, kem chống côn trùng cắn; thuốc đặc trị cho những thành viên có bệnh lý riêng; quý khách sử dụng nước tiết kiệm;Không chụp hình quay phim những nơi có biển cấm (Fly cam phải có giấy phép mới được sử dụng);Không được bắt, di chuyển cua đá, động vật rừng, chuối rừng, sâm cau;Quà có thể mua từ đảo: nước mắm, cá khô, hải sản tươi, giảo cổ lam.",
    "transport": "Xe từ 16 chỗ đến 45 chỗ tuỳ số lượng khách, bảo đảm xe đời mới, chất lượng cao",
    "accommodation": "Nhà khách hoặc homestay trên đảo",
    "meals": "ăn 3 bữa chính tiêu chuẩn 150.000 VNĐ/khách (01 bữa tăng cường nếu có giao lưu 200.000 VNĐ/khách), ăn theo thực đơn ưu tiên đặc sản địa phương, nước uống suốt hành trình",
    "event_support": "Hỗ trợ đoàn trong suốt hành trình: theo sát lịch trình – điều phối giờ giấc – hỗ trợ chụp ảnh – ghi nhận nhu cầu cá nhân; kiểm soát an toàn điểm đến; nhắc nhở sức khỏe – trang phục – di chuyển; hỗ trợ xử lý tình huống phát sinh; đồng hành kết nối tập thể; tối ưu trải nghiệm khách hàng theo chuẩn Ruby Wings.",
    "created_at": "2026-01-16T09:07:10.068797Z",
    "last_updated": "2026-01-16T09:07:10.068797Z"
  },
  "tour_013": {
    "tour_id": "tour_013",
    "index": 13,
    "tour_name": "Hành trình trải nghiệm linh hoạt & Nghỉ dưỡng – Hà Nội – Đông Hà – Cổ Thành – Cồn Cỏ – Cửa Việt",
    "location": "Hà Nội – Đông Hà – Thành Cổ – Cửa Việt – Cồn Cỏ",
    "region": "Miền Trung",
    "tags": [
      "du_lịch_xanh",
      "retreat",
      "mạo_hiểm",
      "trải_nghiệm",
      "biển_đảo",
      "tâm_linh",
      "lịch_sử",
      "văn_hóa"
    ],
    "duration": "3 ngày 2 đêm",
    "duration_days": 3,
    "price_text": "Liên hệ tùy gói dịch vụ (trong khoảng 2.200.000 đến 4.500.000 VNĐ/người), phụ thuộc tàu ra đảo – khách sạn – dịch vụ đi kèm",
    "min_price": 2200000,
    "max_price": 4500000,
    "avg_price": 3350000,
    "embedding_text": "Hành trình trải nghiệm linh hoạt & Nghỉ dưỡng – Hà Nội – Đông Hà – Cổ Thành – Cồn Cỏ – Cửa Việt Hành trình 3 ngày 2 đêm kết hợp tâm linh – tri ân lịch sử – nghỉ dưỡng biển và khám phá đảo Cồn Cỏ, mang đến trải nghiệm sâu lắng và thư giãn tại Quảng Trị. Hà Nội – Đông Hà – Thành Cổ – Cửa Việt – Cồn Cỏ Retreat nhẹ nhàng – tâm linh – lịch sử – biển đảo – văn hóa bản địa. Thăm Nghĩa trang Liệt sĩ Trường Sơn – tri ân và cầu nguyện bình an Không gian linh thiêng tại Thánh địa La Vang Tham quan Thành cổ Quảng Trị – Hiền Lương – Bến Hải – Khe Sanh – Dốc Miếu Nghỉ dưỡng tại Khu du lịch biển Cửa Việt Khám phá đảo Cồn Cỏ bằng tàu du lịch và xe điện Tìm hiểu đời sống cư dân đảo và hệ sinh thái biển Ngày 1: Đón khách – Thành Cổ Quảng Trị – Cửa Việt (sáng, trưa, chiều) Ngày 2: Cửa Việt – Đảo Cồn Cỏ (sáng, trưa, chiều) Ngày 3: Tham quan Đông Hà – Tiễn đoàn (sáng, trưa, tối) Mang CMND/CCCD, chuẩn bị đồ bơi – giày mềm – thuốc say sóng, hạn chế dùng nước ngọt trên đảo… 3 ngày 2 đêm Liên hệ tùy gói dịch vụ (trong khoảng 2.200.000 đến 4.500.000 VNĐ/người), phụ thuộc tàu ra đảo – khách sạn – dịch vụ đi kèm Khách sạn tiêu chuẩn từ 3* hoặc homestay chất lượng tương đương; phòng sạch sẽ, thoáng mát, đầy đủ tiện nghi cơ bản (máy lạnh, nước nóng, vệ sinh riêng). Tiêu chuẩn có thể thay đổi tùy theo gói dịch vụ, địa phương lưu trú và nhu cầu nâng cấp của đoàn ăn 3 bữa chính tiêu chuẩn 150.000 VNĐ/khách (01 bữa tăng cường nếu có đêm giao lưu: 200.000VNĐ/khách), ăn thực đơn ưu tiên đặc sản địa phương, nước uống suốt hành trình Xe từ 16 chỗ đến 45 chỗ tuỳ số lượng khách, bảo đảm xe đời mới, chất lượng cao Hỗ trợ đoàn trong suốt hành trình: theo sát lịch trình – điều phối giờ giấc – hỗ trợ chụp ảnh – ghi nhận nhu cầu cá nhân; kiểm soát an toàn điểm đến; nhắc nhở sức khỏe – trang phục – di chuyển; hỗ trợ xử lý tình huống phát sinh; đồng hành kết nối tập thể; tối ưu trải nghiệm khách hàng theo chuẩn Ruby Wings.",
    "popularity_score": 0.88,
    "value_score": 0.6,
    "family_friendly": false,
    "senior_friendly": false,
    "corporate_friendly": false,
    "summary": "Hành trình 3 ngày 2 đêm kết hợp tâm linh – tri ân lịch sử – nghỉ dưỡng biển và khám phá đảo Cồn Cỏ, mang đến trải nghiệm sâu lắng và thư giãn tại Quảng Trị.",
    "style": "Retreat nhẹ nhàng – tâm linh – lịch sử – biển đảo – văn hóa bản địa.",
    "includes": [
      "Thăm Nghĩa trang Liệt sĩ Trường Sơn – tri ân và cầu nguyện bình an",
      "Không gian linh thiêng tại Thánh địa La Vang",
      "Tham quan Thành cổ Quảng Trị – Hiền Lương – Bến Hải – Khe Sanh – Dốc Miếu",
      "Nghỉ dưỡng tại Khu du lịch biển Cửa Việt",
      "Khám phá đảo Cồn Cỏ bằng tàu du lịch và xe điện",
      "Tìm hiểu đời sống cư dân đảo và hệ sinh thái biển",
      "Ngày 1: Đón khách – Thành Cổ Quảng Trị – Cửa Việt (sáng, trưa, chiều)",
      "Ngày 2: Cửa Việt – Đảo Cồn Cỏ (sáng, trưa, chiều)",
      "Ngày 3: Tham quan Đông Hà – Tiễn đoàn (sáng, trưa, tối)"
    ],
    "notes": "Mang CMND/CCCD, chuẩn bị đồ bơi – giày mềm – thuốc say sóng, hạn chế dùng nước ngọt trên đảo…",
    "transport": "Xe từ 16 chỗ đến 45 chỗ tuỳ số lượng khách, bảo đảm xe đời mới, chất lượng cao",
    "accommodation": "Khách sạn tiêu chuẩn từ 3* hoặc homestay chất lượng tương đương; phòng sạch sẽ, thoáng mát, đầy đủ tiện nghi cơ bản (máy lạnh, nước nóng, vệ sinh riêng). Tiêu chuẩn có thể thay đổi tùy theo gói dịch vụ, địa phương lưu trú và nhu cầu nâng cấp của đoàn",
    "meals": "ăn 3 bữa chính tiêu chuẩn 150.000 VNĐ/khách (01 bữa tăng cường nếu có đêm giao lưu: 200.000VNĐ/khách), ăn thực đơn ưu tiên đặc sản địa phương, nước uống suốt hành trình",
    "event_support": "Hỗ trợ đoàn trong suốt hành trình: theo sát lịch trình – điều phối giờ giấc – hỗ trợ chụp ảnh – ghi nhận nhu cầu cá nhân; kiểm soát an toàn điểm đến; nhắc nhở sức khỏe – trang phục – di chuyển; hỗ trợ xử lý tình huống phát sinh; đồng hành kết nối tập thể; tối ưu trải nghiệm khách hàng theo chuẩn Ruby Wings.",
    "created_at": "2026-01-16T09:07:10.068797Z",
    "last_updated": "2026-01-16T09:07:10.068797Z"
  },
  "tour_014": {
    "tour_id": "tour_014",
    "index": 14,
    "tour_name": "Tham quan – Trải nghiệm Bình Trị Thiên (04 ngày 03 đêm)",
    "location": "Huế – Quảng Trị – Quảng Bình",
    "region": "Miền Trung",
    "tags": [
      "cao_cấp",
      "gia_đình",
      "thiên_nhiên",
      "mạo_hiểm",
      "trải_nghiệm",
      "biển_đảo",
      "tâm_linh",
      "lịch_sử"
    ],
    "duration": "4 ngày 3 đêm",
    "duration_days": 4,
    "price_text": "Giá theo yêu cầu đoàn; đã bao gồm 6 bữa chính (150.000đ/suất), 1 bữa đặc sản miền Trung (200.000đ/suất), khách sạn 3*, vận chuyển và vé tham quan.",
    "min_price": 150000,
    "max_price": 200000,
    "avg_price": 175000,
    "embedding_text": "Tham quan – Trải nghiệm Bình Trị Thiên (04 ngày 03 đêm) Hành trình 4N3Đ khám phá ba vùng đất giàu di sản: Huế – Quảng Trị – Quảng Bình. Từ vẻ đẹp trầm mặc của cố đô, dấu ấn lịch sử oanh liệt tại DMZ đến kỳ quan thiên nhiên Phong Nha và biển Nhật Lệ. Một hành trình kết hợp văn hoá – tâm linh – thiên nhiên – lịch sử đặc sắc. Huế – Quảng Trị – Quảng Bình Du lịch văn hoá – tâm linh – lịch sử – thiên nhiên. Hành trình nhịp chậm, giàu cảm xúc, kết nối di sản cố đô, ký ức chiến tranh và kỳ quan thiên nhiên miền Trung. Xe chất lượng cao phục vụ trọn tuyến Huế – Quảng Trị – Quảng Bình. 6 bữa chính tiêu chuẩn 150.000đ/suất; 01 bữa đặc sản miền Trung tiêu chuẩn 200.000đ/suất; ăn sáng tại khách sạn. Khách sạn hoặc resort tiêu chuẩn 3*: 2 khách/phòng; trường hợp lẻ nam/nữ ngủ phòng 3. Hướng dẫn viên chuyên nghiệp – am hiểu văn hoá – lịch sử vùng Bình Trị Thiên. Vé tham quan các điểm theo chương trình: Chùa Thiên Mụ, Đại Nội, Lăng Minh Mạng, Lăng Khải Định, La Vang, Thành Cổ Quảng Trị, Nghĩa trang Trường Sơn, Cầu Hiền Lương – Bến Hải, Địa đạo Vịnh Mốc, Động Phong Nha, Vũng Chùa (mộ Đại tướng Võ Nguyên Giáp), Quảng Bình Quan… Khăn lạnh – nước uống suốt hành trình. Quà tặng: Nón du lịch hoặc ba lô tiện lợi. Bảo hiểm du lịch theo luật Du lịch Việt Nam. Không bao gồm: bia/nước ngọt bữa ăn; giặt ủi; phòng đơn +400.000đ/khách; tip HDV & lái xe; VAT. Huỷ tour: Trước 10 ngày: 30%; 5–10 ngày: 50%; 3–5 ngày: 75%; dưới 3 ngày: 100%. Trẻ em: dưới 4 tuổi miễn phí; 4–8 tuổi: 50%; 8–11 tuổi: 75%; từ 11 tuổi tính như người lớn. 4 ngày 3 đêm Giá theo yêu cầu đoàn; đã bao gồm 6 bữa chính (150.000đ/suất), 1 bữa đặc sản miền Trung (200.000đ/suất), khách sạn 3*, vận chuyển và vé tham quan. Khách sạn hoặc resort 3* tại Huế – Đông Hà – Đồng Hới (2 khách/phòng, lẻ ngủ phòng 3). 6 bữa chính tiêu chuẩn 150.000đ/suất; 1 bữa đặc sản miền Trung 200.000đ/suất; ăn sáng tại khách sạn. ['Xe du lịch 16–45 chỗ đời mới'] Hỗ trợ đoàn trong suốt hành trình: theo sát lịch trình – điều phối giờ giấc – hỗ trợ chụp ảnh – ghi nhận nhu cầu cá nhân; kiểm soát an toàn điểm đến; nhắc nhở sức khỏe – trang phục – di chuyển; hỗ trợ xử lý tình huống phát sinh; đồng hành kết nối tập thể; tối ưu trải nghiệm khách hàng theo chuẩn Ruby Wings.",
    "popularity_score": 0.87,
    "value_score": 0.8,
    "family_friendly": true,
    "senior_friendly": false,
    "corporate_friendly": false,
    "summary": "Hành trình 4N3Đ khám phá ba vùng đất giàu di sản: Huế – Quảng Trị – Quảng Bình. Từ vẻ đẹp trầm mặc của cố đô, dấu ấn lịch sử oanh liệt tại DMZ đến kỳ quan thiên nhiên Phong Nha và biển Nhật Lệ. Một hành trình kết hợp văn hoá – tâm linh – thiên nhiên – lịch sử đặc sắc.",
    "style": "Du lịch văn hoá – tâm linh – lịch sử – thiên nhiên. Hành trình nhịp chậm, giàu cảm xúc, kết nối di sản cố đô, ký ức chiến tranh và kỳ quan thiên nhiên miền Trung.",
    "includes": [
      "Xe chất lượng cao phục vụ trọn tuyến Huế – Quảng Trị – Quảng Bình.",
      "6 bữa chính tiêu chuẩn 150.000đ/suất; 01 bữa đặc sản miền Trung tiêu chuẩn 200.000đ/suất; ăn sáng tại khách sạn.",
      "Khách sạn hoặc resort tiêu chuẩn 3*: 2 khách/phòng; trường hợp lẻ nam/nữ ngủ phòng 3.",
      "Hướng dẫn viên chuyên nghiệp – am hiểu văn hoá – lịch sử vùng Bình Trị Thiên.",
      "Vé tham quan các điểm theo chương trình: Chùa Thiên Mụ, Đại Nội, Lăng Minh Mạng, Lăng Khải Định, La Vang, Thành Cổ Quảng Trị, Nghĩa trang Trường Sơn, Cầu Hiền Lương – Bến Hải, Địa đạo Vịnh Mốc, Động Phong Nha, Vũng Chùa (mộ Đại tướng Võ Nguyên Giáp), Quảng Bình Quan…",
      "Khăn lạnh – nước uống suốt hành trình.",
      "Quà tặng: Nón du lịch hoặc ba lô tiện lợi.",
      "Bảo hiểm du lịch theo luật Du lịch Việt Nam."
    ],
    "notes": "Không bao gồm: bia/nước ngọt bữa ăn; giặt ủi; phòng đơn +400.000đ/khách; tip HDV & lái xe; VAT. Huỷ tour: Trước 10 ngày: 30%; 5–10 ngày: 50%; 3–5 ngày: 75%; dưới 3 ngày: 100%. Trẻ em: dưới 4 tuổi miễn phí; 4–8 tuổi: 50%; 8–11 tuổi: 75%; từ 11 tuổi tính như người lớn.",
    "transport": [
      "Xe du lịch 16–45 chỗ đời mới"
    ],
    "accommodation": "Khách sạn hoặc resort 3* tại Huế – Đông Hà – Đồng Hới (2 khách/phòng, lẻ ngủ phòng 3).",
    "meals": "6 bữa chính tiêu chuẩn 150.000đ/suất; 1 bữa đặc sản miền Trung 200.000đ/suất; ăn sáng tại khách sạn.",
    "event_support": "Hỗ trợ đoàn trong suốt hành trình: theo sát lịch trình – điều phối giờ giấc – hỗ trợ chụp ảnh – ghi nhận nhu cầu cá nhân; kiểm soát an toàn điểm đến; nhắc nhở sức khỏe – trang phục – di chuyển; hỗ trợ xử lý tình huống phát sinh; đồng hành kết nối tập thể; tối ưu trải nghiệm khách hàng theo chuẩn Ruby Wings.",
    "created_at": "2026-01-16T09:07:10.068797Z",
    "last_updated": "2026-01-16T09:07:10.068797Z"
  },
  "tour_015": {
    "tour_id": "tour_015",
    "index": 15,
    "tour_name": "Khám phá Khe Sanh – Tiểu Đà Lạt giữa đại ngàn Trường Sơn (2 ngày 1 đêm)",
    "location": "Đông Hà – Khe Sanh – Sa Mù – Cửa Việt",
    "region": "Miền Trung",
    "tags": [
      "2_ngày",
      "du_lịch_xanh",
      "thiên_nhiên",
      "mạo_hiểm",
      "trải_nghiệm",
      "biển_đảo",
      "lịch_sử",
      "văn_hóa"
    ],
    "duration": "2 ngày 1 đêm",
    "duration_days": 2,
    "price_text": "1.285.000 – 1.485.000 VNĐ/người (phụ thuộc số lượng khách và loại xe)",
    "min_price": 1285000,
    "max_price": 1485000,
    "avg_price": 1385000,
    "embedding_text": "Khám phá Khe Sanh – Tiểu Đà Lạt giữa đại ngàn Trường Sơn (2 ngày 1 đêm) Hành trình 2 ngày 1 đêm khám phá Khe Sanh mát lạnh, trải nghiệm bản làng Pa Cô – Vân Kiều, đồi cà phê – hồ tiêu, đèo Sa Mù và nét chuyển mình của vùng đất lửa. Đông Hà – Khe Sanh – Sa Mù – Cửa Việt Khám phá thiên nhiên – văn hóa bản địa – khí hậu đại ngàn – lịch sử. Khí hậu mát mẻ quanh năm – 'tiểu Đà Lạt' của Quảng Trị Khám phá đồi cà phê – hồ tiêu – bản làng Pa Cô – Vân Kiều Check-in Đèo Sa Mù huyền ảo Thưởng thức ẩm thực dân tộc Pa Cô – Vân Kiều Ngắm hệ thống điện gió và cảnh quan đại ngàn Ngày 1: Đông Hà – Khe Sanh – Sa Mù (sáng, trưa, tối) Ngày 2: Sa Mù – Khe Sanh – Cửa Việt – Trả khách (sáng, trưa, chiều) Lưu ý về trang phục, sức khỏe, an toàn di chuyển; chuẩn bị giấy tờ tùy thân; tuân thủ hướng dẫn của HDV; bảo vệ môi trường tại điểm đến; hạn chế mang đồ công nghệ không cần thiết; có mặt đúng giờ theo lịch trình; một số hoạt động có thể thay đổi tùy điều kiện thời tiết hoặc quy định địa phương 2 ngày 1 đêm 1.285.000 – 1.485.000 VNĐ/người (phụ thuộc số lượng khách và loại xe) Lưu trú tại Khe Sanh (nhà nghỉ/khách sạn/homestay tiêu chuẩn từ 3*) ăn 3 bữa chính tiêu chuẩn 150.000 VNĐ/khách (01 bữa tăng cường nếu có giao lưu: 200.000VNĐ/khách), ăn theo thực đơn ưu tiên đặc sản địa phương, nước uống suốt hành trình Xe từ 16 chỗ đến 45 chỗ tuỳ số lượng khách, bảo đảm xe đời mới, chất lượng cao Hỗ trợ đoàn trong suốt hành trình: theo sát lịch trình – điều phối giờ giấc – hỗ trợ chụp ảnh – ghi nhận nhu cầu cá nhân; kiểm soát an toàn điểm đến; nhắc nhở sức khỏe – trang phục – di chuyển; hỗ trợ xử lý tình huống phát sinh; đồng hành kết nối tập thể; tối ưu trải nghiệm khách hàng theo chuẩn Ruby Wings.",
    "popularity_score": 0.86,
    "value_score": 0.8,
    "family_friendly": false,
    "senior_friendly": false,
    "corporate_friendly": false,
    "summary": "Hành trình 2 ngày 1 đêm khám phá Khe Sanh mát lạnh, trải nghiệm bản làng Pa Cô – Vân Kiều, đồi cà phê – hồ tiêu, đèo Sa Mù và nét chuyển mình của vùng đất lửa.",
    "style": "Khám phá thiên nhiên – văn hóa bản địa – khí hậu đại ngàn – lịch sử.",
    "includes": [
      "Khí hậu mát mẻ quanh năm – 'tiểu Đà Lạt' của Quảng Trị",
      "Khám phá đồi cà phê – hồ tiêu – bản làng Pa Cô – Vân Kiều",
      "Check-in Đèo Sa Mù huyền ảo",
      "Thưởng thức ẩm thực dân tộc Pa Cô – Vân Kiều",
      "Ngắm hệ thống điện gió và cảnh quan đại ngàn",
      "Ngày 1: Đông Hà – Khe Sanh – Sa Mù (sáng, trưa, tối)",
      "Ngày 2: Sa Mù – Khe Sanh – Cửa Việt – Trả khách (sáng, trưa, chiều)"
    ],
    "notes": "Lưu ý về trang phục, sức khỏe, an toàn di chuyển; chuẩn bị giấy tờ tùy thân; tuân thủ hướng dẫn của HDV; bảo vệ môi trường tại điểm đến; hạn chế mang đồ công nghệ không cần thiết; có mặt đúng giờ theo lịch trình; một số hoạt động có thể thay đổi tùy điều kiện thời tiết hoặc quy định địa phương",
    "transport": "Xe từ 16 chỗ đến 45 chỗ tuỳ số lượng khách, bảo đảm xe đời mới, chất lượng cao",
    "accommodation": "Lưu trú tại Khe Sanh (nhà nghỉ/khách sạn/homestay tiêu chuẩn từ 3*)",
    "meals": "ăn 3 bữa chính tiêu chuẩn 150.000 VNĐ/khách (01 bữa tăng cường nếu có giao lưu: 200.000VNĐ/khách), ăn theo thực đơn ưu tiên đặc sản địa phương, nước uống suốt hành trình",
    "event_support": "Hỗ trợ đoàn trong suốt hành trình: theo sát lịch trình – điều phối giờ giấc – hỗ trợ chụp ảnh – ghi nhận nhu cầu cá nhân; kiểm soát an toàn điểm đến; nhắc nhở sức khỏe – trang phục – di chuyển; hỗ trợ xử lý tình huống phát sinh; đồng hành kết nối tập thể; tối ưu trải nghiệm khách hàng theo chuẩn Ruby Wings.",
    "created_at": "2026-01-16T09:07:10.068797Z",
    "last_updated": "2026-01-16T09:07:10.068797Z"
  },
  "tour_016": {
    "tour_id": "tour_016",
    "index": 16,
    "tour_name": "Khám phá miền đất trù phú Phương Nam",
    "location": "TP.HCM – Bình Dương – Cần Thơ – Sóc Trăng – Cà Mau – Đồng Tháp",
    "region": "Miền Nam",
    "tags": [
      "trải_nghiệm",
      "thiên_nhiên",
      "du_lịch_xanh",
      "mạo_hiểm"
    ],
    "duration": "6 ngày 5 đêm",
    "duration_days": 6,
    "price_text": "Giá sẽ được cập nhật sau và phụ thuộc vào nhiều yếu tố: số lượng khách, thời điểm khởi hành, cấp độ dịch vụ lựa chọn (cơ bản – nâng cao – cao cấp), hạng phương tiện, tiêu chuẩn lưu trú – ăn uống, vé tham quan và các yêu cầu tùy chỉnh theo nhóm. Khi chốt đủ thông tin, Ruby Wings sẽ gửi báo giá chi tiết",
    "min_price": 500000,
    "max_price": 1500000,
    "avg_price": 1000000,
    "embedding_text": "Khám phá miền đất trù phú Phương Nam Hành trình 6 ngày 5 đêm khám phá Thành phố Hồ Chí Minh, Bình Dương, miền Tây sông nước và mũi Cà Mau – kết hợp văn hoá, sinh thái, ẩm thực và trải nghiệm đặc sắc. TP.HCM – Bình Dương – Cần Thơ – Sóc Trăng – Cà Mau – Đồng Tháp Khám phá đô thị – sinh thái – văn hoá – ẩm thực; nhịp độ vừa phải, phù hợp đa dạng đối tượng. Tham quan Đại Nam (Bình Dương) Khám phá Dinh Độc Lập – TP.HCM Du thuyền sông rạch Cần Thơ – chợ nổi – vườn trái Khám phá rừng ngập mặn Cà Mau – Đất Mũi Tham quan Đồng Tháp – xứ sở sen Ngày 1: Đông Hà – Huế – TP.HCM (sáng/trưa/tối) Ngày 2: TP.HCM – Bình Dương – Đại Nam (sáng/trưa/tối) Ngày 3: Thủ Dầu Một – Cần Thơ (sáng/trưa/tối) Ngày 4: Cần Thơ – Sóc Trăng – Cà Mau (sáng/trưa/tối) Ngày 5: Cà Mau – Đất Mũi – Đồng Tháp (sáng/trưa/tối) Ngày 6: Đồng Tháp – TP.HCM (sáng/trưa/--) Lưu ý về trang phục, sức khỏe, an toàn di chuyển; chuẩn bị giấy tờ tùy thân; tuân thủ hướng dẫn của HDV; bảo vệ môi trường tại điểm đến; hạn chế mang đồ công nghệ không cần thiết; có mặt đúng giờ theo lịch trình; một số hoạt động có thể thay đổi tùy điều kiện thời tiết hoặc quy định địa phương 6 ngày 5 đêm Giá sẽ được cập nhật sau và phụ thuộc vào nhiều yếu tố: số lượng khách, thời điểm khởi hành, cấp độ dịch vụ lựa chọn (cơ bản – nâng cao – cao cấp), hạng phương tiện, tiêu chuẩn lưu trú – ăn uống, vé tham quan và các yêu cầu tùy chỉnh theo nhóm. Khi chốt đủ thông tin, Ruby Wings sẽ gửi báo giá chi tiết Lưu trú 5 đêm theo tiêu chuẩn chương trình ăn tiêu chuẩn 150.000 VNĐ/khách (có 1-2 bữa đặc sản 200.000VNĐ/khách nếu có), ăn theo thực đơn đặc sản địa phương, nước uống suốt hành trình Xe từ 16 chỗ đến 45 chỗ tuỳ số lượng khách, bảo đảm xe đời mới, chất lượng cao Hỗ trợ đoàn trong suốt hành trình: theo sát lịch trình – điều phối giờ giấc – hỗ trợ chụp ảnh – ghi nhận nhu cầu cá nhân; kiểm soát an toàn điểm đến; nhắc nhở sức khỏe – trang phục – di chuyển; hỗ trợ xử lý tình huống phát sinh; đồng hành kết nối tập thể; tối ưu trải nghiệm khách hàng theo chuẩn Ruby Wings.",
    "popularity_score": 0.85,
    "value_score": 0.8,
    "family_friendly": false,
    "senior_friendly": false,
    "corporate_friendly": false,
    "summary": "Hành trình 6 ngày 5 đêm khám phá Thành phố Hồ Chí Minh, Bình Dương, miền Tây sông nước và mũi Cà Mau – kết hợp văn hoá, sinh thái, ẩm thực và trải nghiệm đặc sắc.",
    "style": "Khám phá đô thị – sinh thái – văn hoá – ẩm thực; nhịp độ vừa phải, phù hợp đa dạng đối tượng.",
    "includes": [
      "Tham quan Đại Nam (Bình Dương)",
      "Khám phá Dinh Độc Lập – TP.HCM",
      "Du thuyền sông rạch Cần Thơ – chợ nổi – vườn trái",
      "Khám phá rừng ngập mặn Cà Mau – Đất Mũi",
      "Tham quan Đồng Tháp – xứ sở sen",
      "Ngày 1: Đông Hà – Huế – TP.HCM (sáng/trưa/tối)",
      "Ngày 2: TP.HCM – Bình Dương – Đại Nam (sáng/trưa/tối)",
      "Ngày 3: Thủ Dầu Một – Cần Thơ (sáng/trưa/tối)",
      "Ngày 4: Cần Thơ – Sóc Trăng – Cà Mau (sáng/trưa/tối)",
      "Ngày 5: Cà Mau – Đất Mũi – Đồng Tháp (sáng/trưa/tối)",
      "Ngày 6: Đồng Tháp – TP.HCM (sáng/trưa/--)"
    ],
    "notes": "Lưu ý về trang phục, sức khỏe, an toàn di chuyển; chuẩn bị giấy tờ tùy thân; tuân thủ hướng dẫn của HDV; bảo vệ môi trường tại điểm đến; hạn chế mang đồ công nghệ không cần thiết; có mặt đúng giờ theo lịch trình; một số hoạt động có thể thay đổi tùy điều kiện thời tiết hoặc quy định địa phương",
    "transport": "Xe từ 16 chỗ đến 45 chỗ tuỳ số lượng khách, bảo đảm xe đời mới, chất lượng cao",
    "accommodation": "Lưu trú 5 đêm theo tiêu chuẩn chương trình",
    "meals": "ăn tiêu chuẩn 150.000 VNĐ/khách (có 1-2 bữa đặc sản 200.000VNĐ/khách nếu có), ăn theo thực đơn đặc sản địa phương, nước uống suốt hành trình",
    "event_support": "Hỗ trợ đoàn trong suốt hành trình: theo sát lịch trình – điều phối giờ giấc – hỗ trợ chụp ảnh – ghi nhận nhu cầu cá nhân; kiểm soát an toàn điểm đến; nhắc nhở sức khỏe – trang phục – di chuyển; hỗ trợ xử lý tình huống phát sinh; đồng hành kết nối tập thể; tối ưu trải nghiệm khách hàng theo chuẩn Ruby Wings.",
    "created_at": "2026-01-16T09:07:10.068797Z",
    "last_updated": "2026-01-16T09:07:10.068797Z"
  },
  "tour_017": {
    "tour_id": "tour_017",
    "index": 17,
    "tour_name": "Hành Trình Phong Hương – Bình Yên Giữa Núi Rừng Trường Sơn (2 ngày 1 đêm)",
    "location": "Huế – Thành Cổ Quảng Trị – Khe Sanh – Trường Sơn – Đakrông – La Vang – Huế",
    "region": "Miền Trung",
    "tags": [
      "thiền",
      "2_ngày",
      "lửa_trại",
      "gia_đình",
      "cao_cấp",
      "retreat",
      "thiên_nhiên",
      "mạo_hiểm",
      "trải_nghiệm",
      "tâm_linh",
      "lịch_sử",
      "văn_hóa"
    ],
    "duration": "2 ngày 1 đêm",
    "duration_days": 2,
    "price_text": "1.990.000 – 2.400.000 VNĐ/khách",
    "min_price": 1990000,
    "max_price": 2400000,
    "avg_price": 2195000,
    "embedding_text": "Hành Trình Phong Hương – Bình Yên Giữa Núi Rừng Trường Sơn (2 ngày 1 đêm) Hành trình 2 ngày 1 đêm khám phá vẻ đẹp nguyên sơ của Tây Trường Sơn, kết hợp trải nghiệm lịch sử – thiên nhiên – văn hóa bản địa và thực hành thiền – khí công giữa núi rừng. Chuyến đi mang lại sự thư giãn, kết nối nội tâm và tri ân những giá trị lịch sử thiêng liêng. Huế – Thành Cổ Quảng Trị – Khe Sanh – Trường Sơn – Đakrông – La Vang – Huế Trải nghiệm thiên nhiên – lịch sử – chữa lành; nhịp đi chậm, sâu; kết hợp giao lưu văn hóa bản địa và thực hành thiền – khí công; phù hợp nhóm gia đình, cộng đồng, đoàn trải nghiệm. Xe du lịch đời mới, máy lạnh, lái xe chuyên nghiệp phục vụ suốt hành trình 01 đêm homestay tại Khe Sanh/Hướng Hóa, đầy đủ tiện nghi cơ bản, có ăn sáng 02 bữa sáng, 02 bữa trưa, 01 bữa tối theo chương trình (tiêu chuẩn 150.000 VNĐ/suất) Vé tham quan các điểm theo chương trình (01 lần vào cửa) Tham quan Thành Cổ Quảng Trị, sân bay Tà Cơn – Bảo tàng Khe Sanh Du thuyền hồ Rào Quán, check-in Cây Cô Đơn, cánh đồng điện gió Giao lưu văn hóa cộng đồng: lửa trại, cồng chiêng, bánh Ayớh, rượu cần Thực hành thiền – khí công buổi sáng giữa thiên nhiên Trường Sơn Tham quan Danh thắng Đakrông và Thánh địa La Vang Hướng dẫn viên chuyên nghiệp, am hiểu lịch sử – văn hóa địa phương Bảo hiểm du lịch theo quy định (mức 50.000.000 VNĐ/khách) Nước uống phục vụ suốt hành trình Quà tặng: mũ/nón du lịch Ruby Wings Chụp ảnh, tổng hợp hình ảnh & video thành slideshow/clip kỷ niệm Thời gian có thể điều chỉnh linh hoạt theo điều kiện thực tế nhưng vẫn đảm bảo đầy đủ điểm tham quan. Không bao gồm VAT, chi phí cá nhân, đồ uống ngoài chương trình, tiền tip HDV & lái xe, dịch vụ quay/chụp chuyên nghiệp nâng cao. Các chi phí phát sinh do yếu tố bất khả kháng không nằm trong giá tour. 2 ngày 1 đêm 1.990.000 – 2.400.000 VNĐ/khách Homestay Khe Sanh/Hướng Hóa, tiêu chuẩn sạch sẽ, tiện nghi cơ bản 02 bữa sáng, 02 bữa trưa, 01 bữa tối theo chương trình (150.000 VNĐ/suất); nước uống đầy đủ Xe du lịch từ 16 chỗ đến 45 chỗ tùy số lượng khách, xe đời mới chất lượng cao Hỗ trợ đoàn xuyên suốt hành trình: điều phối lịch trình, tổ chức giao lưu văn hóa – lửa trại, hướng dẫn thiền – khí công cơ bản, hỗ trợ chụp ảnh, đảm bảo an toàn và tối ưu trải nghiệm theo chuẩn Ruby Wings.",
    "popularity_score": 0.84,
    "value_score": 0.6,
    "family_friendly": true,
    "senior_friendly": false,
    "corporate_friendly": false,
    "summary": "Hành trình 2 ngày 1 đêm khám phá vẻ đẹp nguyên sơ của Tây Trường Sơn, kết hợp trải nghiệm lịch sử – thiên nhiên – văn hóa bản địa và thực hành thiền – khí công giữa núi rừng. Chuyến đi mang lại sự thư giãn, kết nối nội tâm và tri ân những giá trị lịch sử thiêng liêng.",
    "style": "Trải nghiệm thiên nhiên – lịch sử – chữa lành; nhịp đi chậm, sâu; kết hợp giao lưu văn hóa bản địa và thực hành thiền – khí công; phù hợp nhóm gia đình, cộng đồng, đoàn trải nghiệm.",
    "includes": [
      "Xe du lịch đời mới, máy lạnh, lái xe chuyên nghiệp phục vụ suốt hành trình",
      "01 đêm homestay tại Khe Sanh/Hướng Hóa, đầy đủ tiện nghi cơ bản, có ăn sáng",
      "02 bữa sáng, 02 bữa trưa, 01 bữa tối theo chương trình (tiêu chuẩn 150.000 VNĐ/suất)",
      "Vé tham quan các điểm theo chương trình (01 lần vào cửa)",
      "Tham quan Thành Cổ Quảng Trị, sân bay Tà Cơn – Bảo tàng Khe Sanh",
      "Du thuyền hồ Rào Quán, check-in Cây Cô Đơn, cánh đồng điện gió",
      "Giao lưu văn hóa cộng đồng: lửa trại, cồng chiêng, bánh Ayớh, rượu cần",
      "Thực hành thiền – khí công buổi sáng giữa thiên nhiên Trường Sơn",
      "Tham quan Danh thắng Đakrông và Thánh địa La Vang",
      "Hướng dẫn viên chuyên nghiệp, am hiểu lịch sử – văn hóa địa phương",
      "Bảo hiểm du lịch theo quy định (mức 50.000.000 VNĐ/khách)",
      "Nước uống phục vụ suốt hành trình",
      "Quà tặng: mũ/nón du lịch Ruby Wings",
      "Chụp ảnh, tổng hợp hình ảnh & video thành slideshow/clip kỷ niệm"
    ],
    "notes": "Thời gian có thể điều chỉnh linh hoạt theo điều kiện thực tế nhưng vẫn đảm bảo đầy đủ điểm tham quan. Không bao gồm VAT, chi phí cá nhân, đồ uống ngoài chương trình, tiền tip HDV & lái xe, dịch vụ quay/chụp chuyên nghiệp nâng cao. Các chi phí phát sinh do yếu tố bất khả kháng không nằm trong giá tour.",
    "transport": "Xe du lịch từ 16 chỗ đến 45 chỗ tùy số lượng khách, xe đời mới chất lượng cao",
    "accommodation": "Homestay Khe Sanh/Hướng Hóa, tiêu chuẩn sạch sẽ, tiện nghi cơ bản",
    "meals": "02 bữa sáng, 02 bữa trưa, 01 bữa tối theo chương trình (150.000 VNĐ/suất); nước uống đầy đủ",
    "event_support": "Hỗ trợ đoàn xuyên suốt hành trình: điều phối lịch trình, tổ chức giao lưu văn hóa – lửa trại, hướng dẫn thiền – khí công cơ bản, hỗ trợ chụp ảnh, đảm bảo an toàn và tối ưu trải nghiệm theo chuẩn Ruby Wings.",
    "created_at": "2026-01-16T09:07:10.068797Z",
    "last_updated": "2026-01-16T09:07:10.068797Z"
  },
  "tour_018": {
    "tour_id": "tour_018",
    "index": 18,
    "tour_name": "Tour trải nghiệm linh hoạt – Đông Hà – Ninh Bình – Hạ Long – Đông Hà (4 ngày)",
    "location": "Đông Hà – Ninh Bình – Hạ Long – Hà Nội",
    "region": "Miền Bắc",
    "tags": [
      "cao_cấp",
      "thiên_nhiên",
      "trải_nghiệm",
      "biển_đảo",
      "văn_hóa"
    ],
    "duration": "4 ngày 3 đêm",
    "duration_days": 4,
    "price_text": "4.995.000 VNĐ/khách (tham khảo đoàn 35 khách, phụ thuộc mùa và yêu cầu nâng cấp dịch vụ)",
    "min_price": 4995000,
    "max_price": 4995000,
    "avg_price": 4995000,
    "embedding_text": "Tour trải nghiệm linh hoạt – Đông Hà – Ninh Bình – Hạ Long – Đông Hà (4 ngày) Hành trình liên vùng 4 ngày 3 đêm kết hợp văn hóa Ninh Bình, di sản Hạ Long, vui chơi Sun World và trải nghiệm xe giường nằm + xe du lịch cao cấp. Đông Hà – Ninh Bình – Hạ Long – Hà Nội Di sản – biển – giải trí – trải nghiệm tiện nghi. Chùa Bái Đính – quần thể chùa lớn nhất Đông Nam Á Tràng An – di sản thiên nhiên & văn hoá thế giới Tam Cốc – thuyền sông Ngô Đồng Sun World Hạ Long – cáp treo Nữ Hoàng – Sun Wheel Bãi Cháy – tắm biển – dạo biển về đêm Ngày 0: Đông Hà → Ninh Bình (xe giường nằm) Ngày 1: Ninh Bình – Bái Đính – Tràng An – Tam Cốc Ngày 2: Tam Chúc – Hạ Long (sáng/trưa/tối) Ngày 3: Hạ Long – Hà Nội – xe giường nằm về Quảng Trị Ngày 4: Về đến Quảng Trị (kết thúc) Giá thay đổi theo mùa, số lượng khách và yêu cầu nâng cấp dịch vụ. 4 ngày 3 đêm 4.995.000 VNĐ/khách (tham khảo đoàn 35 khách, phụ thuộc mùa và yêu cầu nâng cấp dịch vụ) Khách sạn 3* (theo chương trình), ngủ đêm trên xe giường nằm 2 khách/phòng 6 bữa chính (5 bữa 150k, 1 bữa 200k hoặc bữa trên du thuyền 5*), ăn theo thực đơn địa phương, nước uống suốt hành trình Xe từ 16 chỗ đến 45 chỗ tuỳ số lượng khách, bảo đảm xe đời mới, chất lượng cao Hỗ trợ đoàn trong suốt hành trình: theo sát lịch trình – điều phối giờ giấc – hỗ trợ chụp ảnh – ghi nhận nhu cầu cá nhân; kiểm soát an toàn điểm đến; nhắc nhở sức khỏe – trang phục – di chuyển; hỗ trợ xử lý tình huống phát sinh; đồng hành kết nối tập thể; tối ưu trải nghiệm khách hàng theo chuẩn Ruby Wings.",
    "popularity_score": 0.83,
    "value_score": 0.6,
    "family_friendly": false,
    "senior_friendly": false,
    "corporate_friendly": false,
    "summary": "Hành trình liên vùng 4 ngày 3 đêm kết hợp văn hóa Ninh Bình, di sản Hạ Long, vui chơi Sun World và trải nghiệm xe giường nằm + xe du lịch cao cấp.",
    "style": "Di sản – biển – giải trí – trải nghiệm tiện nghi.",
    "includes": [
      "Chùa Bái Đính – quần thể chùa lớn nhất Đông Nam Á",
      "Tràng An – di sản thiên nhiên & văn hoá thế giới",
      "Tam Cốc – thuyền sông Ngô Đồng",
      "Sun World Hạ Long – cáp treo Nữ Hoàng – Sun Wheel",
      "Bãi Cháy – tắm biển – dạo biển về đêm",
      "Ngày 0: Đông Hà → Ninh Bình (xe giường nằm)",
      "Ngày 1: Ninh Bình – Bái Đính – Tràng An – Tam Cốc",
      "Ngày 2: Tam Chúc – Hạ Long (sáng/trưa/tối)",
      "Ngày 3: Hạ Long – Hà Nội – xe giường nằm về Quảng Trị",
      "Ngày 4: Về đến Quảng Trị (kết thúc)"
    ],
    "notes": "Giá thay đổi theo mùa, số lượng khách và yêu cầu nâng cấp dịch vụ.",
    "transport": "Xe từ 16 chỗ đến 45 chỗ tuỳ số lượng khách, bảo đảm xe đời mới, chất lượng cao",
    "accommodation": "Khách sạn 3* (theo chương trình), ngủ đêm trên xe giường nằm 2 khách/phòng",
    "meals": "6 bữa chính (5 bữa 150k, 1 bữa 200k hoặc bữa trên du thuyền 5*), ăn theo thực đơn địa phương, nước uống suốt hành trình",
    "event_support": "Hỗ trợ đoàn trong suốt hành trình: theo sát lịch trình – điều phối giờ giấc – hỗ trợ chụp ảnh – ghi nhận nhu cầu cá nhân; kiểm soát an toàn điểm đến; nhắc nhở sức khỏe – trang phục – di chuyển; hỗ trợ xử lý tình huống phát sinh; đồng hành kết nối tập thể; tối ưu trải nghiệm khách hàng theo chuẩn Ruby Wings.",
    "created_at": "2026-01-16T09:07:10.069814Z",
    "last_updated": "2026-01-16T09:07:10.069814Z"
  },
  "tour_019": {
    "tour_id": "tour_019",
    "index": 19,
    "tour_name": "Trải Nghiệm Tinh Hoa Bắc Bộ: Hà Nội – Sa Pa – Phú Thọ (5 ngày 4 đêm)",
    "location": "Quảng Trị – Hà Nội – Sa Pa (Lào Cai) – Phú Thọ – Hà Nội – Quảng Trị",
    "region": "Miền Bắc",
    "tags": [
      "gia_đình",
      "thiên_nhiên",
      "mạo_hiểm",
      "trải_nghiệm",
      "lịch_sử",
      "văn_hóa"
    ],
    "duration": "5 ngày 4 đêm",
    "duration_days": 5,
    "price_text": "5.070.000 – 5.220.000 VNĐ/khách (tùy quy mô đoàn 33–42 khách)",
    "min_price": 5070000,
    "max_price": 5220000,
    "avg_price": 5145000,
    "embedding_text": "Trải Nghiệm Tinh Hoa Bắc Bộ: Hà Nội – Sa Pa – Phú Thọ (5 ngày 4 đêm) Hành trình 5 ngày 4 đêm khám phá tinh hoa Bắc Bộ: Thủ đô Hà Nội ngàn năm văn hiến, chinh phục Fansipan – Nóc nhà Đông Dương, trải nghiệm văn hóa Sa Pa và dâng hương Đền Hùng – cội nguồn dân tộc Việt. Chương trình kết hợp thiên nhiên – văn hóa – lịch sử, phù hợp Quý thầy cô và các đoàn giáo dục. Quảng Trị – Hà Nội – Sa Pa (Lào Cai) – Phú Thọ – Hà Nội – Quảng Trị Trải nghiệm văn hóa – lịch sử – thiên nhiên; kết hợp chinh phục Fansipan, khám phá Sa Pa và hành hương về cội nguồn Đền Hùng; nhịp đi phù hợp Quý thầy cô và các đoàn giáo dục. Tàu hỏa SE4 chiều Quảng Trị – Hà Nội và SE5 chiều Hà Nội – Quảng Trị (hoặc xe giường nằm theo phương án tổ chức) Xe du lịch 35 chỗ đời mới (2022–2025) phục vụ theo chương trình Khách sạn tiêu chuẩn 3* tại Sa Pa, Phú Thọ và Hà Nội (ăn sáng tại khách sạn; bữa đầu ăn phở Hà Nội) 06 bữa chính theo chương trình (05 bữa tiêu chuẩn 150.000 VNĐ/suất; 01 bữa đặc sản 200.000 VNĐ/suất) Hướng dẫn viên chuyên nghiệp, có khả năng hoạt náo, theo đoàn suốt hành trình Tổ chức Gala với sân khấu, âm thanh, ánh sáng tại khách sạn đêm cuối Tham quan Nhà thờ đá Sa Pa, Fansipan, Đèo Ô Quy Hồ, Bản Cát Cát, Chợ đêm Sa Pa Tham quan Đền Hùng – Phú Thọ; Hồ Gươm – Đền Ngọc Sơn Vé tham quan vào cửa đầu tiên theo chương trình (vé Fansipan theo quy định) Nước uống, nón du lịch, khăn lạnh Bảo hiểm du lịch theo quy định Chương trình có thể hoán đổi thứ tự điểm tham quan nhưng vẫn đảm bảo đầy đủ nội dung. Không bao gồm VAT, chi phí cá nhân, đồ uống ngoài bữa ăn, dịch vụ tự chọn, phụ thu phòng đơn, tiền tip HDV & lái xe, phụ thu lễ/tết/cuối tuần. Chính sách trẻ em và chính sách hủy tour áp dụng theo quy định chi tiết của chương trình. 5 ngày 4 đêm 5.070.000 – 5.220.000 VNĐ/khách (tùy quy mô đoàn 33–42 khách) Khách sạn tiêu chuẩn 3*; phòng 2 khách hoặc phòng 3 cho khách lẻ 06 bữa chính theo chương trình (150.000 VNĐ/suất; 01 bữa đặc sản 200.000 VNĐ/suất); ăn sáng tại khách sạn và theo chương trình Tàu hỏa đường dài và xe du lịch 35 chỗ đời mới phục vụ theo chương trình Hỗ trợ đoàn suốt hành trình: điều phối lịch trình, tổ chức Gala – giao lưu, hỗ trợ chụp ảnh, kiểm soát an toàn, xử lý tình huống phát sinh và đồng hành chăm sóc trải nghiệm theo chuẩn Ruby Wings.",
    "popularity_score": 0.82,
    "value_score": 0.6,
    "family_friendly": true,
    "senior_friendly": false,
    "corporate_friendly": false,
    "summary": "Hành trình 5 ngày 4 đêm khám phá tinh hoa Bắc Bộ: Thủ đô Hà Nội ngàn năm văn hiến, chinh phục Fansipan – Nóc nhà Đông Dương, trải nghiệm văn hóa Sa Pa và dâng hương Đền Hùng – cội nguồn dân tộc Việt. Chương trình kết hợp thiên nhiên – văn hóa – lịch sử, phù hợp Quý thầy cô và các đoàn giáo dục.",
    "style": "Trải nghiệm văn hóa – lịch sử – thiên nhiên; kết hợp chinh phục Fansipan, khám phá Sa Pa và hành hương về cội nguồn Đền Hùng; nhịp đi phù hợp Quý thầy cô và các đoàn giáo dục.",
    "includes": [
      "Tàu hỏa SE4 chiều Quảng Trị – Hà Nội và SE5 chiều Hà Nội – Quảng Trị (hoặc xe giường nằm theo phương án tổ chức)",
      "Xe du lịch 35 chỗ đời mới (2022–2025) phục vụ theo chương trình",
      "Khách sạn tiêu chuẩn 3* tại Sa Pa, Phú Thọ và Hà Nội (ăn sáng tại khách sạn; bữa đầu ăn phở Hà Nội)",
      "06 bữa chính theo chương trình (05 bữa tiêu chuẩn 150.000 VNĐ/suất; 01 bữa đặc sản 200.000 VNĐ/suất)",
      "Hướng dẫn viên chuyên nghiệp, có khả năng hoạt náo, theo đoàn suốt hành trình",
      "Tổ chức Gala với sân khấu, âm thanh, ánh sáng tại khách sạn đêm cuối",
      "Tham quan Nhà thờ đá Sa Pa, Fansipan, Đèo Ô Quy Hồ, Bản Cát Cát, Chợ đêm Sa Pa",
      "Tham quan Đền Hùng – Phú Thọ; Hồ Gươm – Đền Ngọc Sơn",
      "Vé tham quan vào cửa đầu tiên theo chương trình (vé Fansipan theo quy định)",
      "Nước uống, nón du lịch, khăn lạnh",
      "Bảo hiểm du lịch theo quy định"
    ],
    "notes": "Chương trình có thể hoán đổi thứ tự điểm tham quan nhưng vẫn đảm bảo đầy đủ nội dung. Không bao gồm VAT, chi phí cá nhân, đồ uống ngoài bữa ăn, dịch vụ tự chọn, phụ thu phòng đơn, tiền tip HDV & lái xe, phụ thu lễ/tết/cuối tuần. Chính sách trẻ em và chính sách hủy tour áp dụng theo quy định chi tiết của chương trình.",
    "transport": "Tàu hỏa đường dài và xe du lịch 35 chỗ đời mới phục vụ theo chương trình",
    "accommodation": "Khách sạn tiêu chuẩn 3*; phòng 2 khách hoặc phòng 3 cho khách lẻ",
    "meals": "06 bữa chính theo chương trình (150.000 VNĐ/suất; 01 bữa đặc sản 200.000 VNĐ/suất); ăn sáng tại khách sạn và theo chương trình",
    "event_support": "Hỗ trợ đoàn suốt hành trình: điều phối lịch trình, tổ chức Gala – giao lưu, hỗ trợ chụp ảnh, kiểm soát an toàn, xử lý tình huống phát sinh và đồng hành chăm sóc trải nghiệm theo chuẩn Ruby Wings.",
    "created_at": "2026-01-16T09:07:10.069814Z",
    "last_updated": "2026-01-16T09:07:10.069814Z"
  },
  "tour_020": {
    "tour_id": "tour_020",
    "index": 20,
    "tour_name": "Đông Hà – Nha Trang – Đà Lạt – Đông Hà",
    "location": "Đông Hà – Nha Trang – Đà Lạt",
    "region": "Miền Trung",
    "tags": [
      "thiền",
      "thiên_nhiên",
      "trải_nghiệm",
      "biển_đảo",
      "tâm_linh",
      "văn_hóa"
    ],
    "duration": "4 ngày 3 đêm",
    "duration_days": 4,
    "price_text": "Giá sẽ được cập nhật sau và phụ thuộc vào nhiều yếu tố: số lượng khách, thời điểm khởi hành, cấp độ dịch vụ lựa chọn (cơ bản – nâng cao – cao cấp), hạng phương tiện, tiêu chuẩn lưu trú – ăn uống, vé tham quan và các yêu cầu tùy chỉnh theo nhóm. Khi chốt đủ thông tin, Ruby Wings sẽ gửi báo giá chi tiết)",
    "min_price": 500000,
    "max_price": 1500000,
    "avg_price": 1000000,
    "embedding_text": "Đông Hà – Nha Trang – Đà Lạt – Đông Hà Hành trình 4 ngày 3 đêm đón Tết Nguyên Đán với biển Nha Trang và cao nguyên Đà Lạt; kết hợp tham quan Vinpearl Land, Tháp Bà Ponagar, Thiền viện Trúc Lâm, thác – chùa – dinh – vườn hoa và trải nghiệm văn hóa đặc sắc. Đông Hà – Nha Trang – Đà Lạt Biển – núi – văn hóa – tâm linh – trải nghiệm thành phố. Cáp treo Vinpearl Land – vui chơi hiện đại Tháp Bà Ponagar – văn hóa Champa Viện Hải Dương Học (tùy thời gian) Thác Datanla – trải nghiệm máng trượt tự túc Thiền Viện Trúc Lâm – Vườn hoa Thành phố Chùa Linh Phước – Dinh Bảo Đại (Dinh III) Ngày 1: Đông Hà → Nha Trang (Ăn trưa, tối) Ngày 2: Nha Trang → Vinpearl Land → Đà Lạt (Ăn sáng, trưa, tối) Ngày 3: Tham quan Đà Lạt (Ăn sáng, trưa, tối) Ngày 4: Đà Lạt → Đông Hà (Ăn sáng, trưa, tối) Mang trang phục phù hợp biển – núi – chùa; Tết đông khách nên đặt tour sớm. 4 ngày 3 đêm Giá sẽ được cập nhật sau và phụ thuộc vào nhiều yếu tố: số lượng khách, thời điểm khởi hành, cấp độ dịch vụ lựa chọn (cơ bản – nâng cao – cao cấp), hạng phương tiện, tiêu chuẩn lưu trú – ăn uống, vé tham quan và các yêu cầu tùy chỉnh theo nhóm. Khi chốt đủ thông tin, Ruby Wings sẽ gửi báo giá chi tiết) Khách sạn tiêu chuẩn tại Nha Trang và Đà Lạt (2 đêm) Ăn 3 bữa chính/ngày (tiêu chuẩn 150.000 VNĐ/suất) theo chương trình + sáng tại khách sạn; nước uống mỗi ngày Xe từ 16 chỗ đến 45 chỗ tuỳ số lượng khách, bảo đảm xe đời mới, chất lượng cao Hỗ trợ đoàn trong suốt hành trình: theo sát lịch trình – điều phối giờ giấc – hỗ trợ chụp ảnh – ghi nhận nhu cầu cá nhân; kiểm soát an toàn điểm đến; nhắc nhở sức khỏe – trang phục – di chuyển; hỗ trợ xử lý tình huống phát sinh; đồng hành kết nối tập thể; tối ưu trải nghiệm khách hàng theo chuẩn Ruby Wings.",
    "popularity_score": 0.81,
    "value_score": 0.8,
    "family_friendly": false,
    "senior_friendly": false,
    "corporate_friendly": false,
    "summary": "Hành trình 4 ngày 3 đêm đón Tết Nguyên Đán với biển Nha Trang và cao nguyên Đà Lạt; kết hợp tham quan Vinpearl Land, Tháp Bà Ponagar, Thiền viện Trúc Lâm, thác – chùa – dinh – vườn hoa và trải nghiệm văn hóa đặc sắc.",
    "style": "Biển – núi – văn hóa – tâm linh – trải nghiệm thành phố.",
    "includes": [
      "Cáp treo Vinpearl Land – vui chơi hiện đại",
      "Tháp Bà Ponagar – văn hóa Champa",
      "Viện Hải Dương Học (tùy thời gian)",
      "Thác Datanla – trải nghiệm máng trượt tự túc",
      "Thiền Viện Trúc Lâm – Vườn hoa Thành phố",
      "Chùa Linh Phước – Dinh Bảo Đại (Dinh III)",
      "Ngày 1: Đông Hà → Nha Trang (Ăn trưa, tối)",
      "Ngày 2: Nha Trang → Vinpearl Land → Đà Lạt (Ăn sáng, trưa, tối)",
      "Ngày 3: Tham quan Đà Lạt (Ăn sáng, trưa, tối)",
      "Ngày 4: Đà Lạt → Đông Hà (Ăn sáng, trưa, tối)"
    ],
    "notes": "Mang trang phục phù hợp biển – núi – chùa; Tết đông khách nên đặt tour sớm.",
    "transport": "Xe từ 16 chỗ đến 45 chỗ tuỳ số lượng khách, bảo đảm xe đời mới, chất lượng cao",
    "accommodation": "Khách sạn tiêu chuẩn tại Nha Trang và Đà Lạt (2 đêm)",
    "meals": "Ăn 3 bữa chính/ngày (tiêu chuẩn 150.000 VNĐ/suất) theo chương trình + sáng tại khách sạn; nước uống mỗi ngày",
    "event_support": "Hỗ trợ đoàn trong suốt hành trình: theo sát lịch trình – điều phối giờ giấc – hỗ trợ chụp ảnh – ghi nhận nhu cầu cá nhân; kiểm soát an toàn điểm đến; nhắc nhở sức khỏe – trang phục – di chuyển; hỗ trợ xử lý tình huống phát sinh; đồng hành kết nối tập thể; tối ưu trải nghiệm khách hàng theo chuẩn Ruby Wings.",
    "created_at": "2026-01-16T09:07:10.069814Z",
    "last_updated": "2026-01-16T09:07:10.069814Z"
  },
  "tour_021": {
    "tour_id": "tour_021",
    "index": 21,
    "tour_name": "Khám phá Đà Nẵng – Hội An (2 ngày 1 đêm)",
    "location": "Đà Nẵng – Hội An – Quảng Trị (khởi hành từ Quảng Trị)",
    "region": "Miền Trung",
    "tags": [
      "2_ngày",
      "cao_cấp",
      "gia_đình",
      "thiên_nhiên",
      "mạo_hiểm",
      "trải_nghiệm",
      "lịch_sử",
      "thanh_niên",
      "văn_hóa"
    ],
    "duration": "2 ngày 1 đêm",
    "duration_days": 2,
    "price_text": "Giá theo số lượng nhóm & thời điểm. Giá ưu đãi học sinh áp dụng đến 01/06/2026. Vé VinWonders: 420.000đ/học sinh; giáo viên/phụ huynh: 600.000đ/khách.",
    "min_price": 2026,
    "max_price": 600000,
    "avg_price": 301013,
    "embedding_text": "Khám phá Đà Nẵng – Hội An (2 ngày 1 đêm) Hành trình 2 ngày 1 đêm khám phá những điểm đến tiêu biểu của Đà Nẵng – Hội An: Chùa Linh Ứng, Công viên Kỳ Quan Thế Giới, VinWonders Nam Hội An, Ngũ Hành Sơn, Bảo tàng Quân khu 5… Kết hợp giải trí – văn hóa – thiên nhiên – ẩm thực, phù hợp cho học sinh – gia đình – nhóm bạn. Đà Nẵng – Hội An – Quảng Trị (khởi hành từ Quảng Trị) Trải nghiệm văn hóa – giải trí – giáo dục – thiên nhiên. Nhịp đi phù hợp học sinh, gia đình, nhóm bạn; kết hợp vui chơi giải trí – khám phá – học hỏi qua các không gian lịch sử và văn hóa đặc sắc. Khách sạn tiêu chuẩn 3* (nâng cấp 4* +350.000đ/khách/đêm). Xe du lịch chất lượng cao đưa đón theo chương trình. 03 bữa chính tiêu chuẩn 130.000đ/suất; ăn sáng buffet tại khách sạn. Hướng dẫn viên giàu kinh nghiệm – am hiểu tuyến điểm. Vé tham quan theo chương trình (01 lần vào cổng). Vé vào VinWonders Nam Hội An theo diện đoàn (420.000đ/học sinh / 600.000đ giáo viên & phụ huynh). Trải nghiệm tại VinWonders: Bến Cảng Giao Thoa, Đại Lộ Giấc Mơ, Thành Cổ Loa, Safari River, múa rối nước, dân ca quan họ, công viên nước, khu trò chơi điện tử… Tham quan Chùa Linh Ứng – Công viên Kỳ Quan Thế Giới. Tham quan Ngũ Hành Sơn – làng đá Non Nước. Tham quan Bảo tàng Quân khu 5. Khăn lạnh – nước uống phục vụ đoàn. Quà tặng: mũ du lịch – ảnh đoàn. Bảo hiểm du lịch theo quy định. Chương trình có thể thay đổi thứ tự điểm tham quan nhưng đảm bảo đầy đủ nội dung. Không bao gồm: phòng đơn, chi phí cá nhân, VAT, tip HDV & lái xe, dịch vụ tự chọn. Trẻ em: 11 tuổi+ tính như người lớn; 8–10 tuổi: 75%; 4–7 tuổi: 50%; dưới 4 tuổi miễn phí (gia đình tự lo). Chính sách hủy: 14 ngày: 0%; 7–13 ngày: 30%; 5–6 ngày: 50%; 3–4 ngày: 75%; 1–2 ngày: 90%; ngày khởi hành: 100%. Ưu đãi học sinh áp dụng đến 01/06/2026. Danh sách đoàn phải có dấu nhà trường. 2 ngày 1 đêm Giá theo số lượng nhóm & thời điểm. Giá ưu đãi học sinh áp dụng đến 01/06/2026. Vé VinWonders: 420.000đ/học sinh; giáo viên/phụ huynh: 600.000đ/khách. Khách sạn 3* (có thể nâng cấp 4* theo yêu cầu). 03 bữa chính theo tiêu chuẩn; ăn sáng buffet tại khách sạn; bữa tối VinWonders: học sinh 70.000đ, giáo viên/phụ huynh 130.000đ. ['Xe 16 chỗ', 'Xe 35 chỗ', 'Xe 45 chỗ'] Hỗ trợ đoàn học sinh – chính sách miễn vé giáo viên theo tỷ lệ; hỗ trợ chụp ảnh đoàn; hỗ trợ sắp xếp dịch vụ theo nhu cầu đoàn.",
    "popularity_score": 0.8,
    "value_score": 0.8,
    "family_friendly": true,
    "senior_friendly": false,
    "corporate_friendly": true,
    "summary": "Hành trình 2 ngày 1 đêm khám phá những điểm đến tiêu biểu của Đà Nẵng – Hội An: Chùa Linh Ứng, Công viên Kỳ Quan Thế Giới, VinWonders Nam Hội An, Ngũ Hành Sơn, Bảo tàng Quân khu 5… Kết hợp giải trí – văn hóa – thiên nhiên – ẩm thực, phù hợp cho học sinh – gia đình – nhóm bạn.",
    "style": "Trải nghiệm văn hóa – giải trí – giáo dục – thiên nhiên. Nhịp đi phù hợp học sinh, gia đình, nhóm bạn; kết hợp vui chơi giải trí – khám phá – học hỏi qua các không gian lịch sử và văn hóa đặc sắc.",
    "includes": [
      "Khách sạn tiêu chuẩn 3* (nâng cấp 4* +350.000đ/khách/đêm).",
      "Xe du lịch chất lượng cao đưa đón theo chương trình.",
      "03 bữa chính tiêu chuẩn 130.000đ/suất; ăn sáng buffet tại khách sạn.",
      "Hướng dẫn viên giàu kinh nghiệm – am hiểu tuyến điểm.",
      "Vé tham quan theo chương trình (01 lần vào cổng).",
      "Vé vào VinWonders Nam Hội An theo diện đoàn (420.000đ/học sinh / 600.000đ giáo viên & phụ huynh).",
      "Trải nghiệm tại VinWonders: Bến Cảng Giao Thoa, Đại Lộ Giấc Mơ, Thành Cổ Loa, Safari River, múa rối nước, dân ca quan họ, công viên nước, khu trò chơi điện tử…",
      "Tham quan Chùa Linh Ứng – Công viên Kỳ Quan Thế Giới.",
      "Tham quan Ngũ Hành Sơn – làng đá Non Nước.",
      "Tham quan Bảo tàng Quân khu 5.",
      "Khăn lạnh – nước uống phục vụ đoàn.",
      "Quà tặng: mũ du lịch – ảnh đoàn.",
      "Bảo hiểm du lịch theo quy định."
    ],
    "notes": "Chương trình có thể thay đổi thứ tự điểm tham quan nhưng đảm bảo đầy đủ nội dung. Không bao gồm: phòng đơn, chi phí cá nhân, VAT, tip HDV & lái xe, dịch vụ tự chọn. Trẻ em: 11 tuổi+ tính như người lớn; 8–10 tuổi: 75%; 4–7 tuổi: 50%; dưới 4 tuổi miễn phí (gia đình tự lo). Chính sách hủy: 14 ngày: 0%; 7–13 ngày: 30%; 5–6 ngày: 50%; 3–4 ngày: 75%; 1–2 ngày: 90%; ngày khởi hành: 100%. Ưu đãi học sinh áp dụng đến 01/06/2026. Danh sách đoàn phải có dấu nhà trường.",
    "transport": [
      "Xe 16 chỗ",
      "Xe 35 chỗ",
      "Xe 45 chỗ"
    ],
    "accommodation": "Khách sạn 3* (có thể nâng cấp 4* theo yêu cầu).",
    "meals": "03 bữa chính theo tiêu chuẩn; ăn sáng buffet tại khách sạn; bữa tối VinWonders: học sinh 70.000đ, giáo viên/phụ huynh 130.000đ.",
    "event_support": "Hỗ trợ đoàn học sinh – chính sách miễn vé giáo viên theo tỷ lệ; hỗ trợ chụp ảnh đoàn; hỗ trợ sắp xếp dịch vụ theo nhu cầu đoàn.",
    "created_at": "2026-01-16T09:07:10.069814Z",
    "last_updated": "2026-01-16T09:07:10.069814Z"
  },
  "tour_022": {
    "tour_id": "tour_022",
    "index": 22,
    "tour_name": "Theo Dòng Di Sản Miền Trung – Từ Phố Cổ Đến Cố Đô (3 ngày 2 đêm)",
    "location": "Quảng Trị – Hội An (Quảng Nam) – Đà Nẵng – Huế",
    "region": "Miền Trung",
    "tags": [
      "cao_cấp",
      "gia_đình",
      "retreat",
      "thiên_nhiên",
      "trải_nghiệm",
      "lịch_sử",
      "văn_hóa"
    ],
    "duration": "3 ngày 2 đêm",
    "duration_days": 3,
    "price_text": "2.670.000 – 2.790.000 VNĐ/khách (tùy theo quy mô đoàn 17–25 khách). Nếu tham quan VinWonders Nam Hội An: cộng thêm 600.000 VNĐ/khách.",
    "min_price": 600000,
    "max_price": 2790000,
    "avg_price": 1695000,
    "embedding_text": "Theo Dòng Di Sản Miền Trung – Từ Phố Cổ Đến Cố Đô (3 ngày 2 đêm) Hành trình 3 ngày 2 đêm dành cho Quý thầy cô thư giãn, kết nối và mở rộng góc nhìn về các giá trị văn hóa – lịch sử tiêu biểu của miền Trung, đi qua Hội An, Rừng dừa Bảy Mẫu, Đà Nẵng và Huế, kết hợp tham quan di sản, trải nghiệm làng nghề, giao lưu và nghỉ dưỡng. Quảng Trị – Hội An (Quảng Nam) – Đà Nẵng – Huế Trải nghiệm văn hóa – lịch sử – thư giãn; nhịp đi nhẹ nhàng, trang trọng, phù hợp Quý thầy cô và các đoàn giáo dục; kết hợp tham quan di sản, làng nghề truyền thống, giao lưu và nghỉ dưỡng. Xe du lịch chất lượng cao đưa đón đoàn theo chương trình 05 bữa chính tiêu chuẩn 150.000 VNĐ/khách (01 bữa tăng cường 200.000 VNĐ/khách) 01 bữa đặc sản bánh ướt thịt heo quay Lăng Cô (75.000 VNĐ/khách) Lưu trú khách sạn hoặc resort tiêu chuẩn 3* trở lên (2 khách/phòng) Hướng dẫn viên chuyên nghiệp theo đoàn suốt hành trình Vé tham quan vào cửa lần đầu theo chương trình Tham quan Hội An, Rừng dừa Bảy Mẫu, Ngũ Hành Sơn, Chùa Linh Ứng Đà Nẵng Tham quan Làng hương Thủy Xuân, Đại Nội Huế, Chùa Thiên Mụ Chương trình giao lưu tối ngày thứ 2 (âm thanh – ánh sáng) Nước uống, nón du lịch, bảo hiểm du lịch theo quy định Chương trình có thể hoán đổi thứ tự điểm tham quan nhưng vẫn đảm bảo đầy đủ nội dung. Không bao gồm VAT, chi phí cá nhân, đồ uống ngoài bữa ăn, dịch vụ tự chọn, vé VinWonders Nam Hội An (nếu không đăng ký), phụ thu phòng đơn 350.000 VNĐ/đêm, tiền tip HDV & lái xe. Phụ thu lễ/tết/cuối tuần từ 10–25% tùy thời điểm. Chính sách trẻ em và chính sách hủy tour áp dụng theo quy định chi tiết của chương trình. 3 ngày 2 đêm 2.670.000 – 2.790.000 VNĐ/khách (tùy theo quy mô đoàn 17–25 khách). Nếu tham quan VinWonders Nam Hội An: cộng thêm 600.000 VNĐ/khách. Khách sạn hoặc resort tiêu chuẩn từ 3* trở lên; 2 người/phòng, phòng 3 áp dụng cho khách lẻ nam/nữ 05 bữa chính tiêu chuẩn 150.000 VNĐ/khách (01 bữa tăng cường 200.000 VNĐ/khách), 01 bữa đặc sản Lăng Cô; ăn sáng tại khách sạn Xe từ 16 chỗ đến 45 chỗ tùy số lượng khách, bảo đảm xe đời mới, chất lượng cao Hỗ trợ đoàn trong suốt hành trình: điều phối lịch trình, tổ chức giao lưu, hỗ trợ chụp ảnh – kết nối tập thể, kiểm soát an toàn điểm đến, xử lý tình huống phát sinh và đồng hành chăm sóc trải nghiệm theo chuẩn Ruby Wings.",
    "popularity_score": 0.79,
    "value_score": 0.8,
    "family_friendly": true,
    "senior_friendly": false,
    "corporate_friendly": false,
    "summary": "Hành trình 3 ngày 2 đêm dành cho Quý thầy cô thư giãn, kết nối và mở rộng góc nhìn về các giá trị văn hóa – lịch sử tiêu biểu của miền Trung, đi qua Hội An, Rừng dừa Bảy Mẫu, Đà Nẵng và Huế, kết hợp tham quan di sản, trải nghiệm làng nghề, giao lưu và nghỉ dưỡng.",
    "style": "Trải nghiệm văn hóa – lịch sử – thư giãn; nhịp đi nhẹ nhàng, trang trọng, phù hợp Quý thầy cô và các đoàn giáo dục; kết hợp tham quan di sản, làng nghề truyền thống, giao lưu và nghỉ dưỡng.",
    "includes": [
      "Xe du lịch chất lượng cao đưa đón đoàn theo chương trình",
      "05 bữa chính tiêu chuẩn 150.000 VNĐ/khách (01 bữa tăng cường 200.000 VNĐ/khách)",
      "01 bữa đặc sản bánh ướt thịt heo quay Lăng Cô (75.000 VNĐ/khách)",
      "Lưu trú khách sạn hoặc resort tiêu chuẩn 3* trở lên (2 khách/phòng)",
      "Hướng dẫn viên chuyên nghiệp theo đoàn suốt hành trình",
      "Vé tham quan vào cửa lần đầu theo chương trình",
      "Tham quan Hội An, Rừng dừa Bảy Mẫu, Ngũ Hành Sơn, Chùa Linh Ứng Đà Nẵng",
      "Tham quan Làng hương Thủy Xuân, Đại Nội Huế, Chùa Thiên Mụ",
      "Chương trình giao lưu tối ngày thứ 2 (âm thanh – ánh sáng)",
      "Nước uống, nón du lịch, bảo hiểm du lịch theo quy định"
    ],
    "notes": "Chương trình có thể hoán đổi thứ tự điểm tham quan nhưng vẫn đảm bảo đầy đủ nội dung. Không bao gồm VAT, chi phí cá nhân, đồ uống ngoài bữa ăn, dịch vụ tự chọn, vé VinWonders Nam Hội An (nếu không đăng ký), phụ thu phòng đơn 350.000 VNĐ/đêm, tiền tip HDV & lái xe. Phụ thu lễ/tết/cuối tuần từ 10–25% tùy thời điểm. Chính sách trẻ em và chính sách hủy tour áp dụng theo quy định chi tiết của chương trình.",
    "transport": "Xe từ 16 chỗ đến 45 chỗ tùy số lượng khách, bảo đảm xe đời mới, chất lượng cao",
    "accommodation": "Khách sạn hoặc resort tiêu chuẩn từ 3* trở lên; 2 người/phòng, phòng 3 áp dụng cho khách lẻ nam/nữ",
    "meals": "05 bữa chính tiêu chuẩn 150.000 VNĐ/khách (01 bữa tăng cường 200.000 VNĐ/khách), 01 bữa đặc sản Lăng Cô; ăn sáng tại khách sạn",
    "event_support": "Hỗ trợ đoàn trong suốt hành trình: điều phối lịch trình, tổ chức giao lưu, hỗ trợ chụp ảnh – kết nối tập thể, kiểm soát an toàn điểm đến, xử lý tình huống phát sinh và đồng hành chăm sóc trải nghiệm theo chuẩn Ruby Wings.",
    "created_at": "2026-01-16T09:07:10.069814Z",
    "last_updated": "2026-01-16T09:07:10.069814Z"
  },
  "tour_023": {
    "tour_id": "tour_023",
    "index": 23,
    "tour_name": "Tour trải nghiệm linh hoạt - Đông Hà – Nha Trang – Đà Lạt – Huế",
    "location": "Đông Hà – Nha Trang – Đà Lạt – Đà Nẵng – Huế",
    "region": "Miền Trung",
    "tags": [
      "thiền",
      "gia_đình",
      "thiên_nhiên",
      "trải_nghiệm",
      "biển_đảo",
      "tâm_linh"
    ],
    "duration": "4 ngày 3 đêm",
    "duration_days": 4,
    "price_text": "Giá theo bảng (VNĐ/người): 8–9 khách: 8.570.000; 10–11: 7.960.000; 12–13: 7.620.000; 14–15: 7.530.000; 16–17: 7.300.000; 18–19: 7.120.000; 20–21: 6.960.000; 22–23: 6.840.000 (chưa gồm vé máy bay)",
    "min_price": 6840000,
    "max_price": 8570000,
    "avg_price": 7705000,
    "embedding_text": "Tour trải nghiệm linh hoạt - Đông Hà – Nha Trang – Đà Lạt – Huế Hành trình 4 ngày 3 đêm Tết Nguyên Đán: đi tàu SE7 đến Nha Trang, tham quan các điểm nổi tiếng, tiếp tục đến Đà Lạt ngàn hoa và bay về Đà Nẵng – Huế – Đông Hà. Đông Hà – Nha Trang – Đà Lạt – Đà Nẵng – Huế Biển – núi – tâm linh – trải nghiệm tàu/xe/bay – phù hợp gia đình & cơ quan. Tàu SE7 trải nghiệm đêm Đông Hà → Nha Trang Tháp Bà Ponagar – Viện Hải Dương Học hoặc Nhà thờ Đá Chùa Long Sơn – biểu tượng tâm linh Thác Datanla – Thiền viện Trúc Lâm – Hồ Tuyền Lâm Chùa Linh Phước (PA2) Ga Đà Lạt – Vườn hoa Thành phố – Nhà thờ Con Gà Bay Đà Lạt – Đà Nẵng – ăn tối tại Huế Ngày 1: Đông Hà → Nha Trang (tàu SE7) Ngày 2: Nha Trang tham quan (Ăn sáng, trưa, tối) Ngày 3: Nha Trang → Đà Lạt (Ăn sáng, trưa, tối) Ngày 4: Đà Lạt → sân bay – bay → Đà Nẵng – Huế → Đông Hà Tết cao điểm, cần đặt tour – vé tàu – vé máy bay sớm; chuẩn bị áo ấm vì Đà Lạt lạnh. Giá dịch vụ lễ tết sẽ tăng khoảng 10% 4 ngày 3 đêm Giá theo bảng (VNĐ/người): 8–9 khách: 8.570.000; 10–11: 7.960.000; 12–13: 7.620.000; 14–15: 7.530.000; 16–17: 7.300.000; 18–19: 7.120.000; 20–21: 6.960.000; 22–23: 6.840.000 (chưa gồm vé máy bay) Khách sạn từ 3* (có thể nâng cấp tuy lựa chọn quý khách) 07 bữa chính tiêu chuẩn 150.000 VNĐ/suất + ăn sáng khách sạn; nước uống cả ngày Xe từ 16 chỗ đến 45 chỗ tuỳ số lượng khách, bảo đảm xe đời mới, chất lượng cao Hỗ trợ đoàn trong suốt hành trình: theo sát lịch trình – điều phối giờ giấc – hỗ trợ chụp ảnh – ghi nhận nhu cầu cá nhân; kiểm soát an toàn điểm đến; nhắc nhở sức khỏe – trang phục – di chuyển; hỗ trợ xử lý tình huống phát sinh; đồng hành kết nối tập thể; tối ưu trải nghiệm khách hàng theo chuẩn Ruby Wings.",
    "popularity_score": 0.78,
    "value_score": 0.6,
    "family_friendly": true,
    "senior_friendly": false,
    "corporate_friendly": false,
    "summary": "Hành trình 4 ngày 3 đêm Tết Nguyên Đán: đi tàu SE7 đến Nha Trang, tham quan các điểm nổi tiếng, tiếp tục đến Đà Lạt ngàn hoa và bay về Đà Nẵng – Huế – Đông Hà.",
    "style": "Biển – núi – tâm linh – trải nghiệm tàu/xe/bay – phù hợp gia đình & cơ quan.",
    "includes": [
      "Tàu SE7 trải nghiệm đêm Đông Hà → Nha Trang",
      "Tháp Bà Ponagar – Viện Hải Dương Học hoặc Nhà thờ Đá",
      "Chùa Long Sơn – biểu tượng tâm linh",
      "Thác Datanla – Thiền viện Trúc Lâm – Hồ Tuyền Lâm",
      "Chùa Linh Phước (PA2)",
      "Ga Đà Lạt – Vườn hoa Thành phố – Nhà thờ Con Gà",
      "Bay Đà Lạt – Đà Nẵng – ăn tối tại Huế",
      "Ngày 1: Đông Hà → Nha Trang (tàu SE7)",
      "Ngày 2: Nha Trang tham quan (Ăn sáng, trưa, tối)",
      "Ngày 3: Nha Trang → Đà Lạt (Ăn sáng, trưa, tối)",
      "Ngày 4: Đà Lạt → sân bay – bay → Đà Nẵng – Huế → Đông Hà"
    ],
    "notes": "Tết cao điểm, cần đặt tour – vé tàu – vé máy bay sớm; chuẩn bị áo ấm vì Đà Lạt lạnh. Giá dịch vụ lễ tết sẽ tăng khoảng 10%",
    "transport": "Xe từ 16 chỗ đến 45 chỗ tuỳ số lượng khách, bảo đảm xe đời mới, chất lượng cao",
    "accommodation": "Khách sạn từ 3* (có thể nâng cấp tuy lựa chọn quý khách)",
    "meals": "07 bữa chính tiêu chuẩn 150.000 VNĐ/suất + ăn sáng khách sạn; nước uống cả ngày",
    "event_support": "Hỗ trợ đoàn trong suốt hành trình: theo sát lịch trình – điều phối giờ giấc – hỗ trợ chụp ảnh – ghi nhận nhu cầu cá nhân; kiểm soát an toàn điểm đến; nhắc nhở sức khỏe – trang phục – di chuyển; hỗ trợ xử lý tình huống phát sinh; đồng hành kết nối tập thể; tối ưu trải nghiệm khách hàng theo chuẩn Ruby Wings.",
    "created_at": "2026-01-16T09:07:10.069814Z",
    "last_updated": "2026-01-16T09:07:10.069814Z"
  },
  "tour_024": {
    "tour_id": "tour_024",
    "index": 24,
    "tour_name": "Đông Hà – Nha Trang – Đà Lạt – Buôn Ma Thuột – Đông Hà",
    "location": "Đông Hà – Nha Trang – Đà Lạt – Buôn Ma Thuột",
    "region": "Miền Nam",
    "tags": [
      "thiền",
      "thiên_nhiên",
      "mạo_hiểm",
      "trải_nghiệm",
      "biển_đảo",
      "tâm_linh",
      "văn_hóa"
    ],
    "duration": "4 ngày 3 đêm",
    "duration_days": 4,
    "price_text": "6.670.000 – 8.210.000 VNĐ/người (tùy xe và số lượng khách)",
    "min_price": 6670000,
    "max_price": 8210000,
    "avg_price": 7440000,
    "embedding_text": "Đông Hà – Nha Trang – Đà Lạt – Buôn Ma Thuột – Đông Hà Hành trình 4N3Đ khám phá biển Nha Trang, cao nguyên Đà Lạt và văn hoá Tây Nguyên Buôn Ma Thuột; kết hợp Vinpearl Land, Tháp Bà Ponagar, thác – chùa – hồ – dinh và các trải nghiệm đặc sắc ngày Tết. Đông Hà – Nha Trang – Đà Lạt – Buôn Ma Thuột Biển – núi – văn hóa – tâm linh – khám phá Tây Nguyên. Khám phá Nha Trang – vịnh đẹp nhất thế giới Cáp treo Vinpearl Land – vui chơi giải trí Tháp Bà Ponagar – Viện Hải Dương Học Đà Lạt: Thác Datanla, Thiền viện Trúc Lâm, Hồ Tuyền Lâm, Chùa Linh Phước, Dinh Bảo Đại Buôn Ma Thuột – trải nghiệm văn hoá Tây Nguyên Ngày 1: Đông Hà → Nha Trang (trưa, tối) Ngày 2: Nha Trang → Vinpearl → Đà Lạt (sáng, trưa, tối) Ngày 3: Đà Lạt → Buôn Ma Thuột (sáng, trưa, tối) Ngày 4: Buôn Ma Thuột → Đông Hà (sáng, trưa, tối) Lịch trình có thể điều chỉnh nhẹ theo điều kiện Tết; nên đặt tour sớm để giữ phòng – xe.  Giá dịch vụ lễ tết sẽ tăng khoảng 10% 4 ngày 3 đêm 6.670.000 – 8.210.000 VNĐ/người (tùy xe và số lượng khách) Khách sạn tiêu chuẩn tại Nha Trang – Đà Lạt – Buôn Ma Thuột Ăn đủ 3 bữa chính/ngày + nước uống; ăn sáng tại khách sạn Xe 16–45 chỗ đời mới tùy quy mô đoàn Hỗ trợ đoàn trong suốt hành trình: theo sát lịch trình – điều phối giờ giấc – hỗ trợ chụp ảnh – ghi nhận nhu cầu cá nhân; kiểm soát an toàn điểm đến; nhắc nhở sức khỏe – trang phục – di chuyển; hỗ trợ xử lý tình huống phát sinh; đồng hành kết nối tập thể; tối ưu trải nghiệm khách hàng theo chuẩn Ruby Wings.",
    "popularity_score": 0.77,
    "value_score": 0.6,
    "family_friendly": false,
    "senior_friendly": false,
    "corporate_friendly": false,
    "summary": "Hành trình 4N3Đ khám phá biển Nha Trang, cao nguyên Đà Lạt và văn hoá Tây Nguyên Buôn Ma Thuột; kết hợp Vinpearl Land, Tháp Bà Ponagar, thác – chùa – hồ – dinh và các trải nghiệm đặc sắc ngày Tết.",
    "style": "Biển – núi – văn hóa – tâm linh – khám phá Tây Nguyên.",
    "includes": [
      "Khám phá Nha Trang – vịnh đẹp nhất thế giới",
      "Cáp treo Vinpearl Land – vui chơi giải trí",
      "Tháp Bà Ponagar – Viện Hải Dương Học",
      "Đà Lạt: Thác Datanla, Thiền viện Trúc Lâm, Hồ Tuyền Lâm, Chùa Linh Phước, Dinh Bảo Đại",
      "Buôn Ma Thuột – trải nghiệm văn hoá Tây Nguyên",
      "Ngày 1: Đông Hà → Nha Trang (trưa, tối)",
      "Ngày 2: Nha Trang → Vinpearl → Đà Lạt (sáng, trưa, tối)",
      "Ngày 3: Đà Lạt → Buôn Ma Thuột (sáng, trưa, tối)",
      "Ngày 4: Buôn Ma Thuột → Đông Hà (sáng, trưa, tối)"
    ],
    "notes": "Lịch trình có thể điều chỉnh nhẹ theo điều kiện Tết; nên đặt tour sớm để giữ phòng – xe.  Giá dịch vụ lễ tết sẽ tăng khoảng 10%",
    "transport": "Xe 16–45 chỗ đời mới tùy quy mô đoàn",
    "accommodation": "Khách sạn tiêu chuẩn tại Nha Trang – Đà Lạt – Buôn Ma Thuột",
    "meals": "Ăn đủ 3 bữa chính/ngày + nước uống; ăn sáng tại khách sạn",
    "event_support": "Hỗ trợ đoàn trong suốt hành trình: theo sát lịch trình – điều phối giờ giấc – hỗ trợ chụp ảnh – ghi nhận nhu cầu cá nhân; kiểm soát an toàn điểm đến; nhắc nhở sức khỏe – trang phục – di chuyển; hỗ trợ xử lý tình huống phát sinh; đồng hành kết nối tập thể; tối ưu trải nghiệm khách hàng theo chuẩn Ruby Wings.",
    "created_at": "2026-01-16T09:07:10.069814Z",
    "last_updated": "2026-01-16T09:07:10.069814Z"
  },
  "tour_025": {
    "tour_id": "tour_025",
    "index": 25,
    "tour_name": "Phú Quốc 4N3Đ – Khám phá Nam đảo & Bắc đảo",
    "location": "Đông Hà – Đà Nẵng – Phú Quốc",
    "region": "Miền Trung",
    "tags": [
      "thiên_nhiên",
      "mạo_hiểm",
      "trải_nghiệm",
      "biển_đảo",
      "tâm_linh"
    ],
    "duration": "4 ngày 3 đêm",
    "duration_days": 4,
    "price_text": "6.280.000 VNĐ/người (đoàn 09 khách, chưa gồm vé máy bay)",
    "min_price": 6280000,
    "max_price": 6280000,
    "avg_price": 6280000,
    "embedding_text": "Phú Quốc 4N3Đ – Khám phá Nam đảo & Bắc đảo Hành trình 4N3Đ khám phá Nam đảo – Bắc đảo: Safari, Grand World, Cầu Hôn, Chùa Hộ Quốc, show Tinh Hoa Việt Nam, Nhà tù Phú Quốc, rừng nguyên sinh và Bãi Kem. Đông Hà – Đà Nẵng – Phú Quốc Biển – giải trí – thiên nhiên – tâm linh – show nghệ thuật. Check-in Địa Trung Hải – Cầu Hôn Show Awaken Sea hoặc hoạt động đêm Grand World Chùa Hộ Quốc – điểm tâm linh lớn nhất đảo Vinpearl Safari hoặc Cáp treo Hòn Thơm / Cano 3 đảo Grand World – Bảo tàng Gấu – Show Tinh Hoa Việt Nam Rừng nguyên sinh – Đền Nguyễn Trung Trực – Nhà tù Phú Quốc – Bãi Kem Ngày 1: Đông Hà – Đà Nẵng – Phú Quốc (trưa, tối) Ngày 2: Safari/Cáp treo – Grand World (sáng, trưa, tối) Ngày 3: Rừng nguyên sinh – Bãi Kem – Nhà tù Phú Quốc (sáng, trưa, tối) Ngày 4: Tự do – Cafe Grand World – bay về Đà Nẵng (sáng, trưa) Khuyến nghị đặt vé máy bay sớm để giữ giá tốt; chuẩn bị đồ đi biển. 4 ngày 3 đêm 6.280.000 VNĐ/người (đoàn 09 khách, chưa gồm vé máy bay) Khách sạn tiêu chuẩn từ 3* tại Phú Quốc (3 đêm) tiêu chuẩn 150.000 VNĐ/suất + ăn sáng khách sạn; nước uống mỗi ngày Máy bay + xe du lịch tại Phú Quốc Hỗ trợ đoàn trong suốt hành trình: theo sát lịch trình – điều phối giờ giấc – hỗ trợ chụp ảnh – ghi nhận nhu cầu cá nhân; kiểm soát an toàn điểm đến; nhắc nhở sức khỏe – trang phục – di chuyển; hỗ trợ xử lý tình huống phát sinh; đồng hành kết nối tập thể; tối ưu trải nghiệm khách hàng theo chuẩn Ruby Wings.",
    "popularity_score": 0.77,
    "value_score": 0.6,
    "family_friendly": false,
    "senior_friendly": false,
    "corporate_friendly": false,
    "summary": "Hành trình 4N3Đ khám phá Nam đảo – Bắc đảo: Safari, Grand World, Cầu Hôn, Chùa Hộ Quốc, show Tinh Hoa Việt Nam, Nhà tù Phú Quốc, rừng nguyên sinh và Bãi Kem.",
    "style": "Biển – giải trí – thiên nhiên – tâm linh – show nghệ thuật.",
    "includes": [
      "Check-in Địa Trung Hải – Cầu Hôn",
      "Show Awaken Sea hoặc hoạt động đêm Grand World",
      "Chùa Hộ Quốc – điểm tâm linh lớn nhất đảo",
      "Vinpearl Safari hoặc Cáp treo Hòn Thơm / Cano 3 đảo",
      "Grand World – Bảo tàng Gấu – Show Tinh Hoa Việt Nam",
      "Rừng nguyên sinh – Đền Nguyễn Trung Trực – Nhà tù Phú Quốc – Bãi Kem",
      "Ngày 1: Đông Hà – Đà Nẵng – Phú Quốc (trưa, tối)",
      "Ngày 2: Safari/Cáp treo – Grand World (sáng, trưa, tối)",
      "Ngày 3: Rừng nguyên sinh – Bãi Kem – Nhà tù Phú Quốc (sáng, trưa, tối)",
      "Ngày 4: Tự do – Cafe Grand World – bay về Đà Nẵng (sáng, trưa)"
    ],
    "notes": "Khuyến nghị đặt vé máy bay sớm để giữ giá tốt; chuẩn bị đồ đi biển.",
    "transport": "Máy bay + xe du lịch tại Phú Quốc",
    "accommodation": "Khách sạn tiêu chuẩn từ 3* tại Phú Quốc (3 đêm)",
    "meals": "tiêu chuẩn 150.000 VNĐ/suất + ăn sáng khách sạn; nước uống mỗi ngày",
    "event_support": "Hỗ trợ đoàn trong suốt hành trình: theo sát lịch trình – điều phối giờ giấc – hỗ trợ chụp ảnh – ghi nhận nhu cầu cá nhân; kiểm soát an toàn điểm đến; nhắc nhở sức khỏe – trang phục – di chuyển; hỗ trợ xử lý tình huống phát sinh; đồng hành kết nối tập thể; tối ưu trải nghiệm khách hàng theo chuẩn Ruby Wings.",
    "created_at": "2026-01-16T09:07:10.070778Z",
    "last_updated": "2026-01-16T09:07:10.070778Z"
  },
  "tour_026": {
    "tour_id": "tour_026",
    "index": 26,
    "tour_name": "Khám Phá Đất Việt – Văn Hóa & Kỳ Quan Thiên Nhiên (Tam Đảo – Mộc Châu) (4 ngày 3 đêm, di chuyển ban đêm)",
    "location": "Quảng Trị – Hà Nội – Tam Đảo (Vĩnh Phúc) – Mộc Châu (Sơn La) – Quảng Trị",
    "region": "Miền Bắc",
    "tags": [
      "du_lịch_xanh",
      "gia_đình",
      "lửa_trại",
      "thiên_nhiên",
      "mạo_hiểm",
      "trải_nghiệm",
      "biển_đảo",
      "tâm_linh",
      "văn_hóa"
    ],
    "duration": "4 ngày 3 đêm (di chuyển ban đêm)",
    "duration_days": 4,
    "price_text": "4.230.000 – 4.290.000 VNĐ/khách (tùy quy mô đoàn 33–42 khách)",
    "min_price": 4230000,
    "max_price": 4290000,
    "avg_price": 4260000,
    "embedding_text": "Khám Phá Đất Việt – Văn Hóa & Kỳ Quan Thiên Nhiên (Tam Đảo – Mộc Châu) (4 ngày 3 đêm, di chuyển ban đêm) Hành trình 4 ngày 3 đêm khám phá vẻ đẹp thiên nhiên và văn hóa đặc sắc miền Bắc, từ thị trấn mờ sương Tam Đảo đến cao nguyên xanh mát Mộc Châu. Chương trình kết hợp du lịch thiên nhiên, tâm linh, trải nghiệm văn hóa bản địa và giao lưu cộng đồng, phù hợp cho Quý thầy cô và các đoàn giáo dục. Quảng Trị – Hà Nội – Tam Đảo (Vĩnh Phúc) – Mộc Châu (Sơn La) – Quảng Trị Trải nghiệm thiên nhiên – văn hóa – cộng đồng; kết hợp du lịch núi rừng, tâm linh và giao lưu bản địa; nhịp đi linh hoạt, phù hợp Quý thầy cô và các đoàn giáo dục. Vé xe giường nằm đời mới Quảng Trị – Hà Nội – Quảng Trị (02 người/giường) Xe du lịch 16–35 chỗ đời mới phục vụ tham quan tại Hà Nội – Tam Đảo – Mộc Châu Lưu trú Tam Đảo khách sạn tiêu chuẩn 3* (ăn sáng buffet) Lưu trú Mộc Châu nhà nghỉ cộng đồng truyền thống 06 bữa chính theo chương trình (tiêu chuẩn 150.000 VNĐ/suất, 01 bữa đặc sản 200.000 VNĐ/suất) Ăn sáng theo chương trình (01 bữa phở Hà Nội bên ngoài) Hướng dẫn viên nhiệt tình phục vụ theo chương trình; bố trí điều hành theo đoàn Vé tham quan vào cửa lần đầu theo chương trình Tham quan Tây Thiên, Tháp truyền hình Tam Đảo, Cổng Trời Tam Đảo, Nhà thờ đá Tam Đảo Tham quan Đèo Thung Khe, Thác Dải Yếm, Vườn mận, Rừng thông Bản Áng Tổ chức đêm lửa trại với âm thanh, ánh sáng, MC và đội múa bản địa Nước uống 2 chai 0,5l/khách/ngày, nón du lịch Bảo hiểm du lịch theo quy định Chương trình có thể hoán đổi thứ tự điểm tham quan nhưng vẫn đảm bảo đầy đủ nội dung. Không bao gồm VAT, chi phí cá nhân, đồ uống ngoài bữa ăn, vé cầu kính Bạch Long, phụ thu phòng đơn (425.000 VNĐ/phòng/đêm), tiền bồi dưỡng HDV & lái xe, dịch vụ trung chuyển phát sinh. Chính sách trẻ em và chính sách hủy tour áp dụng theo quy định chi tiết của chương trình. 4 ngày 3 đêm (di chuyển ban đêm) 4.230.000 – 4.290.000 VNĐ/khách (tùy quy mô đoàn 33–42 khách) Khách sạn 3* tại Tam Đảo; nhà nghỉ cộng đồng truyền thống tại Mộc Châu; phòng 2 khách hoặc phòng 3 cho khách lẻ 06 bữa chính theo chương trình (150.000 VNĐ/suất; 01 bữa đặc sản 200.000 VNĐ/suất); ăn sáng tại khách sạn và theo chương trình Xe giường nằm đường dài và xe du lịch từ 16 đến 35 chỗ phục vụ tham quan theo chương trình Hỗ trợ đoàn trong suốt hành trình: điều phối lịch trình, tổ chức lửa trại – giao lưu, hỗ trợ chụp ảnh, kiểm soát an toàn, xử lý tình huống phát sinh và đồng hành chăm sóc trải nghiệm theo chuẩn Ruby Wings.",
    "popularity_score": 0.76,
    "value_score": 0.6,
    "family_friendly": true,
    "senior_friendly": false,
    "corporate_friendly": false,
    "summary": "Hành trình 4 ngày 3 đêm khám phá vẻ đẹp thiên nhiên và văn hóa đặc sắc miền Bắc, từ thị trấn mờ sương Tam Đảo đến cao nguyên xanh mát Mộc Châu. Chương trình kết hợp du lịch thiên nhiên, tâm linh, trải nghiệm văn hóa bản địa và giao lưu cộng đồng, phù hợp cho Quý thầy cô và các đoàn giáo dục.",
    "style": "Trải nghiệm thiên nhiên – văn hóa – cộng đồng; kết hợp du lịch núi rừng, tâm linh và giao lưu bản địa; nhịp đi linh hoạt, phù hợp Quý thầy cô và các đoàn giáo dục.",
    "includes": [
      "Vé xe giường nằm đời mới Quảng Trị – Hà Nội – Quảng Trị (02 người/giường)",
      "Xe du lịch 16–35 chỗ đời mới phục vụ tham quan tại Hà Nội – Tam Đảo – Mộc Châu",
      "Lưu trú Tam Đảo khách sạn tiêu chuẩn 3* (ăn sáng buffet)",
      "Lưu trú Mộc Châu nhà nghỉ cộng đồng truyền thống",
      "06 bữa chính theo chương trình (tiêu chuẩn 150.000 VNĐ/suất, 01 bữa đặc sản 200.000 VNĐ/suất)",
      "Ăn sáng theo chương trình (01 bữa phở Hà Nội bên ngoài)",
      "Hướng dẫn viên nhiệt tình phục vụ theo chương trình; bố trí điều hành theo đoàn",
      "Vé tham quan vào cửa lần đầu theo chương trình",
      "Tham quan Tây Thiên, Tháp truyền hình Tam Đảo, Cổng Trời Tam Đảo, Nhà thờ đá Tam Đảo",
      "Tham quan Đèo Thung Khe, Thác Dải Yếm, Vườn mận, Rừng thông Bản Áng",
      "Tổ chức đêm lửa trại với âm thanh, ánh sáng, MC và đội múa bản địa",
      "Nước uống 2 chai 0,5l/khách/ngày, nón du lịch",
      "Bảo hiểm du lịch theo quy định"
    ],
    "notes": "Chương trình có thể hoán đổi thứ tự điểm tham quan nhưng vẫn đảm bảo đầy đủ nội dung. Không bao gồm VAT, chi phí cá nhân, đồ uống ngoài bữa ăn, vé cầu kính Bạch Long, phụ thu phòng đơn (425.000 VNĐ/phòng/đêm), tiền bồi dưỡng HDV & lái xe, dịch vụ trung chuyển phát sinh. Chính sách trẻ em và chính sách hủy tour áp dụng theo quy định chi tiết của chương trình.",
    "transport": "Xe giường nằm đường dài và xe du lịch từ 16 đến 35 chỗ phục vụ tham quan theo chương trình",
    "accommodation": "Khách sạn 3* tại Tam Đảo; nhà nghỉ cộng đồng truyền thống tại Mộc Châu; phòng 2 khách hoặc phòng 3 cho khách lẻ",
    "meals": "06 bữa chính theo chương trình (150.000 VNĐ/suất; 01 bữa đặc sản 200.000 VNĐ/suất); ăn sáng tại khách sạn và theo chương trình",
    "event_support": "Hỗ trợ đoàn trong suốt hành trình: điều phối lịch trình, tổ chức lửa trại – giao lưu, hỗ trợ chụp ảnh, kiểm soát an toàn, xử lý tình huống phát sinh và đồng hành chăm sóc trải nghiệm theo chuẩn Ruby Wings.",
    "created_at": "2026-01-16T09:07:10.070778Z",
    "last_updated": "2026-01-16T09:07:10.070778Z"
  },
  "tour_027": {
    "tour_id": "tour_027",
    "index": 27,
    "tour_name": "Đông Hà – Nha Trang – Quy Nhơn – Đông Hà (5 ngày 4 đêm)",
    "location": "Đông Hà – Nha Trang – Quy Nhơn",
    "region": "Miền Trung",
    "tags": [
      "trải_nghiệm",
      "retreat",
      "văn_hóa",
      "biển_đảo"
    ],
    "duration": "5 ngày 4 đêm",
    "duration_days": 5,
    "price_text": "4.300.000 – 4.490.000 VNĐ VNĐ/khách (tùy quy mô đoàn 33–42 khách, xe 45 chỗ), Giá sẽ được cập nhật sau và phụ thuộc vào nhiều yếu tố: số lượng khách, thời điểm khởi hành, cấp độ dịch vụ lựa chọn (cơ bản – nâng cao – cao cấp), hạng phương tiện, tiêu chuẩn lưu trú – ăn uống, vé tham quan và các yêu cầu tùy chỉnh theo nhóm. Khi chốt đủ thông tin, Ruby Wings sẽ gửi báo giá chi tiết.",
    "min_price": 4300000,
    "max_price": 4490000,
    "avg_price": 4395000,
    "embedding_text": "Đông Hà – Nha Trang – Quy Nhơn – Đông Hà (5 ngày 4 đêm) Hành trình 5N4Đ kết hợp tàu hỏa và xe du lịch: tham quan Nha Trang – Quy Nhơn với Tháp Bà Ponagar, Viện Hải Dương Học, Vinpearl Land, Eo Gió, Ghềnh Ráng – Tiên Sa, Tháp Đôi và Bảo tàng Quang Trung. Đông Hà – Nha Trang – Quy Nhơn Biển – văn hóa – giải trí – di sản – nghỉ dưỡng. Tàu SE7 hành trình đêm Đông Hà → Nha Trang Tháp Bà Ponagar – Chùa Long Sơn Viện Hải Dương Học hoặc Nhà thờ Đá Nha Trang Vinpearl Land – vui chơi trọn ngày Eo Gió – Ghềnh Ráng – Tiên Sa – Mộ Hàn Mặc Tử Tháp Đôi – Bảo tàng Quang Trung Ngày 1: Đông Hà → Nha Trang bằng tàu (tối tự túc) Ngày 2: Nha Trang tham quan (sáng, trưa, tối) Ngày 3: Vinpearl Land → di chuyển Quy Nhơn (sáng, trưa, tối) Ngày 4: Quy Nhơn tham quan (sáng, trưa, tối) Ngày 5: Quy Nhơn – Đông Hà bằng tàu SE2 (sáng) Giá chưa bao gồm vé Vinpearl Land; cần đặt tàu sớm dịp cao điểm. 5 ngày 4 đêm 4.300.000 – 4.490.000 VNĐ VNĐ/khách (tùy quy mô đoàn 33–42 khách, xe 45 chỗ), Giá sẽ được cập nhật sau và phụ thuộc vào nhiều yếu tố: số lượng khách, thời điểm khởi hành, cấp độ dịch vụ lựa chọn (cơ bản – nâng cao – cao cấp), hạng phương tiện, tiêu chuẩn lưu trú – ăn uống, vé tham quan và các yêu cầu tùy chỉnh theo nhóm. Khi chốt đủ thông tin, Ruby Wings sẽ gửi báo giá chi tiết. Khách sạn tiêu chuẩn từ 3* tại Nha Trang & Quy Nhơn Ăn theo chương trình tiêu chuẩn 150.000 VNĐ/suất; sáng tại khách sạn; nước uống mỗi ngày Tàu SE7/SE2 + xe 16–45 chỗ tùy đoàn Hỗ trợ đoàn trong suốt hành trình: theo sát lịch trình – điều phối giờ giấc – hỗ trợ chụp ảnh – ghi nhận nhu cầu cá nhân; kiểm soát an toàn điểm đến; nhắc nhở sức khỏe – trang phục – di chuyển; hỗ trợ xử lý tình huống phát sinh; đồng hành kết nối tập thể; tối ưu trải nghiệm khách hàng theo chuẩn Ruby Wings.",
    "popularity_score": 0.75,
    "value_score": 0.8,
    "family_friendly": false,
    "senior_friendly": false,
    "corporate_friendly": false,
    "summary": "Hành trình 5N4Đ kết hợp tàu hỏa và xe du lịch: tham quan Nha Trang – Quy Nhơn với Tháp Bà Ponagar, Viện Hải Dương Học, Vinpearl Land, Eo Gió, Ghềnh Ráng – Tiên Sa, Tháp Đôi và Bảo tàng Quang Trung.",
    "style": "Biển – văn hóa – giải trí – di sản – nghỉ dưỡng.",
    "includes": [
      "Tàu SE7 hành trình đêm Đông Hà → Nha Trang",
      "Tháp Bà Ponagar – Chùa Long Sơn",
      "Viện Hải Dương Học hoặc Nhà thờ Đá Nha Trang",
      "Vinpearl Land – vui chơi trọn ngày",
      "Eo Gió – Ghềnh Ráng – Tiên Sa – Mộ Hàn Mặc Tử",
      "Tháp Đôi – Bảo tàng Quang Trung",
      "Ngày 1: Đông Hà → Nha Trang bằng tàu (tối tự túc)",
      "Ngày 2: Nha Trang tham quan (sáng, trưa, tối)",
      "Ngày 3: Vinpearl Land → di chuyển Quy Nhơn (sáng, trưa, tối)",
      "Ngày 4: Quy Nhơn tham quan (sáng, trưa, tối)",
      "Ngày 5: Quy Nhơn – Đông Hà bằng tàu SE2 (sáng)"
    ],
    "notes": "Giá chưa bao gồm vé Vinpearl Land; cần đặt tàu sớm dịp cao điểm.",
    "transport": "Tàu SE7/SE2 + xe 16–45 chỗ tùy đoàn",
    "accommodation": "Khách sạn tiêu chuẩn từ 3* tại Nha Trang & Quy Nhơn",
    "meals": "Ăn theo chương trình tiêu chuẩn 150.000 VNĐ/suất; sáng tại khách sạn; nước uống mỗi ngày",
    "event_support": "Hỗ trợ đoàn trong suốt hành trình: theo sát lịch trình – điều phối giờ giấc – hỗ trợ chụp ảnh – ghi nhận nhu cầu cá nhân; kiểm soát an toàn điểm đến; nhắc nhở sức khỏe – trang phục – di chuyển; hỗ trợ xử lý tình huống phát sinh; đồng hành kết nối tập thể; tối ưu trải nghiệm khách hàng theo chuẩn Ruby Wings.",
    "created_at": "2026-01-16T09:07:10.070778Z",
    "last_updated": "2026-01-16T09:07:10.070778Z"
  },
  "tour_028": {
    "tour_id": "tour_028",
    "index": 28,
    "tour_name": "Miền Trung Di Sản – Khám Phá Quy Nhơn – Phú Yên (4 ngày 3 đêm)",
    "location": "Quảng Trị – Quy Nhơn (Bình Định) – Tuy Hòa (Phú Yên) – Hải Vân Quan – Quảng Trị",
    "region": "Miền Trung",
    "tags": [
      "gia_đình",
      "retreat",
      "thiên_nhiên",
      "mạo_hiểm",
      "trải_nghiệm",
      "biển_đảo",
      "lịch_sử",
      "team_building",
      "văn_hóa"
    ],
    "duration": "4 ngày 3 đêm",
    "duration_days": 4,
    "price_text": "4.050.000 – 4.250.000 VNĐ/khách (tùy quy mô đoàn 33–42 khách, xe 45 chỗ)",
    "min_price": 4050000,
    "max_price": 4250000,
    "avg_price": 4150000,
    "embedding_text": "Miền Trung Di Sản – Khám Phá Quy Nhơn – Phú Yên (4 ngày 3 đêm) Hành trình 4 ngày 3 đêm kết nối những điểm đến tiêu biểu của dải đất miền Trung, nơi hội tụ vẻ đẹp thiên nhiên hoang sơ, chiều sâu lịch sử và các thắng cảnh biển kỳ vĩ bậc nhất Việt Nam. Chương trình phù hợp cho Quý thầy cô và các đoàn giáo dục, kết hợp tham quan di sản, văn hóa Chăm Pa, danh thắng biển và giao lưu tập thể. Quảng Trị – Quy Nhơn (Bình Định) – Tuy Hòa (Phú Yên) – Hải Vân Quan – Quảng Trị Trải nghiệm di sản – văn hóa – biển đảo; nhịp đi cân bằng giữa tham quan và nghỉ dưỡng; phù hợp Quý thầy cô, đoàn giáo dục và tập thể cơ quan. Xe du lịch 35–45 chỗ đời mới (2022–2025) đưa đón theo chương trình 08 bữa chính (07 bữa tiêu chuẩn 150.000 VNĐ/suất, 01 bữa tăng cường 200.000 VNĐ/suất) Lưu trú khách sạn tiêu chuẩn 3*, ăn sáng tại khách sạn Hướng dẫn viên chuyên nghiệp theo đoàn suốt hành trình Vé tham quan vào cửa lần đầu theo chương trình Tham quan Eo Gió, Tháp Đôi, Bảo tàng Quang Trung Tham quan Chùa Thiên Hưng, Ghềnh Ráng – Tiên Sa Tham quan Tháp Nhạn, Nhà thờ Mằng Lăng Tham quan Bãi Xép – Ghềnh Ông, Gành Đá Đĩa Tham quan Bãi Môn – Mũi Đại Lãnh Tham quan Hải Vân Quan Tổ chức Gala đêm cuối với sân khấu, âm thanh, ánh sáng Nước uống, nón du lịch, bảo hiểm du lịch theo quy định Chương trình có thể hoán đổi thứ tự điểm tham quan nhưng vẫn đảm bảo đầy đủ nội dung. Không bao gồm VAT, chi phí cá nhân, đồ uống ngoài bữa ăn, dịch vụ tự chọn, phụ thu phòng đơn, tiền tip HDV & lái xe (khoảng 30.000 VNĐ/ngày/khách). Phụ thu lễ/tết/cuối tuần từ 10–25% tùy thời điểm. Chính sách trẻ em và chính sách hủy tour áp dụng theo quy định chi tiết của chương trình. 4 ngày 3 đêm 4.050.000 – 4.250.000 VNĐ/khách (tùy quy mô đoàn 33–42 khách, xe 45 chỗ) Khách sạn tiêu chuẩn 3*, phòng 2 khách; ăn sáng tại khách sạn 08 bữa chính (07 bữa 150.000 VNĐ/suất, 01 bữa 200.000 VNĐ/suất); ăn sáng tại khách sạn Xe từ 35 chỗ đến 45 chỗ tùy số lượng khách, bảo đảm xe đời mới, chất lượng cao Hỗ trợ đoàn trong suốt hành trình: điều phối lịch trình, tổ chức Gala – giao lưu, hỗ trợ chụp ảnh, kiểm soát an toàn điểm đến, xử lý tình huống phát sinh và đồng hành chăm sóc trải nghiệm theo chuẩn Ruby Wings.",
    "popularity_score": 0.74,
    "value_score": 0.6,
    "family_friendly": true,
    "senior_friendly": false,
    "corporate_friendly": true,
    "summary": "Hành trình 4 ngày 3 đêm kết nối những điểm đến tiêu biểu của dải đất miền Trung, nơi hội tụ vẻ đẹp thiên nhiên hoang sơ, chiều sâu lịch sử và các thắng cảnh biển kỳ vĩ bậc nhất Việt Nam. Chương trình phù hợp cho Quý thầy cô và các đoàn giáo dục, kết hợp tham quan di sản, văn hóa Chăm Pa, danh thắng biển và giao lưu tập thể.",
    "style": "Trải nghiệm di sản – văn hóa – biển đảo; nhịp đi cân bằng giữa tham quan và nghỉ dưỡng; phù hợp Quý thầy cô, đoàn giáo dục và tập thể cơ quan.",
    "includes": [
      "Xe du lịch 35–45 chỗ đời mới (2022–2025) đưa đón theo chương trình",
      "08 bữa chính (07 bữa tiêu chuẩn 150.000 VNĐ/suất, 01 bữa tăng cường 200.000 VNĐ/suất)",
      "Lưu trú khách sạn tiêu chuẩn 3*, ăn sáng tại khách sạn",
      "Hướng dẫn viên chuyên nghiệp theo đoàn suốt hành trình",
      "Vé tham quan vào cửa lần đầu theo chương trình",
      "Tham quan Eo Gió, Tháp Đôi, Bảo tàng Quang Trung",
      "Tham quan Chùa Thiên Hưng, Ghềnh Ráng – Tiên Sa",
      "Tham quan Tháp Nhạn, Nhà thờ Mằng Lăng",
      "Tham quan Bãi Xép – Ghềnh Ông, Gành Đá Đĩa",
      "Tham quan Bãi Môn – Mũi Đại Lãnh",
      "Tham quan Hải Vân Quan",
      "Tổ chức Gala đêm cuối với sân khấu, âm thanh, ánh sáng",
      "Nước uống, nón du lịch, bảo hiểm du lịch theo quy định"
    ],
    "notes": "Chương trình có thể hoán đổi thứ tự điểm tham quan nhưng vẫn đảm bảo đầy đủ nội dung. Không bao gồm VAT, chi phí cá nhân, đồ uống ngoài bữa ăn, dịch vụ tự chọn, phụ thu phòng đơn, tiền tip HDV & lái xe (khoảng 30.000 VNĐ/ngày/khách). Phụ thu lễ/tết/cuối tuần từ 10–25% tùy thời điểm. Chính sách trẻ em và chính sách hủy tour áp dụng theo quy định chi tiết của chương trình.",
    "transport": "Xe từ 35 chỗ đến 45 chỗ tùy số lượng khách, bảo đảm xe đời mới, chất lượng cao",
    "accommodation": "Khách sạn tiêu chuẩn 3*, phòng 2 khách; ăn sáng tại khách sạn",
    "meals": "08 bữa chính (07 bữa 150.000 VNĐ/suất, 01 bữa 200.000 VNĐ/suất); ăn sáng tại khách sạn",
    "event_support": "Hỗ trợ đoàn trong suốt hành trình: điều phối lịch trình, tổ chức Gala – giao lưu, hỗ trợ chụp ảnh, kiểm soát an toàn điểm đến, xử lý tình huống phát sinh và đồng hành chăm sóc trải nghiệm theo chuẩn Ruby Wings.",
    "created_at": "2026-01-16T09:07:10.070778Z",
    "last_updated": "2026-01-16T09:07:10.070778Z"
  },
  "tour_029": {
    "tour_id": "tour_029",
    "index": 29,
    "tour_name": "Di sản Huế & Đầm Chuồn – Hoàng hôn phá Tam Giang",
    "location": "Huế – Rú Chá – Đầm Chuồn",
    "region": "Miền Trung",
    "tags": [
      "du_lịch_xanh",
      "1_ngày",
      "thiên_nhiên",
      "trải_nghiệm",
      "tâm_linh",
      "văn_hóa"
    ],
    "duration": "1 ngày",
    "duration_days": 1,
    "price_text": "500.000 – 1.200.000 VNĐ/người (tùy thực đơn & loại xe)",
    "min_price": 500000,
    "max_price": 1200000,
    "avg_price": 850000,
    "embedding_text": "Di sản Huế & Đầm Chuồn – Hoàng hôn phá Tam Giang Hành trình 1 ngày trải nghiệm văn hóa – tâm linh – thiên nhiên: Đại Nội, chùa Từ Hiếu, nhà lưu niệm Bác Hồ, rừng ngập mặn Rú Chá và thưởng thức hải sản trên Đầm Chuồn lúc hoàng hôn. Huế – Rú Chá – Đầm Chuồn Trải nghiệm văn hóa – tâm linh – thiên nhiên – hành trình chậm Đại Nội Huế – Hoàng thành, Tử Cấm Thành Chùa Từ Hiếu hoặc Chùa Thiên Mụ Nhà lưu niệm Bác Hồ Rừng ngập mặn Rú Chá – hệ sinh thái nguyên sinh quý hiếm Đầm Chuồn – dùng cơm tối trên đầm giữa hoàng hôn 07:30–08:00: Đón khách tại điểm hẹn 08:00–10:30: Tham quan Đại Nội 10:30–12:00: Chùa Từ Hiếu / Thiên Mụ 12:00–14:30: Ăn trưa – nghỉ ngơi 14:30–15:30: Nhà lưu niệm Bác Hồ 15:30–16:30: Tham quan Rú Chá 16:30–18:30: Đầm Chuồn – ăn tối trên đầm 18:30: Trở về Huế Hành trình chậm, sâu; phù hợp khách thích văn hóa – thiên nhiên – tâm linh; trang phục lịch sự khi vào chùa. 1 ngày 500.000 – 1.200.000 VNĐ/người (tùy thực đơn & loại xe) Không áp dụng (tour 1 ngày) 1 bữa trưa + 1 bữa tối hải sản trên Đầm Chuồn; nước uống theo chương trình Xe từ 16 chỗ đến 45 chỗ tuỳ số lượng khách, bảo đảm xe đời mới, chất lượng cao Hỗ trợ đoàn trong suốt hành trình: theo sát lịch trình – điều phối giờ giấc – hỗ trợ chụp ảnh – ghi nhận nhu cầu cá nhân; kiểm soát an toàn điểm đến; nhắc nhở sức khỏe – trang phục – di chuyển; hỗ trợ xử lý tình huống phát sinh; đồng hành kết nối tập thể; tối ưu trải nghiệm khách hàng theo chuẩn Ruby Wings.",
    "popularity_score": 0.73,
    "value_score": 0.8,
    "family_friendly": false,
    "senior_friendly": true,
    "corporate_friendly": false,
    "summary": "Hành trình 1 ngày trải nghiệm văn hóa – tâm linh – thiên nhiên: Đại Nội, chùa Từ Hiếu, nhà lưu niệm Bác Hồ, rừng ngập mặn Rú Chá và thưởng thức hải sản trên Đầm Chuồn lúc hoàng hôn.",
    "style": "Trải nghiệm văn hóa – tâm linh – thiên nhiên – hành trình chậm",
    "includes": [
      "Đại Nội Huế – Hoàng thành, Tử Cấm Thành",
      "Chùa Từ Hiếu hoặc Chùa Thiên Mụ",
      "Nhà lưu niệm Bác Hồ",
      "Rừng ngập mặn Rú Chá – hệ sinh thái nguyên sinh quý hiếm",
      "Đầm Chuồn – dùng cơm tối trên đầm giữa hoàng hôn",
      "07:30–08:00: Đón khách tại điểm hẹn",
      "08:00–10:30: Tham quan Đại Nội",
      "10:30–12:00: Chùa Từ Hiếu / Thiên Mụ",
      "12:00–14:30: Ăn trưa – nghỉ ngơi",
      "14:30–15:30: Nhà lưu niệm Bác Hồ",
      "15:30–16:30: Tham quan Rú Chá",
      "16:30–18:30: Đầm Chuồn – ăn tối trên đầm",
      "18:30: Trở về Huế"
    ],
    "notes": "Hành trình chậm, sâu; phù hợp khách thích văn hóa – thiên nhiên – tâm linh; trang phục lịch sự khi vào chùa.",
    "transport": "Xe từ 16 chỗ đến 45 chỗ tuỳ số lượng khách, bảo đảm xe đời mới, chất lượng cao",
    "accommodation": "Không áp dụng (tour 1 ngày)",
    "meals": "1 bữa trưa + 1 bữa tối hải sản trên Đầm Chuồn; nước uống theo chương trình",
    "event_support": "Hỗ trợ đoàn trong suốt hành trình: theo sát lịch trình – điều phối giờ giấc – hỗ trợ chụp ảnh – ghi nhận nhu cầu cá nhân; kiểm soát an toàn điểm đến; nhắc nhở sức khỏe – trang phục – di chuyển; hỗ trợ xử lý tình huống phát sinh; đồng hành kết nối tập thể; tối ưu trải nghiệm khách hàng theo chuẩn Ruby Wings.",
    "created_at": "2026-01-16T09:07:10.070778Z",
    "last_updated": "2026-01-16T09:07:10.070778Z"
  },
  "tour_030": {
    "tour_id": "tour_030",
    "index": 30,
    "tour_name": "Văn hoá tổ chức & Hành vi chuẩn Ruby Wings (Nội dung văn hoá – không phải tour)",
    "location": "Nội bộ Ruby Wings (Không áp dụng địa điểm du lịch)",
    "region": "Miền Trung",
    "tags": [
      "thiền",
      "team_building",
      "tâm_linh",
      "du_lịch_xanh"
    ],
    "duration": "Sẽ cập nhật sau",
    "duration_days": 1,
    "price_text": "Sẽ cập nhật sau",
    "min_price": 1000000,
    "max_price": 2000000,
    "avg_price": 1500000,
    "embedding_text": "Văn hoá tổ chức & Hành vi chuẩn Ruby Wings (Nội dung văn hoá – không phải tour) Khối tiêu chuẩn văn hoá – giao tiếp – phản hồi – báo cáo – phối hợp – phong cách làm việc trong Ruby Wings. Đây là dữ liệu văn hoá doanh nghiệp, không phải chương trình tour. Nội bộ Ruby Wings (Không áp dụng địa điểm du lịch) Văn hoá nội bộ theo định hướng nhân văn – chuẩn mực – có chiều sâu. Cách giao tiếp rõ ràng, tôn trọng, không phán xét con người mà tập trung vào hành vi; phản hồi dựa trên quan sát & mục tiêu chung; làm việc khoa học – có ý thức – hiểu bối cảnh. Phong cách kết hợp chuyên nghiệp hiện đại và tư duy tỉnh thức dựa trên thiền – khí công – giá trị sống. Bộ nguyên tắc giao tiếp: Rõ ràng – chính xác – có cấu trúc; tôn trọng – chân thành – cầu thị; phản hồi trong vòng 24 giờ; chọn đúng kênh giao tiếp (trực tiếp – nhóm – email – form). Bộ tiêu chuẩn phản hồi: Quan sát – mục tiêu chung; không công kích cá nhân; phản hồi đi kèm giải pháp; tiếp nhận phản hồi với thái độ lắng nghe – không biện minh. Quy trình báo cáo – phối hợp: Báo cáo đúng hạn, đúng mẫu; có tóm tắt – nguyên nhân – giải pháp; phối hợp liên ngành qua Notion/Trello/Drive/Form. Phong cách làm việc Ruby Wings: Chủ động – tỉnh táo – chuẩn mực – chân thành – có chiều sâu; kiểm soát cảm xúc; làm việc dựa trên giá trị thật. Hệ thống kỳ vọng hành vi: Giao tiếp chuẩn; phản hồi tích cực; báo cáo đúng hạn; duy trì năng lượng tích cực; hành động nhân văn. Bộ tinh thần văn hoá: Chuẩn mực – Chân thành – Có chiều sâu được áp dụng đồng bộ trong Travel – Learn – Stay – Auto. Nội dung này thuộc hệ thống văn hoá nội bộ Ruby Wings, không phải tour du lịch. Dùng để đào tạo nhân sự, xây dựng văn hoá và đồng bộ hành vi trong toàn hệ sinh thái. Sẽ cập nhật sau Sẽ cập nhật sau Sẽ cập nhật sau Sẽ cập nhật sau Sẽ cập nhật sau Nội dung văn hoá – không áp dụng sự kiện tour",
    "popularity_score": 0.72,
    "value_score": 0.6,
    "family_friendly": false,
    "senior_friendly": true,
    "corporate_friendly": true,
    "summary": "Khối tiêu chuẩn văn hoá – giao tiếp – phản hồi – báo cáo – phối hợp – phong cách làm việc trong Ruby Wings. Đây là dữ liệu văn hoá doanh nghiệp, không phải chương trình tour.",
    "style": "Văn hoá nội bộ theo định hướng nhân văn – chuẩn mực – có chiều sâu. Cách giao tiếp rõ ràng, tôn trọng, không phán xét con người mà tập trung vào hành vi; phản hồi dựa trên quan sát & mục tiêu chung; làm việc khoa học – có ý thức – hiểu bối cảnh. Phong cách kết hợp chuyên nghiệp hiện đại và tư duy tỉnh thức dựa trên thiền – khí công – giá trị sống.",
    "includes": [
      "Bộ nguyên tắc giao tiếp: Rõ ràng – chính xác – có cấu trúc; tôn trọng – chân thành – cầu thị; phản hồi trong vòng 24 giờ; chọn đúng kênh giao tiếp (trực tiếp – nhóm – email – form).",
      "Bộ tiêu chuẩn phản hồi: Quan sát – mục tiêu chung; không công kích cá nhân; phản hồi đi kèm giải pháp; tiếp nhận phản hồi với thái độ lắng nghe – không biện minh.",
      "Quy trình báo cáo – phối hợp: Báo cáo đúng hạn, đúng mẫu; có tóm tắt – nguyên nhân – giải pháp; phối hợp liên ngành qua Notion/Trello/Drive/Form.",
      "Phong cách làm việc Ruby Wings: Chủ động – tỉnh táo – chuẩn mực – chân thành – có chiều sâu; kiểm soát cảm xúc; làm việc dựa trên giá trị thật.",
      "Hệ thống kỳ vọng hành vi: Giao tiếp chuẩn; phản hồi tích cực; báo cáo đúng hạn; duy trì năng lượng tích cực; hành động nhân văn.",
      "Bộ tinh thần văn hoá: Chuẩn mực – Chân thành – Có chiều sâu được áp dụng đồng bộ trong Travel – Learn – Stay – Auto."
    ],
    "notes": "Nội dung này thuộc hệ thống văn hoá nội bộ Ruby Wings, không phải tour du lịch. Dùng để đào tạo nhân sự, xây dựng văn hoá và đồng bộ hành vi trong toàn hệ sinh thái.",
    "transport": "Sẽ cập nhật sau",
    "accommodation": "Sẽ cập nhật sau",
    "meals": "Sẽ cập nhật sau",
    "event_support": "Nội dung văn hoá – không áp dụng sự kiện tour",
    "created_at": "2026-01-16T09:07:10.070778Z",
    "last_updated": "2026-01-16T09:07:10.070778Z"
  },
  "tour_031": {
    "tour_id": "tour_031",
    "index": 31,
    "tour_name": "Giới thiệu Ruby Wings – Lịch sử, Triết lý, Tầm nhìn & Hệ sinh thái (Nội dung văn hoá – không phải tour)",
    "location": "148 Trương Gia Mô, Vỹ Dạ, TP. Huế",
    "region": "Miền Trung",
    "tags": [
      "thiền",
      "du_lịch_xanh",
      "retreat",
      "thiên_nhiên",
      "trải_nghiệm",
      "tâm_linh",
      "lịch_sử",
      "team_building",
      "văn_hóa"
    ],
    "duration": "Không áp dụng (Nội dung văn hoá)",
    "duration_days": 1,
    "price_text": "Không áp dụng",
    "min_price": 500000,
    "max_price": 1500000,
    "avg_price": 1000000,
    "embedding_text": "Giới thiệu Ruby Wings – Lịch sử, Triết lý, Tầm nhìn & Hệ sinh thái (Nội dung văn hoá – không phải tour) Khối thông tin tổng hợp về Ruby Wings, bao gồm nguồn gốc hình thành, triết lý nhân văn, hệ sinh thái phát triển và câu chuyện của Giám đốc Lương Tiến Sỹ – người sáng lập, người hồi sinh từ biến cố bệnh tật năm 2015 và mang tinh thần thiền – khí công trở thành cốt lõi của tổ chức. Đây là nội dung văn hoá thương hiệu, không phải chương trình tour. 148 Trương Gia Mô, Vỹ Dạ, TP. Huế Phong cách thương hiệu Ruby Wings mang chiều sâu cảm xúc, được định hình mạnh mẽ bởi Giám đốc Lương Tiến Sỹ – người đã trải nghiệm hành trình chữa lành thông qua thiền – khí công. Tư duy sống chuẩn mực – chân thành – có chiều sâu thấm vào cách tổ chức hoạt động: thiết kế hành trình du lịch, đào tạo nội tâm, quy trình vận hành và tương tác với khách hàng. Ngôn ngữ truyền tải nhẹ nhàng, nhân văn, hướng đến sự tỉnh thức, sự trở về và sự cân bằng của mỗi con người. Thông tin doanh nghiệp: Ruby Wings Travel, mã số thuế, địa chỉ, kênh liên hệ, cộng đồng. Câu chuyện sáng lập của Giám đốc Lương Tiến Sỹ: vượt bệnh, hồi sinh bằng thiền – khí công, từ đó định hình Ruby Wings như một hành trình nhân văn. Triết lý logo: bốn cánh xanh lá (Thân – Tâm – Thiên nhiên – Niềm tin), viên ruby hồng (Trái tim – sự chữa lành), vòng tròn kết nối (tái sinh). Hệ sinh thái Ruby: Travel (du lịch chữa lành), Learn (giáo dục nội tâm), Stay (lưu trú xanh), Auto (di chuyển cân bằng). Sứ mệnh: lan tỏa giá trị sống chuẩn mực – chân thành – có chiều sâu. Tầm nhìn 2030: trở thành đơn vị dẫn đầu về du lịch cảm xúc & phát triển con người tại miền Trung. Giá trị cốt lõi: Chuẩn mực – Chân thành – Có chiều sâu, áp dụng trong dịch vụ – đào tạo – vận hành. Tinh thần 'gieo hạt': xây triết lý và văn hoá trước sản phẩm, kết nối cộng đồng bản địa. Bộ câu hỏi giúp chatbot trả lời khách tìm hiểu về thương hiệu Ruby Wings. Đây là nội dung văn hoá – thương hiệu, không phải sản phẩm tour. Form được tái sử dụng để đồng bộ dữ liệu chatbot. Không áp dụng (Nội dung văn hoá) Không áp dụng Không áp dụng Không áp dụng Không áp dụng Không áp dụng cho tour – đây là nội dung giới thiệu công ty",
    "popularity_score": 0.71,
    "value_score": 0.6,
    "family_friendly": false,
    "senior_friendly": true,
    "corporate_friendly": true,
    "summary": "Khối thông tin tổng hợp về Ruby Wings, bao gồm nguồn gốc hình thành, triết lý nhân văn, hệ sinh thái phát triển và câu chuyện của Giám đốc Lương Tiến Sỹ – người sáng lập, người hồi sinh từ biến cố bệnh tật năm 2015 và mang tinh thần thiền – khí công trở thành cốt lõi của tổ chức. Đây là nội dung văn hoá thương hiệu, không phải chương trình tour.",
    "style": "Phong cách thương hiệu Ruby Wings mang chiều sâu cảm xúc, được định hình mạnh mẽ bởi Giám đốc Lương Tiến Sỹ – người đã trải nghiệm hành trình chữa lành thông qua thiền – khí công. Tư duy sống chuẩn mực – chân thành – có chiều sâu thấm vào cách tổ chức hoạt động: thiết kế hành trình du lịch, đào tạo nội tâm, quy trình vận hành và tương tác với khách hàng. Ngôn ngữ truyền tải nhẹ nhàng, nhân văn, hướng đến sự tỉnh thức, sự trở về và sự cân bằng của mỗi con người.",
    "includes": [
      "Thông tin doanh nghiệp: Ruby Wings Travel, mã số thuế, địa chỉ, kênh liên hệ, cộng đồng.",
      "Câu chuyện sáng lập của Giám đốc Lương Tiến Sỹ: vượt bệnh, hồi sinh bằng thiền – khí công, từ đó định hình Ruby Wings như một hành trình nhân văn.",
      "Triết lý logo: bốn cánh xanh lá (Thân – Tâm – Thiên nhiên – Niềm tin), viên ruby hồng (Trái tim – sự chữa lành), vòng tròn kết nối (tái sinh).",
      "Hệ sinh thái Ruby: Travel (du lịch chữa lành), Learn (giáo dục nội tâm), Stay (lưu trú xanh), Auto (di chuyển cân bằng).",
      "Sứ mệnh: lan tỏa giá trị sống chuẩn mực – chân thành – có chiều sâu.",
      "Tầm nhìn 2030: trở thành đơn vị dẫn đầu về du lịch cảm xúc & phát triển con người tại miền Trung.",
      "Giá trị cốt lõi: Chuẩn mực – Chân thành – Có chiều sâu, áp dụng trong dịch vụ – đào tạo – vận hành.",
      "Tinh thần 'gieo hạt': xây triết lý và văn hoá trước sản phẩm, kết nối cộng đồng bản địa.",
      "Bộ câu hỏi giúp chatbot trả lời khách tìm hiểu về thương hiệu Ruby Wings."
    ],
    "notes": "Đây là nội dung văn hoá – thương hiệu, không phải sản phẩm tour. Form được tái sử dụng để đồng bộ dữ liệu chatbot.",
    "transport": "Không áp dụng",
    "accommodation": "Không áp dụng",
    "meals": "Không áp dụng",
    "event_support": "Không áp dụng cho tour – đây là nội dung giới thiệu công ty",
    "created_at": "2026-01-16T09:07:10.070778Z",
    "last_updated": "2026-01-16T09:07:10.070778Z"
  }
}